Workbook

Sheet 04 — Scenario comparison — Base
A1: 04 — Scenario comparison — Base is Main Scenario
A2: TicketStub — neatHack Business Plan — 2026-10-11 · Main Scenario
A4: Variable / dimension | B4: Value | C4: Value > TicketStub — Conservative | D4: Value > TicketStub — Growth
A5: TS Monthly visits | B5: =10000 -> 10000 | C5: =5000 -> 5000 | D5: =25000 -> 25000
A6: TS Studio start rate | B6: =0.1 -> 0.1 | C6: ='04 — Scenario comparison — Base'!B6 -> 0.1 | D6: ='04 — Scenario comparison — Base'!B6 -> 0.1
A7: TS Paid conversion of visits | B7: =0.02 -> 0.02 | C7: =0.01 -> 0.01 | D7: =0.04 -> 0.04
A8: TS Images per start | B8: ='01 — Editable assumptions — USD'!B8+'01 — Editable assumptions — USD'!B9 -> 2 | C8: ='Model inputs'!B69+'Model inputs'!B28 -> 4 | D8: ='Model inputs'!B68+'Model inputs'!B27 -> 1.5
A9: TS Chats per start | B9: =4 -> 4 | C9: =8 -> 8 | D9: =3 -> 3
A10: TS Digital orders | B10: ='04 — Scenario comparison — Base'!B5*'04 — Scenario comparison — Base'!B7 -> 200 | C10: ='04 — Scenario comparison — Base'!C5*'04 — Scenario comparison — Base'!C7 -> 50 | D10: ='04 — Scenario comparison — Base'!D5*'04 — Scenario comparison — Base'!D7 -> 1000
A11: TS Studio starts | B11: ='04 — Scenario comparison — Base'!B5*'04 — Scenario comparison — Base'!B6 -> 1000 | C11: ='04 — Scenario comparison — Base'!C5*'04 — Scenario comparison — Base'!C6 -> 500 | D11: ='04 — Scenario comparison — Base'!D5*'04 — Scenario comparison — Base'!D6 -> 2500
A12: TS Monthly digital revenue | B12: ='04 — Scenario comparison — Base'!B10*'01 — Editable assumptions — USD'!B11 -> 1800 | C12: ='04 — Scenario comparison — Base'!C10*'Model inputs'!B24 -> 450 | D12: ='04 — Scenario comparison — Base'!D10*'Model inputs'!B23 -> 9000
A13: TS Monthly AI spend | B13: ='04 — Scenario comparison — Base'!B11*'03 — Digital unit economics and'!B9 -> 308.99 | C13: ='04 — Scenario comparison — Base'!C11*'Model inputs'!B8 -> 301.57 | D13: ='04 — Scenario comparison — Base'!D11*'Model inputs'!B7 -> 588.63125
A14: TS AI cost per paid order | B14: =IFERROR('04 — Scenario comparison — Base'!B13/'04 — Scenario comparison — Base'!B10,"") -> 1.54495 | C14: =IFERROR('04 — Scenario comparison — Base'!C13/'04 — Scenario comparison — Base'!C10,"") -> 6.0314 | D14: =IFERROR('04 — Scenario comparison — Base'!D13/'04 — Scenario comparison — Base'!D10,"") -> 0.58863125
A15: TS Digital contribution per order | B15: ='01 — Editable assumptions — USD'!B11-'03 — Digital unit economics and'!B15-'03 — Digital unit economics and'!B16-'03 — Digital unit economics and'!B17-'04 — Scenario comparison — Base'!B14 -> 6.51405 | C15: ='Model inputs'!B24-'Model inputs'!B86-'Model inputs'!B110-'Model inputs'!B113-'04 — Scenario comparison — Base'!C14 -> 2.0276 | D15: ='Model inputs'!B23-'Model inputs'!B85-'Model inputs'!B109-'Model inputs'!B112-'04 — Scenario comparison — Base'!D14 -> 7.4703688
A16: TS Digital contribution margin | B16: =IFERROR('04 — Scenario comparison — Base'!B15/'01 — Editable assumptions — USD'!B11,"") -> 0.72378333 | C16: =IFERROR('04 — Scenario comparison — Base'!C15/'Model inputs'!B24,"") -> 0.22528889 | D16: =IFERROR('04 — Scenario comparison — Base'!D15/'Model inputs'!B23,"") -> 0.83004097
A17: TS Fixed monthly budget | B17: =SUM('02 — Fixed monthly budgets — es'!B5,'02 — Fixed monthly budgets — es'!B6,'02 — Fixed monthly budgets — es'!B7,'02 — Fixed monthly budgets — es'!B8,'02 — Fixed monthly budgets — es'!B9,'02 — Fixed monthly budgets — es'!B10,'02 — Fixed monthly budgets — es'!B11) -> 300 | C17: =SUM('Model inputs'!B46,'Model inputs'!B47,'Model inputs'!B48,'Model inputs'!B49,'Model inputs'!B50,'Model inputs'!B51,'Model inputs'!B52) -> 150 | D17: =SUM('Model inputs'!B38,'Model inputs'!B39,'Model inputs'!B40,'Model inputs'!B41,'Model inputs'!B42,'Model inputs'!B43,'Model inputs'!B44) -> 900
A18: TS Monthly marketing | B18: =300 -> 300 | C18: =100 -> 100 | D18: =1500 -> 1500
A19: TS Monthly operating profit bootstrap | B19: ='03 — Digital unit economics and'!B20-'04 — Scenario comparison — Base'!B17-'04 — Scenario comparison — Base'!B18-'01 — Editable assumptions — USD'!B36 -> 702.81 | C19: ='Model inputs'!B77-'04 — Scenario comparison — Base'!C17-'04 — Scenario comparison — Base'!C18-'Model inputs'!B58 -> -148.62 | D19: ='Model inputs'!B76-'04 — Scenario comparison — Base'!D17-'04 — Scenario comparison — Base'!D18-'Model inputs'!B57 -> 5070.3688
A20: TS Monthly operating profit founder | B20: ='03 — Digital unit economics and'!B20-'04 — Scenario comparison — Base'!B17-'04 — Scenario comparison — Base'!B18-'01 — Editable assumptions — USD'!B37 -> -2297.19 | C20: ='Model inputs'!B77-'04 — Scenario comparison — Base'!C17-'04 — Scenario comparison — Base'!C18-'Model inputs'!B62 -> -3148.62 | D20: ='Model inputs'!B76-'04 — Scenario comparison — Base'!D17-'04 — Scenario comparison — Base'!D18-'Model inputs'!B61 -> 2070.3688
A21: TS Break-even orders bootstrap | B21: =IF(IF(IF(ISERROR('04 — Scenario comparison — Base'!B15>0),'04 — Scenario comparison — Base'!B15>0,IF('04 — Scenario comparison — Base'!B15="","",'04 — Scenario comparison — Base'!B15>0))="",FALSE,IF(ISERROR('04 — Scenario comparison — Base'!B15>0),'04 — Scenario comparison — Base'!B15>0,IF('04 — Scenario comparison — Base'!B15="","",'04 — Scenario comparison — Base'!B15>0))),CEILING(('04 — Scenario comparison — Base'!B17+'04 — Scenario comparison — Base'!B18+'01 — Editable assumptions — USD'!B36)/'04 — Scenario comparison — Base'!B15,1),"") -> 93 | C21: =IF(IF(IF(ISERROR('04 — Scenario comparison — Base'!C15>0),'04 — Scenario comparison — Base'!C15>0,IF('04 — Scenario comparison — Base'!C15="","",'04 — Scenario comparison — Base'!C15>0))="",FALSE,IF(ISERROR('04 — Scenario comparison — Base'!C15>0),'04 — Scenario comparison — Base'!C15>0,IF('04 — Scenario comparison — Base'!C15="","",'04 — Scenario comparison — Base'!C15>0))),CEILING(('04 — Scenario comparison — Base'!C17+'04 — Scenario comparison — Base'!C18+'Model inputs'!B58)/'04 — Scenario comparison — Base'!C15,1),"") -> 124 | D21: =IF(IF(IF(ISERROR('04 — Scenario comparison — Base'!D15>0),'04 — Scenario comparison — Base'!D15>0,IF('04 — Scenario comparison — Base'!D15="","",'04 — Scenario comparison — Base'!D15>0))="",FALSE,IF(ISERROR('04 — Scenario comparison — Base'!D15>0),'04 — Scenario comparison — Base'!D15>0,IF('04 — Scenario comparison — Base'!D15="","",'04 — Scenario comparison — Base'!D15>0))),CEILING(('04 — Scenario comparison — Base'!D17+'04 — Scenario comparison — Base'!D18+'Model inputs'!B57)/'04 — Scenario comparison — Base'!D15,1),"") -> 322
A22: TS Break-even orders founder | B22: =IF(IF(IF(ISERROR('04 — Scenario comparison — Base'!B15>0),'04 — Scenario comparison — Base'!B15>0,IF('04 — Scenario comparison — Base'!B15="","",'04 — Scenario comparison — Base'!B15>0))="",FALSE,IF(ISERROR('04 — Scenario comparison — Base'!B15>0),'04 — Scenario comparison — Base'!B15>0,IF('04 — Scenario comparison — Base'!B15="","",'04 — Scenario comparison — Base'!B15>0))),CEILING(('04 — Scenario comparison — Base'!B17+'04 — Scenario comparison — Base'!B18+'01 — Editable assumptions — USD'!B37)/'04 — Scenario comparison — Base'!B15,1),"") -> 553 | C22: =IF(IF(IF(ISERROR('04 — Scenario comparison — Base'!C15>0),'04 — Scenario comparison — Base'!C15>0,IF('04 — Scenario comparison — Base'!C15="","",'04 — Scenario comparison — Base'!C15>0))="",FALSE,IF(ISERROR('04 — Scenario comparison — Base'!C15>0),'04 — Scenario comparison — Base'!C15>0,IF('04 — Scenario comparison — Base'!C15="","",'04 — Scenario comparison — Base'!C15>0))),CEILING(('04 — Scenario comparison — Base'!C17+'04 — Scenario comparison — Base'!C18+'Model inputs'!B62)/'04 — Scenario comparison — Base'!C15,1),"") -> 1603 | D22: =IF(IF(IF(ISERROR('04 — Scenario comparison — Base'!D15>0),'04 — Scenario comparison — Base'!D15>0,IF('04 — Scenario comparison — Base'!D15="","",'04 — Scenario comparison — Base'!D15>0))="",FALSE,IF(ISERROR('04 — Scenario comparison — Base'!D15>0),'04 — Scenario comparison — Base'!D15>0,IF('04 — Scenario comparison — Base'!D15="","",'04 — Scenario comparison — Base'!D15>0))),CEILING(('04 — Scenario comparison — Base'!D17+'04 — Scenario comparison — Base'!D18+'Model inputs'!B61)/'04 — Scenario comparison — Base'!D15,1),"") -> 723
A23: TS Launch reserve | B23: ='01 — Editable assumptions — USD'!B38+'01 — Editable assumptions — USD'!B39/'01 — Editable assumptions — USD'!B40*'03 — Digital unit economics and'!B21 -> 616.011 | C23: ='Model inputs'!B18+'Model inputs'!B89/'Model inputs'!B15*'Model inputs'!B83 -> 581.34467 | D23: ='Model inputs'!B17+'Model inputs'!B88/'Model inputs'!B14*'Model inputs'!B82 -> 856.91396
A24: TS Hypothetical opening cash | B24: =1000 -> 1000 | C24: ='04 — Scenario comparison — Base'!B24 -> 1000 | D24: ='04 — Scenario comparison — Base'!B24 -> 1000
A25: TS Launch status | B25: =IF(IF(IF(ISERROR('04 — Scenario comparison — Base'!B24<'04 — Scenario comparison — Base'!B23),'04 — Scenario comparison — Base'!B24<'04 — Scenario comparison — Base'!B23,IF(OR('04 — Scenario comparison — Base'!B24="",'04 — Scenario comparison — Base'!B23=""),"",'04 — Scenario comparison — Base'!B24<'04 — Scenario comparison — Base'!B23))="",FALSE,IF(ISERROR('04 — Scenario comparison — Base'!B24<'04 — Scenario comparison — Base'!B23),'04 — Scenario comparison — Base'!B24<'04 — Scenario comparison — Base'!B23,IF(OR('04 — Scenario comparison — Base'!B24="",'04 — Scenario comparison — Base'!B23=""),"",'04 — Scenario comparison — Base'!B24<'04 — Scenario comparison — Base'!B23))),"UNFUNDED LAUNCH","Reserve funded; ramp still required") -> Reserve funded; ramp still required | C25: =IF(IF(IF(ISERROR('04 — Scenario comparison — Base'!C24<'04 — Scenario comparison — Base'!C23),'04 — Scenario comparison — Base'!C24<'04 — Scenario comparison — Base'!C23,IF(OR('04 — Scenario comparison — Base'!C24="",'04 — Scenario comparison — Base'!C23=""),"",'04 — Scenario comparison — Base'!C24<'04 — Scenario comparison — Base'!C23))="",FALSE,IF(ISERROR('04 — Scenario comparison — Base'!C24<'04 — Scenario comparison — Base'!C23),'04 — Scenario comparison — Base'!C24<'04 — Scenario comparison — Base'!C23,IF(OR('04 — Scenario comparison — Base'!C24="",'04 — Scenario comparison — Base'!C23=""),"",'04 — Scenario comparison — Base'!C24<'04 — Scenario comparison — Base'!C23))),"UNFUNDED LAUNCH","Reserve funded; ramp still required") -> Reserve funded; ramp still required | D25: =IF(IF(IF(ISERROR('04 — Scenario comparison — Base'!D24<'04 — Scenario comparison — Base'!D23),'04 — Scenario comparison — Base'!D24<'04 — Scenario comparison — Base'!D23,IF(OR('04 — Scenario comparison — Base'!D24="",'04 — Scenario comparison — Base'!D23=""),"",'04 — Scenario comparison — Base'!D24<'04 — Scenario comparison — Base'!D23))="",FALSE,IF(ISERROR('04 — Scenario comparison — Base'!D24<'04 — Scenario comparison — Base'!D23),'04 — Scenario comparison — Base'!D24<'04 — Scenario comparison — Base'!D23,IF(OR('04 — Scenario comparison — Base'!D24="",'04 — Scenario comparison — Base'!D23=""),"",'04 — Scenario comparison — Base'!D24<'04 — Scenario comparison — Base'!D23))),"UNFUNDED LAUNCH","Reserve funded; ramp still required") -> Reserve funded; ramp still required
A26: TS Zero cash launch status | B26: =IF(IF(IF(ISERROR('01 — Editable assumptions — USD'!B34<'04 — Scenario comparison — Base'!B23),'01 — Editable assumptions — USD'!B34<'04 — Scenario comparison — Base'!B23,IF(OR('01 — Editable assumptions — USD'!B34="",'04 — Scenario comparison — Base'!B23=""),"",'01 — Editable assumptions — USD'!B34<'04 — Scenario comparison — Base'!B23))="",FALSE,IF(ISERROR('01 — Editable assumptions — USD'!B34<'04 — Scenario comparison — Base'!B23),'01 — Editable assumptions — USD'!B34<'04 — Scenario comparison — Base'!B23,IF(OR('01 — Editable assumptions — USD'!B34="",'04 — Scenario comparison — Base'!B23=""),"",'01 — Editable assumptions — USD'!B34<'04 — Scenario comparison — Base'!B23))),"UNFUNDED LAUNCH","Reserve funded; ramp still required") -> UNFUNDED LAUNCH | C26: =IF(IF(IF(ISERROR('Model inputs'!B12<'04 — Scenario comparison — Base'!C23),'Model inputs'!B12<'04 — Scenario comparison — Base'!C23,IF(OR('Model inputs'!B12="",'04 — Scenario comparison — Base'!C23=""),"",'Model inputs'!B12<'04 — Scenario comparison — Base'!C23))="",FALSE,IF(ISERROR('Model inputs'!B12<'04 — Scenario comparison — Base'!C23),'Model inputs'!B12<'04 — Scenario comparison — Base'!C23,IF(OR('Model inputs'!B12="",'04 — Scenario comparison — Base'!C23=""),"",'Model inputs'!B12<'04 — Scenario comparison — Base'!C23))),"UNFUNDED LAUNCH","Reserve funded; ramp still required") -> UNFUNDED LAUNCH | D26: =IF(IF(IF(ISERROR('Model inputs'!B11<'04 — Scenario comparison — Base'!D23),'Model inputs'!B11<'04 — Scenario comparison — Base'!D23,IF(OR('Model inputs'!B11="",'04 — Scenario comparison — Base'!D23=""),"",'Model inputs'!B11<'04 — Scenario comparison — Base'!D23))="",FALSE,IF(ISERROR('Model inputs'!B11<'04 — Scenario comparison — Base'!D23),'Model inputs'!B11<'04 — Scenario comparison — Base'!D23,IF(OR('Model inputs'!B11="",'04 — Scenario comparison — Base'!D23=""),"",'Model inputs'!B11<'04 — Scenario comparison — Base'!D23))),"UNFUNDED LAUNCH","Reserve funded; ramp still required") -> UNFUNDED LAUNCH
A27: TS Runway months bootstrap | B27: =IF(IF(IF(ISERROR('03 — Digital unit economics and'!B29>0),'03 — Digital unit economics and'!B29>0,IF('03 — Digital unit economics and'!B29="","",'03 — Digital unit economics and'!B29>0))="",FALSE,IF(ISERROR('03 — Digital unit economics and'!B29>0),'03 — Digital unit economics and'!B29>0,IF('03 — Digital unit economics and'!B29="","",'03 — Digital unit economics and'!B29>0))),MAX(0,'04 — Scenario comparison — Base'!B24-'04 — Scenario comparison — Base'!B23)/'03 — Digital unit economics and'!B29,"") | C27: =IF(IF(IF(ISERROR('Model inputs'!B73>0),'Model inputs'!B73>0,IF('Model inputs'!B73="","",'Model inputs'!B73>0))="",FALSE,IF(ISERROR('Model inputs'!B73>0),'Model inputs'!B73>0,IF('Model inputs'!B73="","",'Model inputs'!B73>0))),MAX(0,'04 — Scenario comparison — Base'!C24-'04 — Scenario comparison — Base'!C23)/'Model inputs'!B73,"") -> 2.8169515 | D27: =IF(IF(IF(ISERROR('Model inputs'!B72>0),'Model inputs'!B72>0,IF('Model inputs'!B72="","",'Model inputs'!B72>0))="",FALSE,IF(ISERROR('Model inputs'!B72>0),'Model inputs'!B72>0,IF('Model inputs'!B72="","",'Model inputs'!B72>0))),MAX(0,'04 — Scenario comparison — Base'!D24-'04 — Scenario comparison — Base'!D23)/'Model inputs'!B72,"")
A28: TS Runway months founder | B28: =IF(IF(IF(ISERROR('03 — Digital unit economics and'!B30>0),'03 — Digital unit economics and'!B30>0,IF('03 — Digital unit economics and'!B30="","",'03 — Digital unit economics and'!B30>0))="",FALSE,IF(ISERROR('03 — Digital unit economics and'!B30>0),'03 — Digital unit economics and'!B30>0,IF('03 — Digital unit economics and'!B30="","",'03 — Digital unit economics and'!B30>0))),MAX(0,'04 — Scenario comparison — Base'!B24-'04 — Scenario comparison — Base'!B23)/'03 — Digital unit economics and'!B30,"") -> 0.16715596 | C28: =IF(IF(IF(ISERROR('Model inputs'!B75>0),'Model inputs'!B75>0,IF('Model inputs'!B75="","",'Model inputs'!B75>0))="",FALSE,IF(ISERROR('Model inputs'!B75>0),'Model inputs'!B75>0,IF('Model inputs'!B75="","",'Model inputs'!B75>0))),MAX(0,'04 — Scenario comparison — Base'!C24-'04 — Scenario comparison — Base'!C23)/'Model inputs'!B75,"") -> 0.13296471 | D28: =IF(IF(IF(ISERROR('Model inputs'!B74>0),'Model inputs'!B74>0,IF('Model inputs'!B74="","",'Model inputs'!B74>0))="",FALSE,IF(ISERROR('Model inputs'!B74>0),'Model inputs'!B74>0,IF('Model inputs'!B74="","",'Model inputs'!B74>0))),MAX(0,'04 — Scenario comparison — Base'!D24-'04 — Scenario comparison — Base'!D23)/'Model inputs'!B74,"")
A29: TS Runway at funded bootstrap | B29: =IF(IF(IF(ISERROR('03 — Digital unit economics and'!B29>0),'03 — Digital unit economics and'!B29>0,IF('03 — Digital unit economics and'!B29="","",'03 — Digital unit economics and'!B29>0))="",FALSE,IF(ISERROR('03 — Digital unit economics and'!B29>0),'03 — Digital unit economics and'!B29>0,IF('03 — Digital unit economics and'!B29="","",'03 — Digital unit economics and'!B29>0))),MAX(0,'01 — Editable assumptions — USD'!B35-'04 — Scenario comparison — Base'!B23)/'03 — Digital unit economics and'!B29,"") | C29: =IF(IF(IF(ISERROR('Model inputs'!B73>0),'Model inputs'!B73>0,IF('Model inputs'!B73="","",'Model inputs'!B73>0))="",FALSE,IF(ISERROR('Model inputs'!B73>0),'Model inputs'!B73>0,IF('Model inputs'!B73="","",'Model inputs'!B73>0))),MAX(0,'Model inputs'!B10-'04 — Scenario comparison — Base'!C23)/'Model inputs'!B73,"") -> 29.73123 | D29: =IF(IF(IF(ISERROR('Model inputs'!B72>0),'Model inputs'!B72>0,IF('Model inputs'!B72="","",'Model inputs'!B72>0))="",FALSE,IF(ISERROR('Model inputs'!B72>0),'Model inputs'!B72>0,IF('Model inputs'!B72="","",'Model inputs'!B72>0))),MAX(0,'Model inputs'!B9-'04 — Scenario comparison — Base'!D23)/'Model inputs'!B72,"")
A30: TS Runway at funded founder | B30: =IF(IF(IF(ISERROR('03 — Digital unit economics and'!B30>0),'03 — Digital unit economics and'!B30>0,IF('03 — Digital unit economics and'!B30="","",'03 — Digital unit economics and'!B30>0))="",FALSE,IF(ISERROR('03 — Digital unit economics and'!B30>0),'03 — Digital unit economics and'!B30>0,IF('03 — Digital unit economics and'!B30="","",'03 — Digital unit economics and'!B30>0))),MAX(0,'01 — Editable assumptions — USD'!B35-'04 — Scenario comparison — Base'!B23)/'03 — Digital unit economics and'!B30,"") -> 1.9084138 | C30: =IF(IF(IF(ISERROR('Model inputs'!B75>0),'Model inputs'!B75>0,IF('Model inputs'!B75="","",'Model inputs'!B75>0))="",FALSE,IF(ISERROR('Model inputs'!B75>0),'Model inputs'!B75>0,IF('Model inputs'!B75="","",'Model inputs'!B75>0))),MAX(0,'Model inputs'!B10-'04 — Scenario comparison — Base'!C23)/'Model inputs'!B75,"") -> 1.4033625 | D30: =IF(IF(IF(ISERROR('Model inputs'!B74>0),'Model inputs'!B74>0,IF('Model inputs'!B74="","",'Model inputs'!B74>0))="",FALSE,IF(ISERROR('Model inputs'!B74>0),'Model inputs'!B74>0,IF('Model inputs'!B74="","",'Model inputs'!B74>0))),MAX(0,'Model inputs'!B9-'04 — Scenario comparison — Base'!D23)/'Model inputs'!B74,"")
A31: TS Bootstrap runway interpretation | B31: =IF(IF(IF(ISERROR('04 — Scenario comparison — Base'!B24<'04 — Scenario comparison — Base'!B23),'04 — Scenario comparison — Base'!B24<'04 — Scenario comparison — Base'!B23,IF(OR('04 — Scenario comparison — Base'!B24="",'04 — Scenario comparison — Base'!B23=""),"",'04 — Scenario comparison — Base'!B24<'04 — Scenario comparison — Base'!B23))="",FALSE,IF(ISERROR('04 — Scenario comparison — Base'!B24<'04 — Scenario comparison — Base'!B23),'04 — Scenario comparison — Base'!B24<'04 — Scenario comparison — Base'!B23,IF(OR('04 — Scenario comparison — Base'!B24="",'04 — Scenario comparison — Base'!B23=""),"",'04 — Scenario comparison — Base'!B24<'04 — Scenario comparison — Base'!B23))),"UNFUNDED LAUNCH",IF(IF(IF(ISERROR('03 — Digital unit economics and'!B29=0),'03 — Digital unit economics and'!B29=0,IF('03 — Digital unit economics and'!B29="","",'03 — Digital unit economics and'!B29=0))="",FALSE,IF(ISERROR('03 — Digital unit economics and'!B29=0),'03 — Digital unit economics and'!B29=0,IF('03 — Digital unit economics and'!B29="","",'03 — Digital unit economics and'!B29=0))),"Cash-positive steady state; not guaranteed runway","Finite burn runway; steady-state assumption")) -> Cash-positive steady state; not guaranteed runway | C31: =IF(IF(IF(ISERROR('04 — Scenario comparison — Base'!C24<'04 — Scenario comparison — Base'!C23),'04 — Scenario comparison — Base'!C24<'04 — Scenario comparison — Base'!C23,IF(OR('04 — Scenario comparison — Base'!C24="",'04 — Scenario comparison — Base'!C23=""),"",'04 — Scenario comparison — Base'!C24<'04 — Scenario comparison — Base'!C23))="",FALSE,IF(ISERROR('04 — Scenario comparison — Base'!C24<'04 — Scenario comparison — Base'!C23),'04 — Scenario comparison — Base'!C24<'04 — Scenario comparison — Base'!C23,IF(OR('04 — Scenario comparison — Base'!C24="",'04 — Scenario comparison — Base'!C23=""),"",'04 — Scenario comparison — Base'!C24<'04 — Scenario comparison — Base'!C23))),"UNFUNDED LAUNCH",IF(IF(IF(ISERROR('Model inputs'!B73=0),'Model inputs'!B73=0,IF('Model inputs'!B73="","",'Model inputs'!B73=0))="",FALSE,IF(ISERROR('Model inputs'!B73=0),'Model inputs'!B73=0,IF('Model inputs'!B73="","",'Model inputs'!B73=0))),"Cash-positive steady state; not guaranteed runway","Finite burn runway; steady-state assumption")) -> Finite burn runway; steady-state assumption | D31: =IF(IF(IF(ISERROR('04 — Scenario comparison — Base'!D24<'04 — Scenario comparison — Base'!D23),'04 — Scenario comparison — Base'!D24<'04 — Scenario comparison — Base'!D23,IF(OR('04 — Scenario comparison — Base'!D24="",'04 — Scenario comparison — Base'!D23=""),"",'04 — Scenario comparison — Base'!D24<'04 — Scenario comparison — Base'!D23))="",FALSE,IF(ISERROR('04 — Scenario comparison — Base'!D24<'04 — Scenario comparison — Base'!D23),'04 — Scenario comparison — Base'!D24<'04 — Scenario comparison — Base'!D23,IF(OR('04 — Scenario comparison — Base'!D24="",'04 — Scenario comparison — Base'!D23=""),"",'04 — Scenario comparison — Base'!D24<'04 — Scenario comparison — Base'!D23))),"UNFUNDED LAUNCH",IF(IF(IF(ISERROR('Model inputs'!B72=0),'Model inputs'!B72=0,IF('Model inputs'!B72="","",'Model inputs'!B72=0))="",FALSE,IF(ISERROR('Model inputs'!B72=0),'Model inputs'!B72=0,IF('Model inputs'!B72="","",'Model inputs'!B72=0))),"Cash-positive steady state; not guaranteed runway","Finite burn runway; steady-state assumption")) -> Cash-positive steady state; not guaranteed runway
A32: TS Founder runway interpretation | B32: =IF(IF(IF(ISERROR('04 — Scenario comparison — Base'!B24<'04 — Scenario comparison — Base'!B23),'04 — Scenario comparison — Base'!B24<'04 — Scenario comparison — Base'!B23,IF(OR('04 — Scenario comparison — Base'!B24="",'04 — Scenario comparison — Base'!B23=""),"",'04 — Scenario comparison — Base'!B24<'04 — Scenario comparison — Base'!B23))="",FALSE,IF(ISERROR('04 — Scenario comparison — Base'!B24<'04 — Scenario comparison — Base'!B23),'04 — Scenario comparison — Base'!B24<'04 — Scenario comparison — Base'!B23,IF(OR('04 — Scenario comparison — Base'!B24="",'04 — Scenario comparison — Base'!B23=""),"",'04 — Scenario comparison — Base'!B24<'04 — Scenario comparison — Base'!B23))),"UNFUNDED LAUNCH",IF(IF(IF(ISERROR('03 — Digital unit economics and'!B30=0),'03 — Digital unit economics and'!B30=0,IF('03 — Digital unit economics and'!B30="","",'03 — Digital unit economics and'!B30=0))="",FALSE,IF(ISERROR('03 — Digital unit economics and'!B30=0),'03 — Digital unit economics and'!B30=0,IF('03 — Digital unit economics and'!B30="","",'03 — Digital unit economics and'!B30=0))),"Cash-positive steady state; not guaranteed runway","Finite burn runway; steady-state assumption")) -> Finite burn runway; steady-state assumption | C32: =IF(IF(IF(ISERROR('04 — Scenario comparison — Base'!C24<'04 — Scenario comparison — Base'!C23),'04 — Scenario comparison — Base'!C24<'04 — Scenario comparison — Base'!C23,IF(OR('04 — Scenario comparison — Base'!C24="",'04 — Scenario comparison — Base'!C23=""),"",'04 — Scenario comparison — Base'!C24<'04 — Scenario comparison — Base'!C23))="",FALSE,IF(ISERROR('04 — Scenario comparison — Base'!C24<'04 — Scenario comparison — Base'!C23),'04 — Scenario comparison — Base'!C24<'04 — Scenario comparison — Base'!C23,IF(OR('04 — Scenario comparison — Base'!C24="",'04 — Scenario comparison — Base'!C23=""),"",'04 — Scenario comparison — Base'!C24<'04 — Scenario comparison — Base'!C23))),"UNFUNDED LAUNCH",IF(IF(IF(ISERROR('Model inputs'!B75=0),'Model inputs'!B75=0,IF('Model inputs'!B75="","",'Model inputs'!B75=0))="",FALSE,IF(ISERROR('Model inputs'!B75=0),'Model inputs'!B75=0,IF('Model inputs'!B75="","",'Model inputs'!B75=0))),"Cash-positive steady state; not guaranteed runway","Finite burn runway; steady-state assumption")) -> Finite burn runway; steady-state assumption | D32: =IF(IF(IF(ISERROR('04 — Scenario comparison — Base'!D24<'04 — Scenario comparison — Base'!D23),'04 — Scenario comparison — Base'!D24<'04 — Scenario comparison — Base'!D23,IF(OR('04 — Scenario comparison — Base'!D24="",'04 — Scenario comparison — Base'!D23=""),"",'04 — Scenario comparison — Base'!D24<'04 — Scenario comparison — Base'!D23))="",FALSE,IF(ISERROR('04 — Scenario comparison — Base'!D24<'04 — Scenario comparison — Base'!D23),'04 — Scenario comparison — Base'!D24<'04 — Scenario comparison — Base'!D23,IF(OR('04 — Scenario comparison — Base'!D24="",'04 — Scenario comparison — Base'!D23=""),"",'04 — Scenario comparison — Base'!D24<'04 — Scenario comparison — Base'!D23))),"UNFUNDED LAUNCH",IF(IF(IF(ISERROR('Model inputs'!B74=0),'Model inputs'!B74=0,IF('Model inputs'!B74="","",'Model inputs'!B74=0))="",FALSE,IF(ISERROR('Model inputs'!B74=0),'Model inputs'!B74=0,IF('Model inputs'!B74="","",'Model inputs'!B74=0))),"Cash-positive steady state; not guaranteed runway","Finite burn runway; steady-state assumption")) -> Cash-positive steady state; not guaranteed runway
A33: TS Six month funding bootstrap | B33: ='04 — Scenario comparison — Base'!B23+'01 — Editable assumptions — USD'!B41*'03 — Digital unit economics and'!B29 -> 616.011 | C33: ='04 — Scenario comparison — Base'!C23+'Model inputs'!B91*'Model inputs'!B73 -> 1473.0647 | D33: ='04 — Scenario comparison — Base'!D23+'Model inputs'!B90*'Model inputs'!B72 -> 856.91396
A34: TS Six month funding founder | B34: ='04 — Scenario comparison — Base'!B23+'01 — Editable assumptions — USD'!B41*'03 — Digital unit economics and'!B30 -> 14399.151 | C34: ='04 — Scenario comparison — Base'!C23+'Model inputs'!B91*'Model inputs'!B75 -> 19473.065 | D34: ='04 — Scenario comparison — Base'!D23+'Model inputs'!B90*'Model inputs'!B74 -> 856.91396
A35: TS Ramp funding bootstrap | B35: ='01 — Editable assumptions — USD'!B42*'03 — Digital unit economics and'!B40+'04 — Scenario comparison — Base'!B33 -> 2416.011 | C35: ='Model inputs'!B97*'Model inputs'!B93+'04 — Scenario comparison — Base'!C33 -> 2223.0647 | D35: ='Model inputs'!B96*'Model inputs'!B92+'04 — Scenario comparison — Base'!D33 -> 8056.914
A36: TS Ramp funding founder | B36: ='01 — Editable assumptions — USD'!B42*'03 — Digital unit economics and'!B41+'04 — Scenario comparison — Base'!B34 -> 25199.151 | C36: ='Model inputs'!B97*'Model inputs'!B95+'04 — Scenario comparison — Base'!C34 -> 29223.065 | D36: ='Model inputs'!B96*'Model inputs'!B94+'04 — Scenario comparison — Base'!D34 -> 17056.914

Sheet 01 — Editable assumptions — USD
A1: 01 — Editable assumptions — USD, not actuals
A2: TicketStub — neatHack Business Plan — 2026-10-11 · Main Scenario
A4: Variable / dimension | B4: Value
A5: TS Monthly visits | B5: ='04 — Scenario comparison — Base'!B5 -> 10000
A6: TS Studio start rate | B6: ='04 — Scenario comparison — Base'!B6 -> 0.1
A7: TS Paid conversion of visits | B7: ='04 — Scenario comparison — Base'!B7 -> 0.02
A8: TS Initial images per start | B8: =1 -> 1
A9: TS Expected revisions per start | B9: =1 -> 1
A10: TS Chats per start | B10: ='04 — Scenario comparison — Base'!B9 -> 4
A11: TS Digital price | B11: =9 -> 9
A12: TS Payment rate | B12: =0.029 -> 0.029
A13: TS Payment fixed fee | B13: =0.3 -> 0.3
A14: TS Digital refund allowance | B14: =0.02 -> 0.02
A15: TS Variable support per order | B15: =0.15 -> 0.15
A16: TS Variable delivery per order | B16: =0.03 -> 0.03
A17: TS Variable email per order | B17: =0.02 -> 0.02
A18: TS Research input tokens | B18: =4000 -> 4000
A19: TS Research output tokens | B19: =600 -> 600
A20: TS Chat input tokens | B20: =3000 -> 3000
A21: TS Chat output tokens | B21: =300 -> 300
A22: TS Text input rate per million tokens | B22: =2 -> 2
A23: TS Text output rate per million tokens | B23: =10 -> 10
A24: TS Image text tokens | B24: =150 -> 150
A25: TS Image output tokens | B25: =4000 -> 4000
A26: TS Image input tokens | B26: =0 -> 0
A27: TS Image text rate per million tokens | B27: =5 -> 5
A28: TS Image output rate per million tokens | B28: =30 -> 30
A29: TS Image input rate per million tokens | B29: =8 -> 8
A30: TS Funding allowance | B30: =0.06 -> 0.06
A31: TS Billed retry rate | B31: =0 -> 0
A32: TS Monthly marketing | B32: ='04 — Scenario comparison — Base'!B18 -> 300
A33: TS Hypothetical opening cash | B33: ='04 — Scenario comparison — Base'!B24 -> 1000
A34: TS Alternative opening cash zero | B34: =0 -> 0
A35: TS Alternative opening cash funded | B35: =5000 -> 5000
A36: TS Founder cash pay bootstrap | B36: =0 -> 0
A37: TS Founder cash pay sensitivity | B37: =3000 -> 3000
A38: TS Contingency reserve | B38: =500 -> 500
A39: TS Payout float days | B39: =7 -> 7
A40: TS Cash month days | B40: =30 -> 30
A41: TS Postlaunch funding months | B41: =6 -> 6
A42: TS Prelaunch months | B42: =DATEDIF(DATE(YEAR('01 — Editable assumptions — USD'!B61),MONTH('01 — Editable assumptions — USD'!B61),1),DATE(YEAR('01 — Editable assumptions — USD'!B60),MONTH('01 — Editable assumptions — USD'!B60),1),"M") -> 3
A43: TS Expected prize cash | B43: =0 -> 0
A44: TS Promotional cash subsidy | B44: =0 -> 0
A45: TS Physical customer shipping | B45: =6 -> 6
A46: TS Physical refund allowance | B46: =0.05 -> 0.05
A47: TS Physical support per order | B47: =0.5 -> 0.5
A48: TS Physical supplier stress | B48: =0.25 -> 0.25
A49: TS Physical float days | B49: =14 -> 14
A50: TS Physical illustrative orders | B50: =100 -> 100
A51: TS Preview conversion minimum | B51: =0.005 -> 0.005
A52: TS Preview conversion maximum | B52: =0.04 -> 0.04
A53: TS Preview conversion step | B53: =0.001 -> 0.001
A54: TS Preview image minimum | B54: =1 -> 1
A55: TS Preview image maximum | B55: =6 -> 6
A56: TS Preview image step | B56: =0.5 -> 0.5
A57: TS Preview funding minimum | B57: =0 -> 0
A58: TS Preview funding maximum | B58: =0.1 -> 0.1
A59: TS Preview funding step | B59: =0.01 -> 0.01
A60: TS Hypothetical launch date | B60: =DATE(2027,1,1) -> 46388
A61: TS Projection start date | B61: =DATE(2026,10,1) -> 46296

Sheet 02 — Fixed monthly budgets — es
A1: 02 — Fixed monthly budgets — estimates
A2: TicketStub — neatHack Business Plan — 2026-10-11 · Main Scenario
A4: Variable / dimension | B4: TS Fixed budget amount
A5: Data and API licensing contingency | B5: =40 -> 40
A6: Database backup and base storage | B6: =30 -> 30
A7: Development AI and tools | B7: =60 -> 60
A8: Domain admin and accounting | B8: =20 -> 20
A9: Email base provision | B9: =20 -> 20
A10: Hosting | B10: =80 -> 80
A11: Monitoring traces and security | B11: =50 -> 50

Sheet 03 — Digital unit economics and
A1: 03 — Digital unit economics and funding — monthly assumptions
A2: TicketStub — neatHack Business Plan — 2026-10-11 · Main Scenario
A4: Variable / dimension | B4: Value
A5: TS Research cost per start | B5: ='01 — Editable assumptions — USD'!B18*'01 — Editable assumptions — USD'!B22/1000000+'01 — Editable assumptions — USD'!B19*'01 — Editable assumptions — USD'!B23/1000000 -> 0.014
A6: TS Chat cost per call | B6: ='01 — Editable assumptions — USD'!B20*'01 — Editable assumptions — USD'!B22/1000000+'01 — Editable assumptions — USD'!B21*'01 — Editable assumptions — USD'!B23/1000000 -> 0.009
A7: TS Image cost per generation | B7: ='01 — Editable assumptions — USD'!B24*'01 — Editable assumptions — USD'!B27/1000000+'01 — Editable assumptions — USD'!B25*'01 — Editable assumptions — USD'!B28/1000000+'01 — Editable assumptions — USD'!B26*'01 — Editable assumptions — USD'!B29/1000000 -> 0.12075
A8: TS Images per start | B8: ='01 — Editable assumptions — USD'!B8+'01 — Editable assumptions — USD'!B9 -> 2
A9: TS AI cost per start | B9: =('03 — Digital unit economics and'!B5+'04 — Scenario comparison — Base'!B9*'03 — Digital unit economics and'!B6+'03 — Digital unit economics and'!B8*'03 — Digital unit economics and'!B7)*(1+'01 — Editable assumptions — USD'!B30)*(1+'01 — Editable assumptions — USD'!B31) -> 0.30899
A10: TS Studio starts | B10: ='04 — Scenario comparison — Base'!B5*'04 — Scenario comparison — Base'!B6 -> 1000
A11: TS Digital orders | B11: ='04 — Scenario comparison — Base'!B5*'04 — Scenario comparison — Base'!B7 -> 200
A12: TS Monthly digital revenue | B12: ='03 — Digital unit economics and'!B11*'01 — Editable assumptions — USD'!B11 -> 1800
A13: TS Monthly AI spend | B13: ='03 — Digital unit economics and'!B10*'03 — Digital unit economics and'!B9 -> 308.99
A14: TS AI cost per paid order | B14: =IFERROR('03 — Digital unit economics and'!B13/'03 — Digital unit economics and'!B11,"") -> 1.54495
A15: TS Payment fee per order | B15: ='01 — Editable assumptions — USD'!B11*'01 — Editable assumptions — USD'!B12+'01 — Editable assumptions — USD'!B13 -> 0.561
A16: TS Refund allowance per order | B16: ='01 — Editable assumptions — USD'!B11*'01 — Editable assumptions — USD'!B14 -> 0.18
A17: TS Variable operations per order | B17: ='01 — Editable assumptions — USD'!B15+'01 — Editable assumptions — USD'!B16+'01 — Editable assumptions — USD'!B17 -> 0.2
A18: TS Digital contribution per order | B18: ='01 — Editable assumptions — USD'!B11-'03 — Digital unit economics and'!B15-'03 — Digital unit economics and'!B16-'03 — Digital unit economics and'!B17-'03 — Digital unit economics and'!B14 -> 6.51405
A19: TS Digital contribution margin | B19: =IFERROR('03 — Digital unit economics and'!B18/'01 — Editable assumptions — USD'!B11,"") -> 0.72378333
A20: TS Monthly contribution | B20: ='03 — Digital unit economics and'!B11*'03 — Digital unit economics and'!B18 -> 1302.81
A21: TS Monthly variable costs | B21: ='03 — Digital unit economics and'!B13+'03 — Digital unit economics and'!B11*('03 — Digital unit economics and'!B15+'03 — Digital unit economics and'!B16+'03 — Digital unit economics and'!B17) -> 497.19
A22: TS Fixed monthly budget | B22: =SUM('02 — Fixed monthly budgets — es'!B5,'02 — Fixed monthly budgets — es'!B6,'02 — Fixed monthly budgets — es'!B7,'02 — Fixed monthly budgets — es'!B8,'02 — Fixed monthly budgets — es'!B9,'02 — Fixed monthly budgets — es'!B10,'02 — Fixed monthly budgets — es'!B11) -> 300
A23: TS Monthly operating profit bootstrap | B23: ='03 — Digital unit economics and'!B20-'03 — Digital unit economics and'!B22-'04 — Scenario comparison — Base'!B18-'01 — Editable assumptions — USD'!B36 -> 702.81
A24: TS Monthly operating profit founder | B24: ='03 — Digital unit economics and'!B20-'03 — Digital unit economics and'!B22-'04 — Scenario comparison — Base'!B18-'01 — Editable assumptions — USD'!B37 -> -2297.19
A25: TS Break-even orders bootstrap | B25: =IF(IF(IF(ISERROR('03 — Digital unit economics and'!B18>0),'03 — Digital unit economics and'!B18>0,IF('03 — Digital unit economics and'!B18="","",'03 — Digital unit economics and'!B18>0))="",FALSE,IF(ISERROR('03 — Digital unit economics and'!B18>0),'03 — Digital unit economics and'!B18>0,IF('03 — Digital unit economics and'!B18="","",'03 — Digital unit economics and'!B18>0))),CEILING(('03 — Digital unit economics and'!B22+'04 — Scenario comparison — Base'!B18+'01 — Editable assumptions — USD'!B36)/'03 — Digital unit economics and'!B18,1),"") -> 93
A26: TS Break-even orders founder | B26: =IF(IF(IF(ISERROR('03 — Digital unit economics and'!B18>0),'03 — Digital unit economics and'!B18>0,IF('03 — Digital unit economics and'!B18="","",'03 — Digital unit economics and'!B18>0))="",FALSE,IF(ISERROR('03 — Digital unit economics and'!B18>0),'03 — Digital unit economics and'!B18>0,IF('03 — Digital unit economics and'!B18="","",'03 — Digital unit economics and'!B18>0))),CEILING(('03 — Digital unit economics and'!B22+'04 — Scenario comparison — Base'!B18+'01 — Editable assumptions — USD'!B37)/'03 — Digital unit economics and'!B18,1),"") -> 553
A27: TS Economics reconciliation | B27: ='03 — Digital unit economics and'!B12-'03 — Digital unit economics and'!B21-'03 — Digital unit economics and'!B20 -> -2.2737368e-13
A28: TS Launch reserve | B28: ='01 — Editable assumptions — USD'!B38+'01 — Editable assumptions — USD'!B39/'01 — Editable assumptions — USD'!B40*'03 — Digital unit economics and'!B21 -> 616.011
A29: TS Monthly burn bootstrap | B29: =MAX(0,-'03 — Digital unit economics and'!B23) -> 0
A30: TS Monthly burn founder | B30: =MAX(0,-'03 — Digital unit economics and'!B24) -> 2297.19
A31: TS Runway months bootstrap | B31: =IF(IF(IF(ISERROR('03 — Digital unit economics and'!B29>0),'03 — Digital unit economics and'!B29>0,IF('03 — Digital unit economics and'!B29="","",'03 — Digital unit economics and'!B29>0))="",FALSE,IF(ISERROR('03 — Digital unit economics and'!B29>0),'03 — Digital unit economics and'!B29>0,IF('03 — Digital unit economics and'!B29="","",'03 — Digital unit economics and'!B29>0))),MAX(0,'04 — Scenario comparison — Base'!B24-'03 — Digital unit economics and'!B28)/'03 — Digital unit economics and'!B29,"")
A32: TS Runway months founder | B32: =IF(IF(IF(ISERROR('03 — Digital unit economics and'!B30>0),'03 — Digital unit economics and'!B30>0,IF('03 — Digital unit economics and'!B30="","",'03 — Digital unit economics and'!B30>0))="",FALSE,IF(ISERROR('03 — Digital unit economics and'!B30>0),'03 — Digital unit economics and'!B30>0,IF('03 — Digital unit economics and'!B30="","",'03 — Digital unit economics and'!B30>0))),MAX(0,'04 — Scenario comparison — Base'!B24-'03 — Digital unit economics and'!B28)/'03 — Digital unit economics and'!B30,"") -> 0.16715596
A33: TS Runway at zero bootstrap | B33: =IF(IF(IF(ISERROR('03 — Digital unit economics and'!B29>0),'03 — Digital unit economics and'!B29>0,IF('03 — Digital unit economics and'!B29="","",'03 — Digital unit economics and'!B29>0))="",FALSE,IF(ISERROR('03 — Digital unit economics and'!B29>0),'03 — Digital unit economics and'!B29>0,IF('03 — Digital unit economics and'!B29="","",'03 — Digital unit economics and'!B29>0))),MAX(0,'01 — Editable assumptions — USD'!B34-'03 — Digital unit economics and'!B28)/'03 — Digital unit economics and'!B29,"")
A34: TS Runway at zero founder | B34: =IF(IF(IF(ISERROR('03 — Digital unit economics and'!B30>0),'03 — Digital unit economics and'!B30>0,IF('03 — Digital unit economics and'!B30="","",'03 — Digital unit economics and'!B30>0))="",FALSE,IF(ISERROR('03 — Digital unit economics and'!B30>0),'03 — Digital unit economics and'!B30>0,IF('03 — Digital unit economics and'!B30="","",'03 — Digital unit economics and'!B30>0))),MAX(0,'01 — Editable assumptions — USD'!B34-'03 — Digital unit economics and'!B28)/'03 — Digital unit economics and'!B30,"") -> 0
A35: TS Runway at funded bootstrap | B35: =IF(IF(IF(ISERROR('03 — Digital unit economics and'!B29>0),'03 — Digital unit economics and'!B29>0,IF('03 — Digital unit economics and'!B29="","",'03 — Digital unit economics and'!B29>0))="",FALSE,IF(ISERROR('03 — Digital unit economics and'!B29>0),'03 — Digital unit economics and'!B29>0,IF('03 — Digital unit economics and'!B29="","",'03 — Digital unit economics and'!B29>0))),MAX(0,'01 — Editable assumptions — USD'!B35-'03 — Digital unit economics and'!B28)/'03 — Digital unit economics and'!B29,"")
A36: TS Runway at funded founder | B36: =IF(IF(IF(ISERROR('03 — Digital unit economics and'!B30>0),'03 — Digital unit economics and'!B30>0,IF('03 — Digital unit economics and'!B30="","",'03 — Digital unit economics and'!B30>0))="",FALSE,IF(ISERROR('03 — Digital unit economics and'!B30>0),'03 — Digital unit economics and'!B30>0,IF('03 — Digital unit economics and'!B30="","",'03 — Digital unit economics and'!B30>0))),MAX(0,'01 — Editable assumptions — USD'!B35-'03 — Digital unit economics and'!B28)/'03 — Digital unit economics and'!B30,"") -> 1.9084138
A37: TS Launch funding gap | B37: =MAX(0,'03 — Digital unit economics and'!B28-'04 — Scenario comparison — Base'!B24) -> 0
A38: TS Six month funding bootstrap | B38: ='03 — Digital unit economics and'!B28+'01 — Editable assumptions — USD'!B41*'03 — Digital unit economics and'!B29 -> 616.011
A39: TS Six month funding founder | B39: ='03 — Digital unit economics and'!B28+'01 — Editable assumptions — USD'!B41*'03 — Digital unit economics and'!B30 -> 14399.151
A40: TS Prelaunch monthly burn bootstrap | B40: ='03 — Digital unit economics and'!B22+'04 — Scenario comparison — Base'!B18+'01 — Editable assumptions — USD'!B36 -> 600
A41: TS Prelaunch monthly burn founder | B41: ='03 — Digital unit economics and'!B22+'04 — Scenario comparison — Base'!B18+'01 — Editable assumptions — USD'!B37 -> 3600
A42: TS Ramp funding bootstrap | B42: ='01 — Editable assumptions — USD'!B42*'03 — Digital unit economics and'!B40+'03 — Digital unit economics and'!B38 -> 2416.011
A43: TS Ramp funding founder | B43: ='01 — Editable assumptions — USD'!B42*'03 — Digital unit economics and'!B41+'03 — Digital unit economics and'!B39 -> 25199.151
A44: TS Ramp funding gap bootstrap | B44: =MAX(0,'03 — Digital unit economics and'!B42-'04 — Scenario comparison — Base'!B24) -> 1416.011
A45: TS Ramp funding gap founder | B45: =MAX(0,'03 — Digital unit economics and'!B43-'04 — Scenario comparison — Base'!B24) -> 24199.151
A46: TS Launch status | B46: =IF(IF(IF(ISERROR('04 — Scenario comparison — Base'!B24<'03 — Digital unit economics and'!B28),'04 — Scenario comparison — Base'!B24<'03 — Digital unit economics and'!B28,IF(OR('04 — Scenario comparison — Base'!B24="",'03 — Digital unit economics and'!B28=""),"",'04 — Scenario comparison — Base'!B24<'03 — Digital unit economics and'!B28))="",FALSE,IF(ISERROR('04 — Scenario comparison — Base'!B24<'03 — Digital unit economics and'!B28),'04 — Scenario comparison — Base'!B24<'03 — Digital unit economics and'!B28,IF(OR('04 — Scenario comparison — Base'!B24="",'03 — Digital unit economics and'!B28=""),"",'04 — Scenario comparison — Base'!B24<'03 — Digital unit economics and'!B28))),"UNFUNDED LAUNCH","Reserve funded; ramp still required") -> Reserve funded; ramp still required
A47: TS Zero cash launch status | B47: =IF(IF(IF(ISERROR('01 — Editable assumptions — USD'!B34<'03 — Digital unit economics and'!B28),'01 — Editable assumptions — USD'!B34<'03 — Digital unit economics and'!B28,IF(OR('01 — Editable assumptions — USD'!B34="",'03 — Digital unit economics and'!B28=""),"",'01 — Editable assumptions — USD'!B34<'03 — Digital unit economics and'!B28))="",FALSE,IF(ISERROR('01 — Editable assumptions — USD'!B34<'03 — Digital unit economics and'!B28),'01 — Editable assumptions — USD'!B34<'03 — Digital unit economics and'!B28,IF(OR('01 — Editable assumptions — USD'!B34="",'03 — Digital unit economics and'!B28=""),"",'01 — Editable assumptions — USD'!B34<'03 — Digital unit economics and'!B28))),"UNFUNDED LAUNCH","Reserve funded; ramp still required") -> UNFUNDED LAUNCH
A48: TS Funded cash launch status | B48: =IF(IF(IF(ISERROR('01 — Editable assumptions — USD'!B35<'03 — Digital unit economics and'!B28),'01 — Editable assumptions — USD'!B35<'03 — Digital unit economics and'!B28,IF(OR('01 — Editable assumptions — USD'!B35="",'03 — Digital unit economics and'!B28=""),"",'01 — Editable assumptions — USD'!B35<'03 — Digital unit economics and'!B28))="",FALSE,IF(ISERROR('01 — Editable assumptions — USD'!B35<'03 — Digital unit economics and'!B28),'01 — Editable assumptions — USD'!B35<'03 — Digital unit economics and'!B28,IF(OR('01 — Editable assumptions — USD'!B35="",'03 — Digital unit economics and'!B28=""),"",'01 — Editable assumptions — USD'!B35<'03 — Digital unit economics and'!B28))),"UNFUNDED LAUNCH","Reserve funded; ramp still required") -> Reserve funded; ramp still required
A49: TS Bootstrap runway interpretation | B49: =IF(IF(IF(ISERROR('04 — Scenario comparison — Base'!B24<'03 — Digital unit economics and'!B28),'04 — Scenario comparison — Base'!B24<'03 — Digital unit economics and'!B28,IF(OR('04 — Scenario comparison — Base'!B24="",'03 — Digital unit economics and'!B28=""),"",'04 — Scenario comparison — Base'!B24<'03 — Digital unit economics and'!B28))="",FALSE,IF(ISERROR('04 — Scenario comparison — Base'!B24<'03 — Digital unit economics and'!B28),'04 — Scenario comparison — Base'!B24<'03 — Digital unit economics and'!B28,IF(OR('04 — Scenario comparison — Base'!B24="",'03 — Digital unit economics and'!B28=""),"",'04 — Scenario comparison — Base'!B24<'03 — Digital unit economics and'!B28))),"UNFUNDED LAUNCH",IF(IF(IF(ISERROR('03 — Digital unit economics and'!B29=0),'03 — Digital unit economics and'!B29=0,IF('03 — Digital unit economics and'!B29="","",'03 — Digital unit economics and'!B29=0))="",FALSE,IF(ISERROR('03 — Digital unit economics and'!B29=0),'03 — Digital unit economics and'!B29=0,IF('03 — Digital unit economics and'!B29="","",'03 — Digital unit economics and'!B29=0))),"Cash-positive steady state; not guaranteed runway","Finite burn runway; steady-state assumption")) -> Cash-positive steady state; not guaranteed runway
A50: TS Founder runway interpretation | B50: =IF(IF(IF(ISERROR('04 — Scenario comparison — Base'!B24<'03 — Digital unit economics and'!B28),'04 — Scenario comparison — Base'!B24<'03 — Digital unit economics and'!B28,IF(OR('04 — Scenario comparison — Base'!B24="",'03 — Digital unit economics and'!B28=""),"",'04 — Scenario comparison — Base'!B24<'03 — Digital unit economics and'!B28))="",FALSE,IF(ISERROR('04 — Scenario comparison — Base'!B24<'03 — Digital unit economics and'!B28),'04 — Scenario comparison — Base'!B24<'03 — Digital unit economics and'!B28,IF(OR('04 — Scenario comparison — Base'!B24="",'03 — Digital unit economics and'!B28=""),"",'04 — Scenario comparison — Base'!B24<'03 — Digital unit economics and'!B28))),"UNFUNDED LAUNCH",IF(IF(IF(ISERROR('03 — Digital unit economics and'!B30=0),'03 — Digital unit economics and'!B30=0,IF('03 — Digital unit economics and'!B30="","",'03 — Digital unit economics and'!B30=0))="",FALSE,IF(ISERROR('03 — Digital unit economics and'!B30=0),'03 — Digital unit economics and'!B30=0,IF('03 — Digital unit economics and'!B30="","",'03 — Digital unit economics and'!B30=0))),"Cash-positive steady state; not guaranteed runway","Finite burn runway; steady-state assumption")) -> Finite burn runway; steady-state assumption

Sheet 05 — One-factor sensitivities —
A1: 05 — One-factor sensitivities — editable assumptions
A2: TicketStub — neatHack Business Plan — 2026-10-11 · Main Scenario
A4: Variable / dimension | B4: TS Sens Traffic multiplier | C4: TS Sens Conversion multiplier | D4: TS Sens Start multiplier | E4: TS Sens Images multiplier | F4: TS Sens Chats multiplier | G4: TS Sens Image output multiplier | H4: TS Sens Funding allowance | I4: TS Sens Image input tokens | J4: TS Sens Retry rate | K4: TS Sens Visits | L4: TS Sens Orders | M4: TS Sens Starts | N4: TS Sens Image cost | O4: TS Sens AI spend | P4: TS Sens AI per order | Q4: TS Sens Revenue | R4: TS Sens Contribution per order | S4: TS Sens Operating profit | T4: TS Sens Profit change | U4: TS Sens Founder profit
A5: Baseline | B5: =1 -> 1 | C5: =1 -> 1 | D5: =1 -> 1 | E5: =1 -> 1 | F5: =1 -> 1 | G5: =1 -> 1 | H5: =IF('01 — Editable assumptions — USD'!B30="","",'01 — Editable assumptions — USD'!B30) -> 0.06 | I5: =IF('01 — Editable assumptions — USD'!B26="","",'01 — Editable assumptions — USD'!B26) -> 0 | J5: =IF('01 — Editable assumptions — USD'!B31="","",'01 — Editable assumptions — USD'!B31) -> 0 | K5: ='04 — Scenario comparison — Base'!B5*'05 — One-factor sensitivities —'!B5 -> 10000 | L5: ='05 — One-factor sensitivities —'!K5*'04 — Scenario comparison — Base'!B7*'05 — One-factor sensitivities —'!C5 -> 200 | M5: ='05 — One-factor sensitivities —'!K5*'04 — Scenario comparison — Base'!B6*'05 — One-factor sensitivities —'!D5 -> 1000 | N5: ='01 — Editable assumptions — USD'!B24*'01 — Editable assumptions — USD'!B27/1000000+'01 — Editable assumptions — USD'!B25*'05 — One-factor sensitivities —'!G5*'01 — Editable assumptions — USD'!B28/1000000+'05 — One-factor sensitivities —'!I5*'01 — Editable assumptions — USD'!B29/1000000 -> 0.12075 | O5: ='05 — One-factor sensitivities —'!M5*('03 — Digital unit economics and'!B5+'04 — Scenario comparison — Base'!B9*'05 — One-factor sensitivities —'!F5*'03 — Digital unit economics and'!B6+'04 — Scenario comparison — Base'!B8*'05 — One-factor sensitivities —'!E5*'05 — One-factor sensitivities —'!N5)*(1+'05 — One-factor sensitivities —'!H5)*(1+'05 — One-factor sensitivities —'!J5) -> 308.99 | P5: =IFERROR('05 — One-factor sensitivities —'!O5/'05 — One-factor sensitivities —'!L5,"") -> 1.54495 | Q5: ='05 — One-factor sensitivities —'!L5*'01 — Editable assumptions — USD'!B11 -> 1800 | R5: ='01 — Editable assumptions — USD'!B11-'03 — Digital unit economics and'!B15-'03 — Digital unit economics and'!B16-'03 — Digital unit economics and'!B17-'05 — One-factor sensitivities —'!P5 -> 6.51405 | S5: ='05 — One-factor sensitivities —'!L5*('01 — Editable assumptions — USD'!B11-'03 — Digital unit economics and'!B15-'03 — Digital unit economics and'!B16-'03 — Digital unit economics and'!B17)-'05 — One-factor sensitivities —'!O5-'04 — Scenario comparison — Base'!B17-'04 — Scenario comparison — Base'!B18-'01 — Editable assumptions — USD'!B36 -> 702.81 | T5: ='05 — One-factor sensitivities —'!S5-'04 — Scenario comparison — Base'!B19 -> 0 | U5: ='05 — One-factor sensitivities —'!S5+'01 — Editable assumptions — USD'!B36-'01 — Editable assumptions — USD'!B37 -> -2297.19
A6: Billed retries 10 percent | B6: =1 -> 1 | C6: =1 -> 1 | D6: =1 -> 1 | E6: =1 -> 1 | F6: =1 -> 1 | G6: =1 -> 1 | H6: =IF('01 — Editable assumptions — USD'!B30="","",'01 — Editable assumptions — USD'!B30) -> 0.06 | I6: =IF('01 — Editable assumptions — USD'!B26="","",'01 — Editable assumptions — USD'!B26) -> 0 | J6: =0.1 -> 0.1 | K6: ='04 — Scenario comparison — Base'!B5*'05 — One-factor sensitivities —'!B6 -> 10000 | L6: ='05 — One-factor sensitivities —'!K6*'04 — Scenario comparison — Base'!B7*'05 — One-factor sensitivities —'!C6 -> 200 | M6: ='05 — One-factor sensitivities —'!K6*'04 — Scenario comparison — Base'!B6*'05 — One-factor sensitivities —'!D6 -> 1000 | N6: ='01 — Editable assumptions — USD'!B24*'01 — Editable assumptions — USD'!B27/1000000+'01 — Editable assumptions — USD'!B25*'05 — One-factor sensitivities —'!G6*'01 — Editable assumptions — USD'!B28/1000000+'05 — One-factor sensitivities —'!I6*'01 — Editable assumptions — USD'!B29/1000000 -> 0.12075 | O6: ='05 — One-factor sensitivities —'!M6*('03 — Digital unit economics and'!B5+'04 — Scenario comparison — Base'!B9*'05 — One-factor sensitivities —'!F6*'03 — Digital unit economics and'!B6+'04 — Scenario comparison — Base'!B8*'05 — One-factor sensitivities —'!E6*'05 — One-factor sensitivities —'!N6)*(1+'05 — One-factor sensitivities —'!H6)*(1+'05 — One-factor sensitivities —'!J6) -> 339.889 | P6: =IFERROR('05 — One-factor sensitivities —'!O6/'05 — One-factor sensitivities —'!L6,"") -> 1.699445 | Q6: ='05 — One-factor sensitivities —'!L6*'01 — Editable assumptions — USD'!B11 -> 1800 | R6: ='01 — Editable assumptions — USD'!B11-'03 — Digital unit economics and'!B15-'03 — Digital unit economics and'!B16-'03 — Digital unit economics and'!B17-'05 — One-factor sensitivities —'!P6 -> 6.359555 | S6: ='05 — One-factor sensitivities —'!L6*('01 — Editable assumptions — USD'!B11-'03 — Digital unit economics and'!B15-'03 — Digital unit economics and'!B16-'03 — Digital unit economics and'!B17)-'05 — One-factor sensitivities —'!O6-'04 — Scenario comparison — Base'!B17-'04 — Scenario comparison — Base'!B18-'01 — Editable assumptions — USD'!B36 -> 671.911 | T6: ='05 — One-factor sensitivities —'!S6-'04 — Scenario comparison — Base'!B19 -> -30.899 | U6: ='05 — One-factor sensitivities —'!S6+'01 — Editable assumptions — USD'!B36-'01 — Editable assumptions — USD'!B37 -> -2328.089
A7: Chats x2 — Base eight per start | B7: =1 -> 1 | C7: =1 -> 1 | D7: =1 -> 1 | E7: =1 -> 1 | F7: =2 -> 2 | G7: =1 -> 1 | H7: =IF('01 — Editable assumptions — USD'!B30="","",'01 — Editable assumptions — USD'!B30) -> 0.06 | I7: =IF('01 — Editable assumptions — USD'!B26="","",'01 — Editable assumptions — USD'!B26) -> 0 | J7: =IF('01 — Editable assumptions — USD'!B31="","",'01 — Editable assumptions — USD'!B31) -> 0 | K7: ='04 — Scenario comparison — Base'!B5*'05 — One-factor sensitivities —'!B7 -> 10000 | L7: ='05 — One-factor sensitivities —'!K7*'04 — Scenario comparison — Base'!B7*'05 — One-factor sensitivities —'!C7 -> 200 | M7: ='05 — One-factor sensitivities —'!K7*'04 — Scenario comparison — Base'!B6*'05 — One-factor sensitivities —'!D7 -> 1000 | N7: ='01 — Editable assumptions — USD'!B24*'01 — Editable assumptions — USD'!B27/1000000+'01 — Editable assumptions — USD'!B25*'05 — One-factor sensitivities —'!G7*'01 — Editable assumptions — USD'!B28/1000000+'05 — One-factor sensitivities —'!I7*'01 — Editable assumptions — USD'!B29/1000000 -> 0.12075 | O7: ='05 — One-factor sensitivities —'!M7*('03 — Digital unit economics and'!B5+'04 — Scenario comparison — Base'!B9*'05 — One-factor sensitivities —'!F7*'03 — Digital unit economics and'!B6+'04 — Scenario comparison — Base'!B8*'05 — One-factor sensitivities —'!E7*'05 — One-factor sensitivities —'!N7)*(1+'05 — One-factor sensitivities —'!H7)*(1+'05 — One-factor sensitivities —'!J7) -> 347.15 | P7: =IFERROR('05 — One-factor sensitivities —'!O7/'05 — One-factor sensitivities —'!L7,"") -> 1.73575 | Q7: ='05 — One-factor sensitivities —'!L7*'01 — Editable assumptions — USD'!B11 -> 1800 | R7: ='01 — Editable assumptions — USD'!B11-'03 — Digital unit economics and'!B15-'03 — Digital unit economics and'!B16-'03 — Digital unit economics and'!B17-'05 — One-factor sensitivities —'!P7 -> 6.32325 | S7: ='05 — One-factor sensitivities —'!L7*('01 — Editable assumptions — USD'!B11-'03 — Digital unit economics and'!B15-'03 — Digital unit economics and'!B16-'03 — Digital unit economics and'!B17)-'05 — One-factor sensitivities —'!O7-'04 — Scenario comparison — Base'!B17-'04 — Scenario comparison — Base'!B18-'01 — Editable assumptions — USD'!B36 -> 664.65 | T7: ='05 — One-factor sensitivities —'!S7-'04 — Scenario comparison — Base'!B19 -> -38.16 | U7: ='05 — One-factor sensitivities —'!S7+'01 — Editable assumptions — USD'!B36-'01 — Editable assumptions — USD'!B37 -> -2335.35
A8: Conversion x0.5 — Base 1 percent | B8: =1 -> 1 | C8: =0.5 -> 0.5 | D8: =1 -> 1 | E8: =1 -> 1 | F8: =1 -> 1 | G8: =1 -> 1 | H8: =IF('01 — Editable assumptions — USD'!B30="","",'01 — Editable assumptions — USD'!B30) -> 0.06 | I8: =IF('01 — Editable assumptions — USD'!B26="","",'01 — Editable assumptions — USD'!B26) -> 0 | J8: =IF('01 — Editable assumptions — USD'!B31="","",'01 — Editable assumptions — USD'!B31) -> 0 | K8: ='04 — Scenario comparison — Base'!B5*'05 — One-factor sensitivities —'!B8 -> 10000 | L8: ='05 — One-factor sensitivities —'!K8*'04 — Scenario comparison — Base'!B7*'05 — One-factor sensitivities —'!C8 -> 100 | M8: ='05 — One-factor sensitivities —'!K8*'04 — Scenario comparison — Base'!B6*'05 — One-factor sensitivities —'!D8 -> 1000 | N8: ='01 — Editable assumptions — USD'!B24*'01 — Editable assumptions — USD'!B27/1000000+'01 — Editable assumptions — USD'!B25*'05 — One-factor sensitivities —'!G8*'01 — Editable assumptions — USD'!B28/1000000+'05 — One-factor sensitivities —'!I8*'01 — Editable assumptions — USD'!B29/1000000 -> 0.12075 | O8: ='05 — One-factor sensitivities —'!M8*('03 — Digital unit economics and'!B5+'04 — Scenario comparison — Base'!B9*'05 — One-factor sensitivities —'!F8*'03 — Digital unit economics and'!B6+'04 — Scenario comparison — Base'!B8*'05 — One-factor sensitivities —'!E8*'05 — One-factor sensitivities —'!N8)*(1+'05 — One-factor sensitivities —'!H8)*(1+'05 — One-factor sensitivities —'!J8) -> 308.99 | P8: =IFERROR('05 — One-factor sensitivities —'!O8/'05 — One-factor sensitivities —'!L8,"") -> 3.0899 | Q8: ='05 — One-factor sensitivities —'!L8*'01 — Editable assumptions — USD'!B11 -> 900 | R8: ='01 — Editable assumptions — USD'!B11-'03 — Digital unit economics and'!B15-'03 — Digital unit economics and'!B16-'03 — Digital unit economics and'!B17-'05 — One-factor sensitivities —'!P8 -> 4.9691 | S8: ='05 — One-factor sensitivities —'!L8*('01 — Editable assumptions — USD'!B11-'03 — Digital unit economics and'!B15-'03 — Digital unit economics and'!B16-'03 — Digital unit economics and'!B17)-'05 — One-factor sensitivities —'!O8-'04 — Scenario comparison — Base'!B17-'04 — Scenario comparison — Base'!B18-'01 — Editable assumptions — USD'!B36 -> -103.09 | T8: ='05 — One-factor sensitivities —'!S8-'04 — Scenario comparison — Base'!B19 -> -805.9 | U8: ='05 — One-factor sensitivities —'!S8+'01 — Editable assumptions — USD'!B36-'01 — Editable assumptions — USD'!B37 -> -3103.09
A9: Conversion x1.5 — Base 3 percent | B9: =1 -> 1 | C9: =1.5 -> 1.5 | D9: =1 -> 1 | E9: =1 -> 1 | F9: =1 -> 1 | G9: =1 -> 1 | H9: =IF('01 — Editable assumptions — USD'!B30="","",'01 — Editable assumptions — USD'!B30) -> 0.06 | I9: =IF('01 — Editable assumptions — USD'!B26="","",'01 — Editable assumptions — USD'!B26) -> 0 | J9: =IF('01 — Editable assumptions — USD'!B31="","",'01 — Editable assumptions — USD'!B31) -> 0 | K9: ='04 — Scenario comparison — Base'!B5*'05 — One-factor sensitivities —'!B9 -> 10000 | L9: ='05 — One-factor sensitivities —'!K9*'04 — Scenario comparison — Base'!B7*'05 — One-factor sensitivities —'!C9 -> 300 | M9: ='05 — One-factor sensitivities —'!K9*'04 — Scenario comparison — Base'!B6*'05 — One-factor sensitivities —'!D9 -> 1000 | N9: ='01 — Editable assumptions — USD'!B24*'01 — Editable assumptions — USD'!B27/1000000+'01 — Editable assumptions — USD'!B25*'05 — One-factor sensitivities —'!G9*'01 — Editable assumptions — USD'!B28/1000000+'05 — One-factor sensitivities —'!I9*'01 — Editable assumptions — USD'!B29/1000000 -> 0.12075 | O9: ='05 — One-factor sensitivities —'!M9*('03 — Digital unit economics and'!B5+'04 — Scenario comparison — Base'!B9*'05 — One-factor sensitivities —'!F9*'03 — Digital unit economics and'!B6+'04 — Scenario comparison — Base'!B8*'05 — One-factor sensitivities —'!E9*'05 — One-factor sensitivities —'!N9)*(1+'05 — One-factor sensitivities —'!H9)*(1+'05 — One-factor sensitivities —'!J9) -> 308.99 | P9: =IFERROR('05 — One-factor sensitivities —'!O9/'05 — One-factor sensitivities —'!L9,"") -> 1.0299667 | Q9: ='05 — One-factor sensitivities —'!L9*'01 — Editable assumptions — USD'!B11 -> 2700 | R9: ='01 — Editable assumptions — USD'!B11-'03 — Digital unit economics and'!B15-'03 — Digital unit economics and'!B16-'03 — Digital unit economics and'!B17-'05 — One-factor sensitivities —'!P9 -> 7.0290333 | S9: ='05 — One-factor sensitivities —'!L9*('01 — Editable assumptions — USD'!B11-'03 — Digital unit economics and'!B15-'03 — Digital unit economics and'!B16-'03 — Digital unit economics and'!B17)-'05 — One-factor sensitivities —'!O9-'04 — Scenario comparison — Base'!B17-'04 — Scenario comparison — Base'!B18-'01 — Editable assumptions — USD'!B36 -> 1508.71 | T9: ='05 — One-factor sensitivities —'!S9-'04 — Scenario comparison — Base'!B19 -> 805.9 | U9: ='05 — One-factor sensitivities —'!S9+'01 — Editable assumptions — USD'!B36-'01 — Editable assumptions — USD'!B37 -> -1491.29
A10: Double traffic | B10: =2 -> 2 | C10: =1 -> 1 | D10: =1 -> 1 | E10: =1 -> 1 | F10: =1 -> 1 | G10: =1 -> 1 | H10: =IF('01 — Editable assumptions — USD'!B30="","",'01 — Editable assumptions — USD'!B30) -> 0.06 | I10: =IF('01 — Editable assumptions — USD'!B26="","",'01 — Editable assumptions — USD'!B26) -> 0 | J10: =IF('01 — Editable assumptions — USD'!B31="","",'01 — Editable assumptions — USD'!B31) -> 0 | K10: ='04 — Scenario comparison — Base'!B5*'05 — One-factor sensitivities —'!B10 -> 20000 | L10: ='05 — One-factor sensitivities —'!K10*'04 — Scenario comparison — Base'!B7*'05 — One-factor sensitivities —'!C10 -> 400 | M10: ='05 — One-factor sensitivities —'!K10*'04 — Scenario comparison — Base'!B6*'05 — One-factor sensitivities —'!D10 -> 2000 | N10: ='01 — Editable assumptions — USD'!B24*'01 — Editable assumptions — USD'!B27/1000000+'01 — Editable assumptions — USD'!B25*'05 — One-factor sensitivities —'!G10*'01 — Editable assumptions — USD'!B28/1000000+'05 — One-factor sensitivities —'!I10*'01 — Editable assumptions — USD'!B29/1000000 -> 0.12075 | O10: ='05 — One-factor sensitivities —'!M10*('03 — Digital unit economics and'!B5+'04 — Scenario comparison — Base'!B9*'05 — One-factor sensitivities —'!F10*'03 — Digital unit economics and'!B6+'04 — Scenario comparison — Base'!B8*'05 — One-factor sensitivities —'!E10*'05 — One-factor sensitivities —'!N10)*(1+'05 — One-factor sensitivities —'!H10)*(1+'05 — One-factor sensitivities —'!J10) -> 617.98 | P10: =IFERROR('05 — One-factor sensitivities —'!O10/'05 — One-factor sensitivities —'!L10,"") -> 1.54495 | Q10: ='05 — One-factor sensitivities —'!L10*'01 — Editable assumptions — USD'!B11 -> 3600 | R10: ='01 — Editable assumptions — USD'!B11-'03 — Digital unit economics and'!B15-'03 — Digital unit economics and'!B16-'03 — Digital unit economics and'!B17-'05 — One-factor sensitivities —'!P10 -> 6.51405 | S10: ='05 — One-factor sensitivities —'!L10*('01 — Editable assumptions — USD'!B11-'03 — Digital unit economics and'!B15-'03 — Digital unit economics and'!B16-'03 — Digital unit economics and'!B17)-'05 — One-factor sensitivities —'!O10-'04 — Scenario comparison — Base'!B17-'04 — Scenario comparison — Base'!B18-'01 — Editable assumptions — USD'!B36 -> 2005.62 | T10: ='05 — One-factor sensitivities —'!S10-'04 — Scenario comparison — Base'!B19 -> 1302.81 | U10: ='05 — One-factor sensitivities —'!S10+'01 — Editable assumptions — USD'!B36-'01 — Editable assumptions — USD'!B37 -> -994.38
A11: Funding allowance 10 percent | B11: =1 -> 1 | C11: =1 -> 1 | D11: =1 -> 1 | E11: =1 -> 1 | F11: =1 -> 1 | G11: =1 -> 1 | H11: =0.1 -> 0.1 | I11: =IF('01 — Editable assumptions — USD'!B26="","",'01 — Editable assumptions — USD'!B26) -> 0 | J11: =IF('01 — Editable assumptions — USD'!B31="","",'01 — Editable assumptions — USD'!B31) -> 0 | K11: ='04 — Scenario comparison — Base'!B5*'05 — One-factor sensitivities —'!B11 -> 10000 | L11: ='05 — One-factor sensitivities —'!K11*'04 — Scenario comparison — Base'!B7*'05 — One-factor sensitivities —'!C11 -> 200 | M11: ='05 — One-factor sensitivities —'!K11*'04 — Scenario comparison — Base'!B6*'05 — One-factor sensitivities —'!D11 -> 1000 | N11: ='01 — Editable assumptions — USD'!B24*'01 — Editable assumptions — USD'!B27/1000000+'01 — Editable assumptions — USD'!B25*'05 — One-factor sensitivities —'!G11*'01 — Editable assumptions — USD'!B28/1000000+'05 — One-factor sensitivities —'!I11*'01 — Editable assumptions — USD'!B29/1000000 -> 0.12075 | O11: ='05 — One-factor sensitivities —'!M11*('03 — Digital unit economics and'!B5+'04 — Scenario comparison — Base'!B9*'05 — One-factor sensitivities —'!F11*'03 — Digital unit economics and'!B6+'04 — Scenario comparison — Base'!B8*'05 — One-factor sensitivities —'!E11*'05 — One-factor sensitivities —'!N11)*(1+'05 — One-factor sensitivities —'!H11)*(1+'05 — One-factor sensitivities —'!J11) -> 320.65 | P11: =IFERROR('05 — One-factor sensitivities —'!O11/'05 — One-factor sensitivities —'!L11,"") -> 1.60325 | Q11: ='05 — One-factor sensitivities —'!L11*'01 — Editable assumptions — USD'!B11 -> 1800 | R11: ='01 — Editable assumptions — USD'!B11-'03 — Digital unit economics and'!B15-'03 — Digital unit economics and'!B16-'03 — Digital unit economics and'!B17-'05 — One-factor sensitivities —'!P11 -> 6.45575 | S11: ='05 — One-factor sensitivities —'!L11*('01 — Editable assumptions — USD'!B11-'03 — Digital unit economics and'!B15-'03 — Digital unit economics and'!B16-'03 — Digital unit economics and'!B17)-'05 — One-factor sensitivities —'!O11-'04 — Scenario comparison — Base'!B17-'04 — Scenario comparison — Base'!B18-'01 — Editable assumptions — USD'!B36 -> 691.15 | T11: ='05 — One-factor sensitivities —'!S11-'04 — Scenario comparison — Base'!B19 -> -11.66 | U11: ='05 — One-factor sensitivities —'!S11+'01 — Editable assumptions — USD'!B36-'01 — Editable assumptions — USD'!B37 -> -2308.85
A12: Funding allowance zero | B12: =1 -> 1 | C12: =1 -> 1 | D12: =1 -> 1 | E12: =1 -> 1 | F12: =1 -> 1 | G12: =1 -> 1 | H12: =0 -> 0 | I12: =IF('01 — Editable assumptions — USD'!B26="","",'01 — Editable assumptions — USD'!B26) -> 0 | J12: =IF('01 — Editable assumptions — USD'!B31="","",'01 — Editable assumptions — USD'!B31) -> 0 | K12: ='04 — Scenario comparison — Base'!B5*'05 — One-factor sensitivities —'!B12 -> 10000 | L12: ='05 — One-factor sensitivities —'!K12*'04 — Scenario comparison — Base'!B7*'05 — One-factor sensitivities —'!C12 -> 200 | M12: ='05 — One-factor sensitivities —'!K12*'04 — Scenario comparison — Base'!B6*'05 — One-factor sensitivities —'!D12 -> 1000 | N12: ='01 — Editable assumptions — USD'!B24*'01 — Editable assumptions — USD'!B27/1000000+'01 — Editable assumptions — USD'!B25*'05 — One-factor sensitivities —'!G12*'01 — Editable assumptions — USD'!B28/1000000+'05 — One-factor sensitivities —'!I12*'01 — Editable assumptions — USD'!B29/1000000 -> 0.12075 | O12: ='05 — One-factor sensitivities —'!M12*('03 — Digital unit economics and'!B5+'04 — Scenario comparison — Base'!B9*'05 — One-factor sensitivities —'!F12*'03 — Digital unit economics and'!B6+'04 — Scenario comparison — Base'!B8*'05 — One-factor sensitivities —'!E12*'05 — One-factor sensitivities —'!N12)*(1+'05 — One-factor sensitivities —'!H12)*(1+'05 — One-factor sensitivities —'!J12) -> 291.5 | P12: =IFERROR('05 — One-factor sensitivities —'!O12/'05 — One-factor sensitivities —'!L12,"") -> 1.4575 | Q12: ='05 — One-factor sensitivities —'!L12*'01 — Editable assumptions — USD'!B11 -> 1800 | R12: ='01 — Editable assumptions — USD'!B11-'03 — Digital unit economics and'!B15-'03 — Digital unit economics and'!B16-'03 — Digital unit economics and'!B17-'05 — One-factor sensitivities —'!P12 -> 6.6015 | S12: ='05 — One-factor sensitivities —'!L12*('01 — Editable assumptions — USD'!B11-'03 — Digital unit economics and'!B15-'03 — Digital unit economics and'!B16-'03 — Digital unit economics and'!B17)-'05 — One-factor sensitivities —'!O12-'04 — Scenario comparison — Base'!B17-'04 — Scenario comparison — Base'!B18-'01 — Editable assumptions — USD'!B36 -> 720.3 | T12: ='05 — One-factor sensitivities —'!S12-'04 — Scenario comparison — Base'!B19 -> 17.49 | U12: ='05 — One-factor sensitivities —'!S12+'01 — Editable assumptions — USD'!B36-'01 — Editable assumptions — USD'!B37 -> -2279.7
A13: Half traffic | B13: =0.5 -> 0.5 | C13: =1 -> 1 | D13: =1 -> 1 | E13: =1 -> 1 | F13: =1 -> 1 | G13: =1 -> 1 | H13: =IF('01 — Editable assumptions — USD'!B30="","",'01 — Editable assumptions — USD'!B30) -> 0.06 | I13: =IF('01 — Editable assumptions — USD'!B26="","",'01 — Editable assumptions — USD'!B26) -> 0 | J13: =IF('01 — Editable assumptions — USD'!B31="","",'01 — Editable assumptions — USD'!B31) -> 0 | K13: ='04 — Scenario comparison — Base'!B5*'05 — One-factor sensitivities —'!B13 -> 5000 | L13: ='05 — One-factor sensitivities —'!K13*'04 — Scenario comparison — Base'!B7*'05 — One-factor sensitivities —'!C13 -> 100 | M13: ='05 — One-factor sensitivities —'!K13*'04 — Scenario comparison — Base'!B6*'05 — One-factor sensitivities —'!D13 -> 500 | N13: ='01 — Editable assumptions — USD'!B24*'01 — Editable assumptions — USD'!B27/1000000+'01 — Editable assumptions — USD'!B25*'05 — One-factor sensitivities —'!G13*'01 — Editable assumptions — USD'!B28/1000000+'05 — One-factor sensitivities —'!I13*'01 — Editable assumptions — USD'!B29/1000000 -> 0.12075 | O13: ='05 — One-factor sensitivities —'!M13*('03 — Digital unit economics and'!B5+'04 — Scenario comparison — Base'!B9*'05 — One-factor sensitivities —'!F13*'03 — Digital unit economics and'!B6+'04 — Scenario comparison — Base'!B8*'05 — One-factor sensitivities —'!E13*'05 — One-factor sensitivities —'!N13)*(1+'05 — One-factor sensitivities —'!H13)*(1+'05 — One-factor sensitivities —'!J13) -> 154.495 | P13: =IFERROR('05 — One-factor sensitivities —'!O13/'05 — One-factor sensitivities —'!L13,"") -> 1.54495 | Q13: ='05 — One-factor sensitivities —'!L13*'01 — Editable assumptions — USD'!B11 -> 900 | R13: ='01 — Editable assumptions — USD'!B11-'03 — Digital unit economics and'!B15-'03 — Digital unit economics and'!B16-'03 — Digital unit economics and'!B17-'05 — One-factor sensitivities —'!P13 -> 6.51405 | S13: ='05 — One-factor sensitivities —'!L13*('01 — Editable assumptions — USD'!B11-'03 — Digital unit economics and'!B15-'03 — Digital unit economics and'!B16-'03 — Digital unit economics and'!B17)-'05 — One-factor sensitivities —'!O13-'04 — Scenario comparison — Base'!B17-'04 — Scenario comparison — Base'!B18-'01 — Editable assumptions — USD'!B36 -> 51.405 | T13: ='05 — One-factor sensitivities —'!S13-'04 — Scenario comparison — Base'!B19 -> -651.405 | U13: ='05 — One-factor sensitivities —'!S13+'01 — Editable assumptions — USD'!B36-'01 — Editable assumptions — USD'!B37 -> -2948.595
A14: Image output x0.5 — Base 2000 tokens | B14: =1 -> 1 | C14: =1 -> 1 | D14: =1 -> 1 | E14: =1 -> 1 | F14: =1 -> 1 | G14: =0.5 -> 0.5 | H14: =IF('01 — Editable assumptions — USD'!B30="","",'01 — Editable assumptions — USD'!B30) -> 0.06 | I14: =IF('01 — Editable assumptions — USD'!B26="","",'01 — Editable assumptions — USD'!B26) -> 0 | J14: =IF('01 — Editable assumptions — USD'!B31="","",'01 — Editable assumptions — USD'!B31) -> 0 | K14: ='04 — Scenario comparison — Base'!B5*'05 — One-factor sensitivities —'!B14 -> 10000 | L14: ='05 — One-factor sensitivities —'!K14*'04 — Scenario comparison — Base'!B7*'05 — One-factor sensitivities —'!C14 -> 200 | M14: ='05 — One-factor sensitivities —'!K14*'04 — Scenario comparison — Base'!B6*'05 — One-factor sensitivities —'!D14 -> 1000 | N14: ='01 — Editable assumptions — USD'!B24*'01 — Editable assumptions — USD'!B27/1000000+'01 — Editable assumptions — USD'!B25*'05 — One-factor sensitivities —'!G14*'01 — Editable assumptions — USD'!B28/1000000+'05 — One-factor sensitivities —'!I14*'01 — Editable assumptions — USD'!B29/1000000 -> 0.06075 | O14: ='05 — One-factor sensitivities —'!M14*('03 — Digital unit economics and'!B5+'04 — Scenario comparison — Base'!B9*'05 — One-factor sensitivities —'!F14*'03 — Digital unit economics and'!B6+'04 — Scenario comparison — Base'!B8*'05 — One-factor sensitivities —'!E14*'05 — One-factor sensitivities —'!N14)*(1+'05 — One-factor sensitivities —'!H14)*(1+'05 — One-factor sensitivities —'!J14) -> 181.79 | P14: =IFERROR('05 — One-factor sensitivities —'!O14/'05 — One-factor sensitivities —'!L14,"") -> 0.90895 | Q14: ='05 — One-factor sensitivities —'!L14*'01 — Editable assumptions — USD'!B11 -> 1800 | R14: ='01 — Editable assumptions — USD'!B11-'03 — Digital unit economics and'!B15-'03 — Digital unit economics and'!B16-'03 — Digital unit economics and'!B17-'05 — One-factor sensitivities —'!P14 -> 7.15005 | S14: ='05 — One-factor sensitivities —'!L14*('01 — Editable assumptions — USD'!B11-'03 — Digital unit economics and'!B15-'03 — Digital unit economics and'!B16-'03 — Digital unit economics and'!B17)-'05 — One-factor sensitivities —'!O14-'04 — Scenario comparison — Base'!B17-'04 — Scenario comparison — Base'!B18-'01 — Editable assumptions — USD'!B36 -> 830.01 | T14: ='05 — One-factor sensitivities —'!S14-'04 — Scenario comparison — Base'!B19 -> 127.2 | U14: ='05 — One-factor sensitivities —'!S14+'01 — Editable assumptions — USD'!B36-'01 — Editable assumptions — USD'!B37 -> -2169.99
A15: Image output x2 — Base 8000 tokens | B15: =1 -> 1 | C15: =1 -> 1 | D15: =1 -> 1 | E15: =1 -> 1 | F15: =1 -> 1 | G15: =2 -> 2 | H15: =IF('01 — Editable assumptions — USD'!B30="","",'01 — Editable assumptions — USD'!B30) -> 0.06 | I15: =IF('01 — Editable assumptions — USD'!B26="","",'01 — Editable assumptions — USD'!B26) -> 0 | J15: =IF('01 — Editable assumptions — USD'!B31="","",'01 — Editable assumptions — USD'!B31) -> 0 | K15: ='04 — Scenario comparison — Base'!B5*'05 — One-factor sensitivities —'!B15 -> 10000 | L15: ='05 — One-factor sensitivities —'!K15*'04 — Scenario comparison — Base'!B7*'05 — One-factor sensitivities —'!C15 -> 200 | M15: ='05 — One-factor sensitivities —'!K15*'04 — Scenario comparison — Base'!B6*'05 — One-factor sensitivities —'!D15 -> 1000 | N15: ='01 — Editable assumptions — USD'!B24*'01 — Editable assumptions — USD'!B27/1000000+'01 — Editable assumptions — USD'!B25*'05 — One-factor sensitivities —'!G15*'01 — Editable assumptions — USD'!B28/1000000+'05 — One-factor sensitivities —'!I15*'01 — Editable assumptions — USD'!B29/1000000 -> 0.24075 | O15: ='05 — One-factor sensitivities —'!M15*('03 — Digital unit economics and'!B5+'04 — Scenario comparison — Base'!B9*'05 — One-factor sensitivities —'!F15*'03 — Digital unit economics and'!B6+'04 — Scenario comparison — Base'!B8*'05 — One-factor sensitivities —'!E15*'05 — One-factor sensitivities —'!N15)*(1+'05 — One-factor sensitivities —'!H15)*(1+'05 — One-factor sensitivities —'!J15) -> 563.39 | P15: =IFERROR('05 — One-factor sensitivities —'!O15/'05 — One-factor sensitivities —'!L15,"") -> 2.81695 | Q15: ='05 — One-factor sensitivities —'!L15*'01 — Editable assumptions — USD'!B11 -> 1800 | R15: ='01 — Editable assumptions — USD'!B11-'03 — Digital unit economics and'!B15-'03 — Digital unit economics and'!B16-'03 — Digital unit economics and'!B17-'05 — One-factor sensitivities —'!P15 -> 5.24205 | S15: ='05 — One-factor sensitivities —'!L15*('01 — Editable assumptions — USD'!B11-'03 — Digital unit economics and'!B15-'03 — Digital unit economics and'!B16-'03 — Digital unit economics and'!B17)-'05 — One-factor sensitivities —'!O15-'04 — Scenario comparison — Base'!B17-'04 — Scenario comparison — Base'!B18-'01 — Editable assumptions — USD'!B36 -> 448.41 | T15: ='05 — One-factor sensitivities —'!S15-'04 — Scenario comparison — Base'!B19 -> -254.4 | U15: ='05 — One-factor sensitivities —'!S15+'01 — Editable assumptions — USD'!B36-'01 — Editable assumptions — USD'!B37 -> -2551.59
A16: Images x2 — Base four per start | B16: =1 -> 1 | C16: =1 -> 1 | D16: =1 -> 1 | E16: =2 -> 2 | F16: =1 -> 1 | G16: =1 -> 1 | H16: =IF('01 — Editable assumptions — USD'!B30="","",'01 — Editable assumptions — USD'!B30) -> 0.06 | I16: =IF('01 — Editable assumptions — USD'!B26="","",'01 — Editable assumptions — USD'!B26) -> 0 | J16: =IF('01 — Editable assumptions — USD'!B31="","",'01 — Editable assumptions — USD'!B31) -> 0 | K16: ='04 — Scenario comparison — Base'!B5*'05 — One-factor sensitivities —'!B16 -> 10000 | L16: ='05 — One-factor sensitivities —'!K16*'04 — Scenario comparison — Base'!B7*'05 — One-factor sensitivities —'!C16 -> 200 | M16: ='05 — One-factor sensitivities —'!K16*'04 — Scenario comparison — Base'!B6*'05 — One-factor sensitivities —'!D16 -> 1000 | N16: ='01 — Editable assumptions — USD'!B24*'01 — Editable assumptions — USD'!B27/1000000+'01 — Editable assumptions — USD'!B25*'05 — One-factor sensitivities —'!G16*'01 — Editable assumptions — USD'!B28/1000000+'05 — One-factor sensitivities —'!I16*'01 — Editable assumptions — USD'!B29/1000000 -> 0.12075 | O16: ='05 — One-factor sensitivities —'!M16*('03 — Digital unit economics and'!B5+'04 — Scenario comparison — Base'!B9*'05 — One-factor sensitivities —'!F16*'03 — Digital unit economics and'!B6+'04 — Scenario comparison — Base'!B8*'05 — One-factor sensitivities —'!E16*'05 — One-factor sensitivities —'!N16)*(1+'05 — One-factor sensitivities —'!H16)*(1+'05 — One-factor sensitivities —'!J16) -> 564.98 | P16: =IFERROR('05 — One-factor sensitivities —'!O16/'05 — One-factor sensitivities —'!L16,"") -> 2.8249 | Q16: ='05 — One-factor sensitivities —'!L16*'01 — Editable assumptions — USD'!B11 -> 1800 | R16: ='01 — Editable assumptions — USD'!B11-'03 — Digital unit economics and'!B15-'03 — Digital unit economics and'!B16-'03 — Digital unit economics and'!B17-'05 — One-factor sensitivities —'!P16 -> 5.2341 | S16: ='05 — One-factor sensitivities —'!L16*('01 — Editable assumptions — USD'!B11-'03 — Digital unit economics and'!B15-'03 — Digital unit economics and'!B16-'03 — Digital unit economics and'!B17)-'05 — One-factor sensitivities —'!O16-'04 — Scenario comparison — Base'!B17-'04 — Scenario comparison — Base'!B18-'01 — Editable assumptions — USD'!B36 -> 446.82 | T16: ='05 — One-factor sensitivities —'!S16-'04 — Scenario comparison — Base'!B19 -> -255.99 | U16: ='05 — One-factor sensitivities —'!S16+'01 — Editable assumptions — USD'!B36-'01 — Editable assumptions — USD'!B37 -> -2553.18
A17: Published funding fee 5.5 percent | B17: =1 -> 1 | C17: =1 -> 1 | D17: =1 -> 1 | E17: =1 -> 1 | F17: =1 -> 1 | G17: =1 -> 1 | H17: =0.055 -> 0.055 | I17: =IF('01 — Editable assumptions — USD'!B26="","",'01 — Editable assumptions — USD'!B26) -> 0 | J17: =IF('01 — Editable assumptions — USD'!B31="","",'01 — Editable assumptions — USD'!B31) -> 0 | K17: ='04 — Scenario comparison — Base'!B5*'05 — One-factor sensitivities —'!B17 -> 10000 | L17: ='05 — One-factor sensitivities —'!K17*'04 — Scenario comparison — Base'!B7*'05 — One-factor sensitivities —'!C17 -> 200 | M17: ='05 — One-factor sensitivities —'!K17*'04 — Scenario comparison — Base'!B6*'05 — One-factor sensitivities —'!D17 -> 1000 | N17: ='01 — Editable assumptions — USD'!B24*'01 — Editable assumptions — USD'!B27/1000000+'01 — Editable assumptions — USD'!B25*'05 — One-factor sensitivities —'!G17*'01 — Editable assumptions — USD'!B28/1000000+'05 — One-factor sensitivities —'!I17*'01 — Editable assumptions — USD'!B29/1000000 -> 0.12075 | O17: ='05 — One-factor sensitivities —'!M17*('03 — Digital unit economics and'!B5+'04 — Scenario comparison — Base'!B9*'05 — One-factor sensitivities —'!F17*'03 — Digital unit economics and'!B6+'04 — Scenario comparison — Base'!B8*'05 — One-factor sensitivities —'!E17*'05 — One-factor sensitivities —'!N17)*(1+'05 — One-factor sensitivities —'!H17)*(1+'05 — One-factor sensitivities —'!J17) -> 307.5325 | P17: =IFERROR('05 — One-factor sensitivities —'!O17/'05 — One-factor sensitivities —'!L17,"") -> 1.5376625 | Q17: ='05 — One-factor sensitivities —'!L17*'01 — Editable assumptions — USD'!B11 -> 1800 | R17: ='01 — Editable assumptions — USD'!B11-'03 — Digital unit economics and'!B15-'03 — Digital unit economics and'!B16-'03 — Digital unit economics and'!B17-'05 — One-factor sensitivities —'!P17 -> 6.5213375 | S17: ='05 — One-factor sensitivities —'!L17*('01 — Editable assumptions — USD'!B11-'03 — Digital unit economics and'!B15-'03 — Digital unit economics and'!B16-'03 — Digital unit economics and'!B17)-'05 — One-factor sensitivities —'!O17-'04 — Scenario comparison — Base'!B17-'04 — Scenario comparison — Base'!B18-'01 — Editable assumptions — USD'!B36 -> 704.2675 | T17: ='05 — One-factor sensitivities —'!S17-'04 — Scenario comparison — Base'!B19 -> 1.4575 | U17: ='05 — One-factor sensitivities —'!S17+'01 — Editable assumptions — USD'!B36-'01 — Editable assumptions — USD'!B37 -> -2295.7325
A18: Start rate x2 — Base 20 percent | B18: =1 -> 1 | C18: =1 -> 1 | D18: =2 -> 2 | E18: =1 -> 1 | F18: =1 -> 1 | G18: =1 -> 1 | H18: =IF('01 — Editable assumptions — USD'!B30="","",'01 — Editable assumptions — USD'!B30) -> 0.06 | I18: =IF('01 — Editable assumptions — USD'!B26="","",'01 — Editable assumptions — USD'!B26) -> 0 | J18: =IF('01 — Editable assumptions — USD'!B31="","",'01 — Editable assumptions — USD'!B31) -> 0 | K18: ='04 — Scenario comparison — Base'!B5*'05 — One-factor sensitivities —'!B18 -> 10000 | L18: ='05 — One-factor sensitivities —'!K18*'04 — Scenario comparison — Base'!B7*'05 — One-factor sensitivities —'!C18 -> 200 | M18: ='05 — One-factor sensitivities —'!K18*'04 — Scenario comparison — Base'!B6*'05 — One-factor sensitivities —'!D18 -> 2000 | N18: ='01 — Editable assumptions — USD'!B24*'01 — Editable assumptions — USD'!B27/1000000+'01 — Editable assumptions — USD'!B25*'05 — One-factor sensitivities —'!G18*'01 — Editable assumptions — USD'!B28/1000000+'05 — One-factor sensitivities —'!I18*'01 — Editable assumptions — USD'!B29/1000000 -> 0.12075 | O18: ='05 — One-factor sensitivities —'!M18*('03 — Digital unit economics and'!B5+'04 — Scenario comparison — Base'!B9*'05 — One-factor sensitivities —'!F18*'03 — Digital unit economics and'!B6+'04 — Scenario comparison — Base'!B8*'05 — One-factor sensitivities —'!E18*'05 — One-factor sensitivities —'!N18)*(1+'05 — One-factor sensitivities —'!H18)*(1+'05 — One-factor sensitivities —'!J18) -> 617.98 | P18: =IFERROR('05 — One-factor sensitivities —'!O18/'05 — One-factor sensitivities —'!L18,"") -> 3.0899 | Q18: ='05 — One-factor sensitivities —'!L18*'01 — Editable assumptions — USD'!B11 -> 1800 | R18: ='01 — Editable assumptions — USD'!B11-'03 — Digital unit economics and'!B15-'03 — Digital unit economics and'!B16-'03 — Digital unit economics and'!B17-'05 — One-factor sensitivities —'!P18 -> 4.9691 | S18: ='05 — One-factor sensitivities —'!L18*('01 — Editable assumptions — USD'!B11-'03 — Digital unit economics and'!B15-'03 — Digital unit economics and'!B16-'03 — Digital unit economics and'!B17)-'05 — One-factor sensitivities —'!O18-'04 — Scenario comparison — Base'!B17-'04 — Scenario comparison — Base'!B18-'01 — Editable assumptions — USD'!B36 -> 393.82 | T18: ='05 — One-factor sensitivities —'!S18-'04 — Scenario comparison — Base'!B19 -> -308.99 | U18: ='05 — One-factor sensitivities —'!S18+'01 — Editable assumptions — USD'!B36-'01 — Editable assumptions — USD'!B37 -> -2606.18
A19: True edit 4000 input image tokens | B19: =1 -> 1 | C19: =1 -> 1 | D19: =1 -> 1 | E19: =1 -> 1 | F19: =1 -> 1 | G19: =1 -> 1 | H19: =IF('01 — Editable assumptions — USD'!B30="","",'01 — Editable assumptions — USD'!B30) -> 0.06 | I19: =4000 -> 4000 | J19: =IF('01 — Editable assumptions — USD'!B31="","",'01 — Editable assumptions — USD'!B31) -> 0 | K19: ='04 — Scenario comparison — Base'!B5*'05 — One-factor sensitivities —'!B19 -> 10000 | L19: ='05 — One-factor sensitivities —'!K19*'04 — Scenario comparison — Base'!B7*'05 — One-factor sensitivities —'!C19 -> 200 | M19: ='05 — One-factor sensitivities —'!K19*'04 — Scenario comparison — Base'!B6*'05 — One-factor sensitivities —'!D19 -> 1000 | N19: ='01 — Editable assumptions — USD'!B24*'01 — Editable assumptions — USD'!B27/1000000+'01 — Editable assumptions — USD'!B25*'05 — One-factor sensitivities —'!G19*'01 — Editable assumptions — USD'!B28/1000000+'05 — One-factor sensitivities —'!I19*'01 — Editable assumptions — USD'!B29/1000000 -> 0.15275 | O19: ='05 — One-factor sensitivities —'!M19*('03 — Digital unit economics and'!B5+'04 — Scenario comparison — Base'!B9*'05 — One-factor sensitivities —'!F19*'03 — Digital unit economics and'!B6+'04 — Scenario comparison — Base'!B8*'05 — One-factor sensitivities —'!E19*'05 — One-factor sensitivities —'!N19)*(1+'05 — One-factor sensitivities —'!H19)*(1+'05 — One-factor sensitivities —'!J19) -> 376.83 | P19: =IFERROR('05 — One-factor sensitivities —'!O19/'05 — One-factor sensitivities —'!L19,"") -> 1.88415 | Q19: ='05 — One-factor sensitivities —'!L19*'01 — Editable assumptions — USD'!B11 -> 1800 | R19: ='01 — Editable assumptions — USD'!B11-'03 — Digital unit economics and'!B15-'03 — Digital unit economics and'!B16-'03 — Digital unit economics and'!B17-'05 — One-factor sensitivities —'!P19 -> 6.17485 | S19: ='05 — One-factor sensitivities —'!L19*('01 — Editable assumptions — USD'!B11-'03 — Digital unit economics and'!B15-'03 — Digital unit economics and'!B16-'03 — Digital unit economics and'!B17)-'05 — One-factor sensitivities —'!O19-'04 — Scenario comparison — Base'!B17-'04 — Scenario comparison — Base'!B18-'01 — Editable assumptions — USD'!B36 -> 634.97 | T19: ='05 — One-factor sensitivities —'!S19-'04 — Scenario comparison — Base'!B19 -> -67.84 | U19: ='05 — One-factor sensitivities —'!S19+'01 — Editable assumptions — USD'!B36-'01 — Editable assumptions — USD'!B37 -> -2365.03

Sheet 07 — Cash projection — hypothet
A1: 07 — Cash projection — hypothetical dates and balances
A2: TicketStub — neatHack Business Plan — 2026-10-11 · Main Scenario
A4: Variable / dimension | B4: 2026-10 | C4: 2026-11 | D4: 2026-12 | E4: 2027-01 | F4: 2027-02 | G4: 2027-03 | H4: 2027-04 | I4: 2027-05 | J4: 2027-06 | K4: 2027-07 | L4: 2027-08 | M4: 2027-09 | N4: 2027-10 | O4: 2027-11 | P4: 2027-12
A5: TS Projected digital orders | B5: =IF(IF(IF(ISERROR(DATE(2026,10,1)>=DATE(YEAR('01 — Editable assumptions — USD'!B60),MONTH('01 — Editable assumptions — USD'!B60),1)),DATE(2026,10,1)>=DATE(YEAR('01 — Editable assumptions — USD'!B60),MONTH('01 — Editable assumptions — USD'!B60),1),IF(DATE(YEAR('01 — Editable assumptions — USD'!B60),MONTH('01 — Editable assumptions — USD'!B60),1)="","",DATE(2026,10,1)>=DATE(YEAR('01 — Editable assumptions — USD'!B60),MONTH('01 — Editable assumptions — USD'!B60),1)))="",FALSE,IF(ISERROR(DATE(2026,10,1)>=DATE(YEAR('01 — Editable assumptions — USD'!B60),MONTH('01 — Editable assumptions — USD'!B60),1)),DATE(2026,10,1)>=DATE(YEAR('01 — Editable assumptions — USD'!B60),MONTH('01 — Editable assumptions — USD'!B60),1),IF(DATE(YEAR('01 — Editable assumptions — USD'!B60),MONTH('01 — Editable assumptions — USD'!B60),1)="","",DATE(2026,10,1)>=DATE(YEAR('01 — Editable assumptions — USD'!B60),MONTH('01 — Editable assumptions — USD'!B60),1)))),IF('04 — Scenario comparison — Base'!B10="","",'04 — Scenario comparison — Base'!B10),0) -> 0 | C5: =IF(IF(IF(ISERROR(DATE(2026,11,1)>=DATE(YEAR('01 — Editable assumptions — USD'!B60),MONTH('01 — Editable assumptions — USD'!B60),1)),DATE(2026,11,1)>=DATE(YEAR('01 — Editable assumptions — USD'!B60),MONTH('01 — Editable assumptions — USD'!B60),1),IF(DATE(YEAR('01 — Editable assumptions — USD'!B60),MONTH('01 — Editable assumptions — USD'!B60),1)="","",DATE(2026,11,1)>=DATE(YEAR('01 — Editable assumptions — USD'!B60),MONTH('01 — Editable assumptions — USD'!B60),1)))="",FALSE,IF(ISERROR(DATE(2026,11,1)>=DATE(YEAR('01 — Editable assumptions — USD'!B60),MONTH('01 — Editable assumptions — USD'!B60),1)),DATE(2026,11,1)>=DATE(YEAR('01 — Editable assumptions — USD'!B60),MONTH('01 — Editable assumptions — USD'!B60),1),IF(DATE(YEAR('01 — Editable assumptions — USD'!B60),MONTH('01 — Editable assumptions — USD'!B60),1)="","",DATE(2026,11,1)>=DATE(YEAR('01 — Editable assumptions — USD'!B60),MONTH('01 — Editable assumptions — USD'!B60),1)))),IF('04 — Scenario comparison — Base'!B10="","",'04 — Scenario comparison — Base'!B10),0) -> 0 | D5: =IF(IF(IF(ISERROR(DATE(2026,12,1)>=DATE(YEAR('01 — Editable assumptions — USD'!B60),MONTH('01 — Editable assumptions — USD'!B60),1)),DATE(2026,12,1)>=DATE(YEAR('01 — Editable assumptions — USD'!B60),MONTH('01 — Editable assumptions — USD'!B60),1),IF(DATE(YEAR('01 — Editable assumptions — USD'!B60),MONTH('01 — Editable assumptions — USD'!B60),1)="","",DATE(2026,12,1)>=DATE(YEAR('01 — Editable assumptions — USD'!B60),MONTH('01 — Editable assumptions — USD'!B60),1)))="",FALSE,IF(ISERROR(DATE(2026,12,1)>=DATE(YEAR('01 — Editable assumptions — USD'!B60),MONTH('01 — Editable assumptions — USD'!B60),1)),DATE(2026,12,1)>=DATE(YEAR('01 — Editable assumptions — USD'!B60),MONTH('01 — Editable assumptions — USD'!B60),1),IF(DATE(YEAR('01 — Editable assumptions — USD'!B60),MONTH('01 — Editable assumptions — USD'!B60),1)="","",DATE(2026,12,1)>=DATE(YEAR('01 — Editable assumptions — USD'!B60),MONTH('01 — Editable assumptions — USD'!B60),1)))),IF('04 — Scenario comparison — Base'!B10="","",'04 — Scenario comparison — Base'!B10),0) -> 0 | E5: =IF(IF(IF(ISERROR(DATE(2027,1,1)>=DATE(YEAR('01 — Editable assumptions — USD'!B60),MONTH('01 — Editable assumptions — USD'!B60),1)),DATE(2027,1,1)>=DATE(YEAR('01 — Editable assumptions — USD'!B60),MONTH('01 — Editable assumptions — USD'!B60),1),IF(DATE(YEAR('01 — Editable assumptions — USD'!B60),MONTH('01 — Editable assumptions — USD'!B60),1)="","",DATE(2027,1,1)>=DATE(YEAR('01 — Editable assumptions — USD'!B60),MONTH('01 — Editable assumptions — USD'!B60),1)))="",FALSE,IF(ISERROR(DATE(2027,1,1)>=DATE(YEAR('01 — Editable assumptions — USD'!B60),MONTH('01 — Editable assumptions — USD'!B60),1)),DATE(2027,1,1)>=DATE(YEAR('01 — Editable assumptions — USD'!B60),MONTH('01 — Editable assumptions — USD'!B60),1),IF(DATE(YEAR('01 — Editable assumptions — USD'!B60),MONTH('01 — Editable assumptions — USD'!B60),1)="","",DATE(2027,1,1)>=DATE(YEAR('01 — Editable assumptions — USD'!B60),MONTH('01 — Editable assumptions — USD'!B60),1)))),IF('04 — Scenario comparison — Base'!B10="","",'04 — Scenario comparison — Base'!B10),0) -> 200 | F5: =IF(IF(IF(ISERROR(DATE(2027,2,1)>=DATE(YEAR('01 — Editable assumptions — USD'!B60),MONTH('01 — Editable assumptions — USD'!B60),1)),DATE(2027,2,1)>=DATE(YEAR('01 — Editable assumptions — USD'!B60),MONTH('01 — Editable assumptions — USD'!B60),1),IF(DATE(YEAR('01 — Editable assumptions — USD'!B60),MONTH('01 — Editable assumptions — USD'!B60),1)="","",DATE(2027,2,1)>=DATE(YEAR('01 — Editable assumptions — USD'!B60),MONTH('01 — Editable assumptions — USD'!B60),1)))="",FALSE,IF(ISERROR(DATE(2027,2,1)>=DATE(YEAR('01 — Editable assumptions — USD'!B60),MONTH('01 — Editable assumptions — USD'!B60),1)),DATE(2027,2,1)>=DATE(YEAR('01 — Editable assumptions — USD'!B60),MONTH('01 — Editable assumptions — USD'!B60),1),IF(DATE(YEAR('01 — Editable assumptions — USD'!B60),MONTH('01 — Editable assumptions — USD'!B60),1)="","",DATE(2027,2,1)>=DATE(YEAR('01 — Editable assumptions — USD'!B60),MONTH('01 — Editable assumptions — USD'!B60),1)))),IF('04 — Scenario comparison — Base'!B10="","",'04 — Scenario comparison — Base'!B10),0) -> 200 | G5: =IF(IF(IF(ISERROR(DATE(2027,3,1)>=DATE(YEAR('01 — Editable assumptions — USD'!B60),MONTH('01 — Editable assumptions — USD'!B60),1)),DATE(2027,3,1)>=DATE(YEAR('01 — Editable assumptions — USD'!B60),MONTH('01 — Editable assumptions — USD'!B60),1),IF(DATE(YEAR('01 — Editable assumptions — USD'!B60),MONTH('01 — Editable assumptions — USD'!B60),1)="","",DATE(2027,3,1)>=DATE(YEAR('01 — Editable assumptions — USD'!B60),MONTH('01 — Editable assumptions — USD'!B60),1)))="",FALSE,IF(ISERROR(DATE(2027,3,1)>=DATE(YEAR('01 — Editable assumptions — USD'!B60),MONTH('01 — Editable assumptions — USD'!B60),1)),DATE(2027,3,1)>=DATE(YEAR('01 — Editable assumptions — USD'!B60),MONTH('01 — Editable assumptions — USD'!B60),1),IF(DATE(YEAR('01 — Editable assumptions — USD'!B60),MONTH('01 — Editable assumptions — USD'!B60),1)="","",DATE(2027,3,1)>=DATE(YEAR('01 — Editable assumptions — USD'!B60),MONTH('01 — Editable assumptions — USD'!B60),1)))),IF('04 — Scenario comparison — Base'!B10="","",'04 — Scenario comparison — Base'!B10),0) -> 200 | H5: =IF(IF(IF(ISERROR(DATE(2027,4,1)>=DATE(YEAR('01 — Editable assumptions — USD'!B60),MONTH('01 — Editable assumptions — USD'!B60),1)),DATE(2027,4,1)>=DATE(YEAR('01 — Editable assumptions — USD'!B60),MONTH('01 — Editable assumptions — USD'!B60),1),IF(DATE(YEAR('01 — Editable assumptions — USD'!B60),MONTH('01 — Editable assumptions — USD'!B60),1)="","",DATE(2027,4,1)>=DATE(YEAR('01 — Editable assumptions — USD'!B60),MONTH('01 — Editable assumptions — USD'!B60),1)))="",FALSE,IF(ISERROR(DATE(2027,4,1)>=DATE(YEAR('01 — Editable assumptions — USD'!B60),MONTH('01 — Editable assumptions — USD'!B60),1)),DATE(2027,4,1)>=DATE(YEAR('01 — Editable assumptions — USD'!B60),MONTH('01 — Editable assumptions — USD'!B60),1),IF(DATE(YEAR('01 — Editable assumptions — USD'!B60),MONTH('01 — Editable assumptions — USD'!B60),1)="","",DATE(2027,4,1)>=DATE(YEAR('01 — Editable assumptions — USD'!B60),MONTH('01 — Editable assumptions — USD'!B60),1)))),IF('04 — Scenario comparison — Base'!B10="","",'04 — Scenario comparison — Base'!B10),0) -> 200 | I5: =IF(IF(IF(ISERROR(DATE(2027,5,1)>=DATE(YEAR('01 — Editable assumptions — USD'!B60),MONTH('01 — Editable assumptions — USD'!B60),1)),DATE(2027,5,1)>=DATE(YEAR('01 — Editable assumptions — USD'!B60),MONTH('01 — Editable assumptions — USD'!B60),1),IF(DATE(YEAR('01 — Editable assumptions — USD'!B60),MONTH('01 — Editable assumptions — USD'!B60),1)="","",DATE(2027,5,1)>=DATE(YEAR('01 — Editable assumptions — USD'!B60),MONTH('01 — Editable assumptions — USD'!B60),1)))="",FALSE,IF(ISERROR(DATE(2027,5,1)>=DATE(YEAR('01 — Editable assumptions — USD'!B60),MONTH('01 — Editable assumptions — USD'!B60),1)),DATE(2027,5,1)>=DATE(YEAR('01 — Editable assumptions — USD'!B60),MONTH('01 — Editable assumptions — USD'!B60),1),IF(DATE(YEAR('01 — Editable assumptions — USD'!B60),MONTH('01 — Editable assumptions — USD'!B60),1)="","",DATE(2027,5,1)>=DATE(YEAR('01 — Editable assumptions — USD'!B60),MONTH('01 — Editable assumptions — USD'!B60),1)))),IF('04 — Scenario comparison — Base'!B10="","",'04 — Scenario comparison — Base'!B10),0) -> 200 | J5: =IF(IF(IF(ISERROR(DATE(2027,6,1)>=DATE(YEAR('01 — Editable assumptions — USD'!B60),MONTH('01 — Editable assumptions — USD'!B60),1)),DATE(2027,6,1)>=DATE(YEAR('01 — Editable assumptions — USD'!B60),MONTH('01 — Editable assumptions — USD'!B60),1),IF(DATE(YEAR('01 — Editable assumptions — USD'!B60),MONTH('01 — Editable assumptions — USD'!B60),1)="","",DATE(2027,6,1)>=DATE(YEAR('01 — Editable assumptions — USD'!B60),MONTH('01 — Editable assumptions — USD'!B60),1)))="",FALSE,IF(ISERROR(DATE(2027,6,1)>=DATE(YEAR('01 — Editable assumptions — USD'!B60),MONTH('01 — Editable assumptions — USD'!B60),1)),DATE(2027,6,1)>=DATE(YEAR('01 — Editable assumptions — USD'!B60),MONTH('01 — Editable assumptions — USD'!B60),1),IF(DATE(YEAR('01 — Editable assumptions — USD'!B60),MONTH('01 — Editable assumptions — USD'!B60),1)="","",DATE(2027,6,1)>=DATE(YEAR('01 — Editable assumptions — USD'!B60),MONTH('01 — Editable assumptions — USD'!B60),1)))),IF('04 — Scenario comparison — Base'!B10="","",'04 — Scenario comparison — Base'!B10),0) -> 200 | K5: =IF(IF(IF(ISERROR(DATE(2027,7,1)>=DATE(YEAR('01 — Editable assumptions — USD'!B60),MONTH('01 — Editable assumptions — USD'!B60),1)),DATE(2027,7,1)>=DATE(YEAR('01 — Editable assumptions — USD'!B60),MONTH('01 — Editable assumptions — USD'!B60),1),IF(DATE(YEAR('01 — Editable assumptions — USD'!B60),MONTH('01 — Editable assumptions — USD'!B60),1)="","",DATE(2027,7,1)>=DATE(YEAR('01 — Editable assumptions — USD'!B60),MONTH('01 — Editable assumptions — USD'!B60),1)))="",FALSE,IF(ISERROR(DATE(2027,7,1)>=DATE(YEAR('01 — Editable assumptions — USD'!B60),MONTH('01 — Editable assumptions — USD'!B60),1)),DATE(2027,7,1)>=DATE(YEAR('01 — Editable assumptions — USD'!B60),MONTH('01 — Editable assumptions — USD'!B60),1),IF(DATE(YEAR('01 — Editable assumptions — USD'!B60),MONTH('01 — Editable assumptions — USD'!B60),1)="","",DATE(2027,7,1)>=DATE(YEAR('01 — Editable assumptions — USD'!B60),MONTH('01 — Editable assumptions — USD'!B60),1)))),IF('04 — Scenario comparison — Base'!B10="","",'04 — Scenario comparison — Base'!B10),0) -> 200 | L5: =IF(IF(IF(ISERROR(DATE(2027,8,1)>=DATE(YEAR('01 — Editable assumptions — USD'!B60),MONTH('01 — Editable assumptions — USD'!B60),1)),DATE(2027,8,1)>=DATE(YEAR('01 — Editable assumptions — USD'!B60),MONTH('01 — Editable assumptions — USD'!B60),1),IF(DATE(YEAR('01 — Editable assumptions — USD'!B60),MONTH('01 — Editable assumptions — USD'!B60),1)="","",DATE(2027,8,1)>=DATE(YEAR('01 — Editable assumptions — USD'!B60),MONTH('01 — Editable assumptions — USD'!B60),1)))="",FALSE,IF(ISERROR(DATE(2027,8,1)>=DATE(YEAR('01 — Editable assumptions — USD'!B60),MONTH('01 — Editable assumptions — USD'!B60),1)),DATE(2027,8,1)>=DATE(YEAR('01 — Editable assumptions — USD'!B60),MONTH('01 — Editable assumptions — USD'!B60),1),IF(DATE(YEAR('01 — Editable assumptions — USD'!B60),MONTH('01 — Editable assumptions — USD'!B60),1)="","",DATE(2027,8,1)>=DATE(YEAR('01 — Editable assumptions — USD'!B60),MONTH('01 — Editable assumptions — USD'!B60),1)))),IF('04 — Scenario comparison — Base'!B10="","",'04 — Scenario comparison — Base'!B10),0) -> 200 | M5: =IF(IF(IF(ISERROR(DATE(2027,9,1)>=DATE(YEAR('01 — Editable assumptions — USD'!B60),MONTH('01 — Editable assumptions — USD'!B60),1)),DATE(2027,9,1)>=DATE(YEAR('01 — Editable assumptions — USD'!B60),MONTH('01 — Editable assumptions — USD'!B60),1),IF(DATE(YEAR('01 — Editable assumptions — USD'!B60),MONTH('01 — Editable assumptions — USD'!B60),1)="","",DATE(2027,9,1)>=DATE(YEAR('01 — Editable assumptions — USD'!B60),MONTH('01 — Editable assumptions — USD'!B60),1)))="",FALSE,IF(ISERROR(DATE(2027,9,1)>=DATE(YEAR('01 — Editable assumptions — USD'!B60),MONTH('01 — Editable assumptions — USD'!B60),1)),DATE(2027,9,1)>=DATE(YEAR('01 — Editable assumptions — USD'!B60),MONTH('01 — Editable assumptions — USD'!B60),1),IF(DATE(YEAR('01 — Editable assumptions — USD'!B60),MONTH('01 — Editable assumptions — USD'!B60),1)="","",DATE(2027,9,1)>=DATE(YEAR('01 — Editable assumptions — USD'!B60),MONTH('01 — Editable assumptions — USD'!B60),1)))),IF('04 — Scenario comparison — Base'!B10="","",'04 — Scenario comparison — Base'!B10),0) -> 200 | N5: =IF(IF(IF(ISERROR(DATE(2027,10,1)>=DATE(YEAR('01 — Editable assumptions — USD'!B60),MONTH('01 — Editable assumptions — USD'!B60),1)),DATE(2027,10,1)>=DATE(YEAR('01 — Editable assumptions — USD'!B60),MONTH('01 — Editable assumptions — USD'!B60),1),IF(DATE(YEAR('01 — Editable assumptions — USD'!B60),MONTH('01 — Editable assumptions — USD'!B60),1)="","",DATE(2027,10,1)>=DATE(YEAR('01 — Editable assumptions — USD'!B60),MONTH('01 — Editable assumptions — USD'!B60),1)))="",FALSE,IF(ISERROR(DATE(2027,10,1)>=DATE(YEAR('01 — Editable assumptions — USD'!B60),MONTH('01 — Editable assumptions — USD'!B60),1)),DATE(2027,10,1)>=DATE(YEAR('01 — Editable assumptions — USD'!B60),MONTH('01 — Editable assumptions — USD'!B60),1),IF(DATE(YEAR('01 — Editable assumptions — USD'!B60),MONTH('01 — Editable assumptions — USD'!B60),1)="","",DATE(2027,10,1)>=DATE(YEAR('01 — Editable assumptions — USD'!B60),MONTH('01 — Editable assumptions — USD'!B60),1)))),IF('04 — Scenario comparison — Base'!B10="","",'04 — Scenario comparison — Base'!B10),0) -> 200 | O5: =IF(IF(IF(ISERROR(DATE(2027,11,1)>=DATE(YEAR('01 — Editable assumptions — USD'!B60),MONTH('01 — Editable assumptions — USD'!B60),1)),DATE(2027,11,1)>=DATE(YEAR('01 — Editable assumptions — USD'!B60),MONTH('01 — Editable assumptions — USD'!B60),1),IF(DATE(YEAR('01 — Editable assumptions — USD'!B60),MONTH('01 — Editable assumptions — USD'!B60),1)="","",DATE(2027,11,1)>=DATE(YEAR('01 — Editable assumptions — USD'!B60),MONTH('01 — Editable assumptions — USD'!B60),1)))="",FALSE,IF(ISERROR(DATE(2027,11,1)>=DATE(YEAR('01 — Editable assumptions — USD'!B60),MONTH('01 — Editable assumptions — USD'!B60),1)),DATE(2027,11,1)>=DATE(YEAR('01 — Editable assumptions — USD'!B60),MONTH('01 — Editable assumptions — USD'!B60),1),IF(DATE(YEAR('01 — Editable assumptions — USD'!B60),MONTH('01 — Editable assumptions — USD'!B60),1)="","",DATE(2027,11,1)>=DATE(YEAR('01 — Editable assumptions — USD'!B60),MONTH('01 — Editable assumptions — USD'!B60),1)))),IF('04 — Scenario comparison — Base'!B10="","",'04 — Scenario comparison — Base'!B10),0) -> 200 | P5: =IF(IF(IF(ISERROR(DATE(2027,12,1)>=DATE(YEAR('01 — Editable assumptions — USD'!B60),MONTH('01 — Editable assumptions — USD'!B60),1)),DATE(2027,12,1)>=DATE(YEAR('01 — Editable assumptions — USD'!B60),MONTH('01 — Editable assumptions — USD'!B60),1),IF(DATE(YEAR('01 — Editable assumptions — USD'!B60),MONTH('01 — Editable assumptions — USD'!B60),1)="","",DATE(2027,12,1)>=DATE(YEAR('01 — Editable assumptions — USD'!B60),MONTH('01 — Editable assumptions — USD'!B60),1)))="",FALSE,IF(ISERROR(DATE(2027,12,1)>=DATE(YEAR('01 — Editable assumptions — USD'!B60),MONTH('01 — Editable assumptions — USD'!B60),1)),DATE(2027,12,1)>=DATE(YEAR('01 — Editable assumptions — USD'!B60),MONTH('01 — Editable assumptions — USD'!B60),1),IF(DATE(YEAR('01 — Editable assumptions — USD'!B60),MONTH('01 — Editable assumptions — USD'!B60),1)="","",DATE(2027,12,1)>=DATE(YEAR('01 — Editable assumptions — USD'!B60),MONTH('01 — Editable assumptions — USD'!B60),1)))),IF('04 — Scenario comparison — Base'!B10="","",'04 — Scenario comparison — Base'!B10),0) -> 200
A6: TS Projected digital revenue | B6: ='07 — Cash projection — hypothet'!B5*'01 — Editable assumptions — USD'!B11 -> 0 | C6: ='07 — Cash projection — hypothet'!C5*'01 — Editable assumptions — USD'!B11 -> 0 | D6: ='07 — Cash projection — hypothet'!D5*'01 — Editable assumptions — USD'!B11 -> 0 | E6: ='07 — Cash projection — hypothet'!E5*'01 — Editable assumptions — USD'!B11 -> 1800 | F6: ='07 — Cash projection — hypothet'!F5*'01 — Editable assumptions — USD'!B11 -> 1800 | G6: ='07 — Cash projection — hypothet'!G5*'01 — Editable assumptions — USD'!B11 -> 1800 | H6: ='07 — Cash projection — hypothet'!H5*'01 — Editable assumptions — USD'!B11 -> 1800 | I6: ='07 — Cash projection — hypothet'!I5*'01 — Editable assumptions — USD'!B11 -> 1800 | J6: ='07 — Cash projection — hypothet'!J5*'01 — Editable assumptions — USD'!B11 -> 1800 | K6: ='07 — Cash projection — hypothet'!K5*'01 — Editable assumptions — USD'!B11 -> 1800 | L6: ='07 — Cash projection — hypothet'!L5*'01 — Editable assumptions — USD'!B11 -> 1800 | M6: ='07 — Cash projection — hypothet'!M5*'01 — Editable assumptions — USD'!B11 -> 1800 | N6: ='07 — Cash projection — hypothet'!N5*'01 — Editable assumptions — USD'!B11 -> 1800 | O6: ='07 — Cash projection — hypothet'!O5*'01 — Editable assumptions — USD'!B11 -> 1800 | P6: ='07 — Cash projection — hypothet'!P5*'01 — Editable assumptions — USD'!B11 -> 1800
A7: TS Projected variable costs | B7: =IF(IF(IF(ISERROR(DATE(2026,10,1)>=DATE(YEAR('01 — Editable assumptions — USD'!B60),MONTH('01 — Editable assumptions — USD'!B60),1)),DATE(2026,10,1)>=DATE(YEAR('01 — Editable assumptions — USD'!B60),MONTH('01 — Editable assumptions — USD'!B60),1),IF(DATE(YEAR('01 — Editable assumptions — USD'!B60),MONTH('01 — Editable assumptions — USD'!B60),1)="","",DATE(2026,10,1)>=DATE(YEAR('01 — Editable assumptions — USD'!B60),MONTH('01 — Editable assumptions — USD'!B60),1)))="",FALSE,IF(ISERROR(DATE(2026,10,1)>=DATE(YEAR('01 — Editable assumptions — USD'!B60),MONTH('01 — Editable assumptions — USD'!B60),1)),DATE(2026,10,1)>=DATE(YEAR('01 — Editable assumptions — USD'!B60),MONTH('01 — Editable assumptions — USD'!B60),1),IF(DATE(YEAR('01 — Editable assumptions — USD'!B60),MONTH('01 — Editable assumptions — USD'!B60),1)="","",DATE(2026,10,1)>=DATE(YEAR('01 — Editable assumptions — USD'!B60),MONTH('01 — Editable assumptions — USD'!B60),1)))),IF('03 — Digital unit economics and'!B21="","",'03 — Digital unit economics and'!B21),0) -> 0 | C7: =IF(IF(IF(ISERROR(DATE(2026,11,1)>=DATE(YEAR('01 — Editable assumptions — USD'!B60),MONTH('01 — Editable assumptions — USD'!B60),1)),DATE(2026,11,1)>=DATE(YEAR('01 — Editable assumptions — USD'!B60),MONTH('01 — Editable assumptions — USD'!B60),1),IF(DATE(YEAR('01 — Editable assumptions — USD'!B60),MONTH('01 — Editable assumptions — USD'!B60),1)="","",DATE(2026,11,1)>=DATE(YEAR('01 — Editable assumptions — USD'!B60),MONTH('01 — Editable assumptions — USD'!B60),1)))="",FALSE,IF(ISERROR(DATE(2026,11,1)>=DATE(YEAR('01 — Editable assumptions — USD'!B60),MONTH('01 — Editable assumptions — USD'!B60),1)),DATE(2026,11,1)>=DATE(YEAR('01 — Editable assumptions — USD'!B60),MONTH('01 — Editable assumptions — USD'!B60),1),IF(DATE(YEAR('01 — Editable assumptions — USD'!B60),MONTH('01 — Editable assumptions — USD'!B60),1)="","",DATE(2026,11,1)>=DATE(YEAR('01 — Editable assumptions — USD'!B60),MONTH('01 — Editable assumptions — USD'!B60),1)))),IF('03 — Digital unit economics and'!B21="","",'03 — Digital unit economics and'!B21),0) -> 0 | D7: =IF(IF(IF(ISERROR(DATE(2026,12,1)>=DATE(YEAR('01 — Editable assumptions — USD'!B60),MONTH('01 — Editable assumptions — USD'!B60),1)),DATE(2026,12,1)>=DATE(YEAR('01 — Editable assumptions — USD'!B60),MONTH('01 — Editable assumptions — USD'!B60),1),IF(DATE(YEAR('01 — Editable assumptions — USD'!B60),MONTH('01 — Editable assumptions — USD'!B60),1)="","",DATE(2026,12,1)>=DATE(YEAR('01 — Editable assumptions — USD'!B60),MONTH('01 — Editable assumptions — USD'!B60),1)))="",FALSE,IF(ISERROR(DATE(2026,12,1)>=DATE(YEAR('01 — Editable assumptions — USD'!B60),MONTH('01 — Editable assumptions — USD'!B60),1)),DATE(2026,12,1)>=DATE(YEAR('01 — Editable assumptions — USD'!B60),MONTH('01 — Editable assumptions — USD'!B60),1),IF(DATE(YEAR('01 — Editable assumptions — USD'!B60),MONTH('01 — Editable assumptions — USD'!B60),1)="","",DATE(2026,12,1)>=DATE(YEAR('01 — Editable assumptions — USD'!B60),MONTH('01 — Editable assumptions — USD'!B60),1)))),IF('03 — Digital unit economics and'!B21="","",'03 — Digital unit economics and'!B21),0) -> 0 | E7: =IF(IF(IF(ISERROR(DATE(2027,1,1)>=DATE(YEAR('01 — Editable assumptions — USD'!B60),MONTH('01 — Editable assumptions — USD'!B60),1)),DATE(2027,1,1)>=DATE(YEAR('01 — Editable assumptions — USD'!B60),MONTH('01 — Editable assumptions — USD'!B60),1),IF(DATE(YEAR('01 — Editable assumptions — USD'!B60),MONTH('01 — Editable assumptions — USD'!B60),1)="","",DATE(2027,1,1)>=DATE(YEAR('01 — Editable assumptions — USD'!B60),MONTH('01 — Editable assumptions — USD'!B60),1)))="",FALSE,IF(ISERROR(DATE(2027,1,1)>=DATE(YEAR('01 — Editable assumptions — USD'!B60),MONTH('01 — Editable assumptions — USD'!B60),1)),DATE(2027,1,1)>=DATE(YEAR('01 — Editable assumptions — USD'!B60),MONTH('01 — Editable assumptions — USD'!B60),1),IF(DATE(YEAR('01 — Editable assumptions — USD'!B60),MONTH('01 — Editable assumptions — USD'!B60),1)="","",DATE(2027,1,1)>=DATE(YEAR('01 — Editable assumptions — USD'!B60),MONTH('01 — Editable assumptions — USD'!B60),1)))),IF('03 — Digital unit economics and'!B21="","",'03 — Digital unit economics and'!B21),0) -> 497.19 | F7: =IF(IF(IF(ISERROR(DATE(2027,2,1)>=DATE(YEAR('01 — Editable assumptions — USD'!B60),MONTH('01 — Editable assumptions — USD'!B60),1)),DATE(2027,2,1)>=DATE(YEAR('01 — Editable assumptions — USD'!B60),MONTH('01 — Editable assumptions — USD'!B60),1),IF(DATE(YEAR('01 — Editable assumptions — USD'!B60),MONTH('01 — Editable assumptions — USD'!B60),1)="","",DATE(2027,2,1)>=DATE(YEAR('01 — Editable assumptions — USD'!B60),MONTH('01 — Editable assumptions — USD'!B60),1)))="",FALSE,IF(ISERROR(DATE(2027,2,1)>=DATE(YEAR('01 — Editable assumptions — USD'!B60),MONTH('01 — Editable assumptions — USD'!B60),1)),DATE(2027,2,1)>=DATE(YEAR('01 — Editable assumptions — USD'!B60),MONTH('01 — Editable assumptions — USD'!B60),1),IF(DATE(YEAR('01 — Editable assumptions — USD'!B60),MONTH('01 — Editable assumptions — USD'!B60),1)="","",DATE(2027,2,1)>=DATE(YEAR('01 — Editable assumptions — USD'!B60),MONTH('01 — Editable assumptions — USD'!B60),1)))),IF('03 — Digital unit economics and'!B21="","",'03 — Digital unit economics and'!B21),0) -> 497.19 | G7: =IF(IF(IF(ISERROR(DATE(2027,3,1)>=DATE(YEAR('01 — Editable assumptions — USD'!B60),MONTH('01 — Editable assumptions — USD'!B60),1)),DATE(2027,3,1)>=DATE(YEAR('01 — Editable assumptions — USD'!B60),MONTH('01 — Editable assumptions — USD'!B60),1),IF(DATE(YEAR('01 — Editable assumptions — USD'!B60),MONTH('01 — Editable assumptions — USD'!B60),1)="","",DATE(2027,3,1)>=DATE(YEAR('01 — Editable assumptions — USD'!B60),MONTH('01 — Editable assumptions — USD'!B60),1)))="",FALSE,IF(ISERROR(DATE(2027,3,1)>=DATE(YEAR('01 — Editable assumptions — USD'!B60),MONTH('01 — Editable assumptions — USD'!B60),1)),DATE(2027,3,1)>=DATE(YEAR('01 — Editable assumptions — USD'!B60),MONTH('01 — Editable assumptions — USD'!B60),1),IF(DATE(YEAR('01 — Editable assumptions — USD'!B60),MONTH('01 — Editable assumptions — USD'!B60),1)="","",DATE(2027,3,1)>=DATE(YEAR('01 — Editable assumptions — USD'!B60),MONTH('01 — Editable assumptions — USD'!B60),1)))),IF('03 — Digital unit economics and'!B21="","",'03 — Digital unit economics and'!B21),0) -> 497.19 | H7: =IF(IF(IF(ISERROR(DATE(2027,4,1)>=DATE(YEAR('01 — Editable assumptions — USD'!B60),MONTH('01 — Editable assumptions — USD'!B60),1)),DATE(2027,4,1)>=DATE(YEAR('01 — Editable assumptions — USD'!B60),MONTH('01 — Editable assumptions — USD'!B60),1),IF(DATE(YEAR('01 — Editable assumptions — USD'!B60),MONTH('01 — Editable assumptions — USD'!B60),1)="","",DATE(2027,4,1)>=DATE(YEAR('01 — Editable assumptions — USD'!B60),MONTH('01 — Editable assumptions — USD'!B60),1)))="",FALSE,IF(ISERROR(DATE(2027,4,1)>=DATE(YEAR('01 — Editable assumptions — USD'!B60),MONTH('01 — Editable assumptions — USD'!B60),1)),DATE(2027,4,1)>=DATE(YEAR('01 — Editable assumptions — USD'!B60),MONTH('01 — Editable assumptions — USD'!B60),1),IF(DATE(YEAR('01 — Editable assumptions — USD'!B60),MONTH('01 — Editable assumptions — USD'!B60),1)="","",DATE(2027,4,1)>=DATE(YEAR('01 — Editable assumptions — USD'!B60),MONTH('01 — Editable assumptions — USD'!B60),1)))),IF('03 — Digital unit economics and'!B21="","",'03 — Digital unit economics and'!B21),0) -> 497.19 | I7: =IF(IF(IF(ISERROR(DATE(2027,5,1)>=DATE(YEAR('01 — Editable assumptions — USD'!B60),MONTH('01 — Editable assumptions — USD'!B60),1)),DATE(2027,5,1)>=DATE(YEAR('01 — Editable assumptions — USD'!B60),MONTH('01 — Editable assumptions — USD'!B60),1),IF(DATE(YEAR('01 — Editable assumptions — USD'!B60),MONTH('01 — Editable assumptions — USD'!B60),1)="","",DATE(2027,5,1)>=DATE(YEAR('01 — Editable assumptions — USD'!B60),MONTH('01 — Editable assumptions — USD'!B60),1)))="",FALSE,IF(ISERROR(DATE(2027,5,1)>=DATE(YEAR('01 — Editable assumptions — USD'!B60),MONTH('01 — Editable assumptions — USD'!B60),1)),DATE(2027,5,1)>=DATE(YEAR('01 — Editable assumptions — USD'!B60),MONTH('01 — Editable assumptions — USD'!B60),1),IF(DATE(YEAR('01 — Editable assumptions — USD'!B60),MONTH('01 — Editable assumptions — USD'!B60),1)="","",DATE(2027,5,1)>=DATE(YEAR('01 — Editable assumptions — USD'!B60),MONTH('01 — Editable assumptions — USD'!B60),1)))),IF('03 — Digital unit economics and'!B21="","",'03 — Digital unit economics and'!B21),0) -> 497.19 | J7: =IF(IF(IF(ISERROR(DATE(2027,6,1)>=DATE(YEAR('01 — Editable assumptions — USD'!B60),MONTH('01 — Editable assumptions — USD'!B60),1)),DATE(2027,6,1)>=DATE(YEAR('01 — Editable assumptions — USD'!B60),MONTH('01 — Editable assumptions — USD'!B60),1),IF(DATE(YEAR('01 — Editable assumptions — USD'!B60),MONTH('01 — Editable assumptions — USD'!B60),1)="","",DATE(2027,6,1)>=DATE(YEAR('01 — Editable assumptions — USD'!B60),MONTH('01 — Editable assumptions — USD'!B60),1)))="",FALSE,IF(ISERROR(DATE(2027,6,1)>=DATE(YEAR('01 — Editable assumptions — USD'!B60),MONTH('01 — Editable assumptions — USD'!B60),1)),DATE(2027,6,1)>=DATE(YEAR('01 — Editable assumptions — USD'!B60),MONTH('01 — Editable assumptions — USD'!B60),1),IF(DATE(YEAR('01 — Editable assumptions — USD'!B60),MONTH('01 — Editable assumptions — USD'!B60),1)="","",DATE(2027,6,1)>=DATE(YEAR('01 — Editable assumptions — USD'!B60),MONTH('01 — Editable assumptions — USD'!B60),1)))),IF('03 — Digital unit economics and'!B21="","",'03 — Digital unit economics and'!B21),0) -> 497.19 | K7: =IF(IF(IF(ISERROR(DATE(2027,7,1)>=DATE(YEAR('01 — Editable assumptions — USD'!B60),MONTH('01 — Editable assumptions — USD'!B60),1)),DATE(2027,7,1)>=DATE(YEAR('01 — Editable assumptions — USD'!B60),MONTH('01 — Editable assumptions — USD'!B60),1),IF(DATE(YEAR('01 — Editable assumptions — USD'!B60),MONTH('01 — Editable assumptions — USD'!B60),1)="","",DATE(2027,7,1)>=DATE(YEAR('01 — Editable assumptions — USD'!B60),MONTH('01 — Editable assumptions — USD'!B60),1)))="",FALSE,IF(ISERROR(DATE(2027,7,1)>=DATE(YEAR('01 — Editable assumptions — USD'!B60),MONTH('01 — Editable assumptions — USD'!B60),1)),DATE(2027,7,1)>=DATE(YEAR('01 — Editable assumptions — USD'!B60),MONTH('01 — Editable assumptions — USD'!B60),1),IF(DATE(YEAR('01 — Editable assumptions — USD'!B60),MONTH('01 — Editable assumptions — USD'!B60),1)="","",DATE(2027,7,1)>=DATE(YEAR('01 — Editable assumptions — USD'!B60),MONTH('01 — Editable assumptions — USD'!B60),1)))),IF('03 — Digital unit economics and'!B21="","",'03 — Digital unit economics and'!B21),0) -> 497.19 | L7: =IF(IF(IF(ISERROR(DATE(2027,8,1)>=DATE(YEAR('01 — Editable assumptions — USD'!B60),MONTH('01 — Editable assumptions — USD'!B60),1)),DATE(2027,8,1)>=DATE(YEAR('01 — Editable assumptions — USD'!B60),MONTH('01 — Editable assumptions — USD'!B60),1),IF(DATE(YEAR('01 — Editable assumptions — USD'!B60),MONTH('01 — Editable assumptions — USD'!B60),1)="","",DATE(2027,8,1)>=DATE(YEAR('01 — Editable assumptions — USD'!B60),MONTH('01 — Editable assumptions — USD'!B60),1)))="",FALSE,IF(ISERROR(DATE(2027,8,1)>=DATE(YEAR('01 — Editable assumptions — USD'!B60),MONTH('01 — Editable assumptions — USD'!B60),1)),DATE(2027,8,1)>=DATE(YEAR('01 — Editable assumptions — USD'!B60),MONTH('01 — Editable assumptions — USD'!B60),1),IF(DATE(YEAR('01 — Editable assumptions — USD'!B60),MONTH('01 — Editable assumptions — USD'!B60),1)="","",DATE(2027,8,1)>=DATE(YEAR('01 — Editable assumptions — USD'!B60),MONTH('01 — Editable assumptions — USD'!B60),1)))),IF('03 — Digital unit economics and'!B21="","",'03 — Digital unit economics and'!B21),0) -> 497.19 | M7: =IF(IF(IF(ISERROR(DATE(2027,9,1)>=DATE(YEAR('01 — Editable assumptions — USD'!B60),MONTH('01 — Editable assumptions — USD'!B60),1)),DATE(2027,9,1)>=DATE(YEAR('01 — Editable assumptions — USD'!B60),MONTH('01 — Editable assumptions — USD'!B60),1),IF(DATE(YEAR('01 — Editable assumptions — USD'!B60),MONTH('01 — Editable assumptions — USD'!B60),1)="","",DATE(2027,9,1)>=DATE(YEAR('01 — Editable assumptions — USD'!B60),MONTH('01 — Editable assumptions — USD'!B60),1)))="",FALSE,IF(ISERROR(DATE(2027,9,1)>=DATE(YEAR('01 — Editable assumptions — USD'!B60),MONTH('01 — Editable assumptions — USD'!B60),1)),DATE(2027,9,1)>=DATE(YEAR('01 — Editable assumptions — USD'!B60),MONTH('01 — Editable assumptions — USD'!B60),1),IF(DATE(YEAR('01 — Editable assumptions — USD'!B60),MONTH('01 — Editable assumptions — USD'!B60),1)="","",DATE(2027,9,1)>=DATE(YEAR('01 — Editable assumptions — USD'!B60),MONTH('01 — Editable assumptions — USD'!B60),1)))),IF('03 — Digital unit economics and'!B21="","",'03 — Digital unit economics and'!B21),0) -> 497.19 | N7: =IF(IF(IF(ISERROR(DATE(2027,10,1)>=DATE(YEAR('01 — Editable assumptions — USD'!B60),MONTH('01 — Editable assumptions — USD'!B60),1)),DATE(2027,10,1)>=DATE(YEAR('01 — Editable assumptions — USD'!B60),MONTH('01 — Editable assumptions — USD'!B60),1),IF(DATE(YEAR('01 — Editable assumptions — USD'!B60),MONTH('01 — Editable assumptions — USD'!B60),1)="","",DATE(2027,10,1)>=DATE(YEAR('01 — Editable assumptions — USD'!B60),MONTH('01 — Editable assumptions — USD'!B60),1)))="",FALSE,IF(ISERROR(DATE(2027,10,1)>=DATE(YEAR('01 — Editable assumptions — USD'!B60),MONTH('01 — Editable assumptions — USD'!B60),1)),DATE(2027,10,1)>=DATE(YEAR('01 — Editable assumptions — USD'!B60),MONTH('01 — Editable assumptions — USD'!B60),1),IF(DATE(YEAR('01 — Editable assumptions — USD'!B60),MONTH('01 — Editable assumptions — USD'!B60),1)="","",DATE(2027,10,1)>=DATE(YEAR('01 — Editable assumptions — USD'!B60),MONTH('01 — Editable assumptions — USD'!B60),1)))),IF('03 — Digital unit economics and'!B21="","",'03 — Digital unit economics and'!B21),0) -> 497.19 | O7: =IF(IF(IF(ISERROR(DATE(2027,11,1)>=DATE(YEAR('01 — Editable assumptions — USD'!B60),MONTH('01 — Editable assumptions — USD'!B60),1)),DATE(2027,11,1)>=DATE(YEAR('01 — Editable assumptions — USD'!B60),MONTH('01 — Editable assumptions — USD'!B60),1),IF(DATE(YEAR('01 — Editable assumptions — USD'!B60),MONTH('01 — Editable assumptions — USD'!B60),1)="","",DATE(2027,11,1)>=DATE(YEAR('01 — Editable assumptions — USD'!B60),MONTH('01 — Editable assumptions — USD'!B60),1)))="",FALSE,IF(ISERROR(DATE(2027,11,1)>=DATE(YEAR('01 — Editable assumptions — USD'!B60),MONTH('01 — Editable assumptions — USD'!B60),1)),DATE(2027,11,1)>=DATE(YEAR('01 — Editable assumptions — USD'!B60),MONTH('01 — Editable assumptions — USD'!B60),1),IF(DATE(YEAR('01 — Editable assumptions — USD'!B60),MONTH('01 — Editable assumptions — USD'!B60),1)="","",DATE(2027,11,1)>=DATE(YEAR('01 — Editable assumptions — USD'!B60),MONTH('01 — Editable assumptions — USD'!B60),1)))),IF('03 — Digital unit economics and'!B21="","",'03 — Digital unit economics and'!B21),0) -> 497.19 | P7: =IF(IF(IF(ISERROR(DATE(2027,12,1)>=DATE(YEAR('01 — Editable assumptions — USD'!B60),MONTH('01 — Editable assumptions — USD'!B60),1)),DATE(2027,12,1)>=DATE(YEAR('01 — Editable assumptions — USD'!B60),MONTH('01 — Editable assumptions — USD'!B60),1),IF(DATE(YEAR('01 — Editable assumptions — USD'!B60),MONTH('01 — Editable assumptions — USD'!B60),1)="","",DATE(2027,12,1)>=DATE(YEAR('01 — Editable assumptions — USD'!B60),MONTH('01 — Editable assumptions — USD'!B60),1)))="",FALSE,IF(ISERROR(DATE(2027,12,1)>=DATE(YEAR('01 — Editable assumptions — USD'!B60),MONTH('01 — Editable assumptions — USD'!B60),1)),DATE(2027,12,1)>=DATE(YEAR('01 — Editable assumptions — USD'!B60),MONTH('01 — Editable assumptions — USD'!B60),1),IF(DATE(YEAR('01 — Editable assumptions — USD'!B60),MONTH('01 — Editable assumptions — USD'!B60),1)="","",DATE(2027,12,1)>=DATE(YEAR('01 — Editable assumptions — USD'!B60),MONTH('01 — Editable assumptions — USD'!B60),1)))),IF('03 — Digital unit economics and'!B21="","",'03 — Digital unit economics and'!B21),0) -> 497.19
A8: TS Projected cash flow bootstrap | B8: ='07 — Cash projection — hypothet'!B6-'07 — Cash projection — hypothet'!B7-'04 — Scenario comparison — Base'!B17-'04 — Scenario comparison — Base'!B18-'01 — Editable assumptions — USD'!B36+'01 — Editable assumptions — USD'!B43+'01 — Editable assumptions — USD'!B44 -> -600 | C8: ='07 — Cash projection — hypothet'!C6-'07 — Cash projection — hypothet'!C7-'04 — Scenario comparison — Base'!B17-'04 — Scenario comparison — Base'!B18-'01 — Editable assumptions — USD'!B36+'01 — Editable assumptions — USD'!B43+'01 — Editable assumptions — USD'!B44 -> -600 | D8: ='07 — Cash projection — hypothet'!D6-'07 — Cash projection — hypothet'!D7-'04 — Scenario comparison — Base'!B17-'04 — Scenario comparison — Base'!B18-'01 — Editable assumptions — USD'!B36+'01 — Editable assumptions — USD'!B43+'01 — Editable assumptions — USD'!B44 -> -600 | E8: ='07 — Cash projection — hypothet'!E6-'07 — Cash projection — hypothet'!E7-'04 — Scenario comparison — Base'!B17-'04 — Scenario comparison — Base'!B18-'01 — Editable assumptions — USD'!B36+'01 — Editable assumptions — USD'!B43+'01 — Editable assumptions — USD'!B44 -> 702.81 | F8: ='07 — Cash projection — hypothet'!F6-'07 — Cash projection — hypothet'!F7-'04 — Scenario comparison — Base'!B17-'04 — Scenario comparison — Base'!B18-'01 — Editable assumptions — USD'!B36+'01 — Editable assumptions — USD'!B43+'01 — Editable assumptions — USD'!B44 -> 702.81 | G8: ='07 — Cash projection — hypothet'!G6-'07 — Cash projection — hypothet'!G7-'04 — Scenario comparison — Base'!B17-'04 — Scenario comparison — Base'!B18-'01 — Editable assumptions — USD'!B36+'01 — Editable assumptions — USD'!B43+'01 — Editable assumptions — USD'!B44 -> 702.81 | H8: ='07 — Cash projection — hypothet'!H6-'07 — Cash projection — hypothet'!H7-'04 — Scenario comparison — Base'!B17-'04 — Scenario comparison — Base'!B18-'01 — Editable assumptions — USD'!B36+'01 — Editable assumptions — USD'!B43+'01 — Editable assumptions — USD'!B44 -> 702.81 | I8: ='07 — Cash projection — hypothet'!I6-'07 — Cash projection — hypothet'!I7-'04 — Scenario comparison — Base'!B17-'04 — Scenario comparison — Base'!B18-'01 — Editable assumptions — USD'!B36+'01 — Editable assumptions — USD'!B43+'01 — Editable assumptions — USD'!B44 -> 702.81 | J8: ='07 — Cash projection — hypothet'!J6-'07 — Cash projection — hypothet'!J7-'04 — Scenario comparison — Base'!B17-'04 — Scenario comparison — Base'!B18-'01 — Editable assumptions — USD'!B36+'01 — Editable assumptions — USD'!B43+'01 — Editable assumptions — USD'!B44 -> 702.81 | K8: ='07 — Cash projection — hypothet'!K6-'07 — Cash projection — hypothet'!K7-'04 — Scenario comparison — Base'!B17-'04 — Scenario comparison — Base'!B18-'01 — Editable assumptions — USD'!B36+'01 — Editable assumptions — USD'!B43+'01 — Editable assumptions — USD'!B44 -> 702.81 | L8: ='07 — Cash projection — hypothet'!L6-'07 — Cash projection — hypothet'!L7-'04 — Scenario comparison — Base'!B17-'04 — Scenario comparison — Base'!B18-'01 — Editable assumptions — USD'!B36+'01 — Editable assumptions — USD'!B43+'01 — Editable assumptions — USD'!B44 -> 702.81 | M8: ='07 — Cash projection — hypothet'!M6-'07 — Cash projection — hypothet'!M7-'04 — Scenario comparison — Base'!B17-'04 — Scenario comparison — Base'!B18-'01 — Editable assumptions — USD'!B36+'01 — Editable assumptions — USD'!B43+'01 — Editable assumptions — USD'!B44 -> 702.81 | N8: ='07 — Cash projection — hypothet'!N6-'07 — Cash projection — hypothet'!N7-'04 — Scenario comparison — Base'!B17-'04 — Scenario comparison — Base'!B18-'01 — Editable assumptions — USD'!B36+'01 — Editable assumptions — USD'!B43+'01 — Editable assumptions — USD'!B44 -> 702.81 | O8: ='07 — Cash projection — hypothet'!O6-'07 — Cash projection — hypothet'!O7-'04 — Scenario comparison — Base'!B17-'04 — Scenario comparison — Base'!B18-'01 — Editable assumptions — USD'!B36+'01 — Editable assumptions — USD'!B43+'01 — Editable assumptions — USD'!B44 -> 702.81 | P8: ='07 — Cash projection — hypothet'!P6-'07 — Cash projection — hypothet'!P7-'04 — Scenario comparison — Base'!B17-'04 — Scenario comparison — Base'!B18-'01 — Editable assumptions — USD'!B36+'01 — Editable assumptions — USD'!B43+'01 — Editable assumptions — USD'!B44 -> 702.81
A9: TS Projected cash flow founder | B9: ='07 — Cash projection — hypothet'!B8+'01 — Editable assumptions — USD'!B36-'01 — Editable assumptions — USD'!B37 -> -3600 | C9: ='07 — Cash projection — hypothet'!C8+'01 — Editable assumptions — USD'!B36-'01 — Editable assumptions — USD'!B37 -> -3600 | D9: ='07 — Cash projection — hypothet'!D8+'01 — Editable assumptions — USD'!B36-'01 — Editable assumptions — USD'!B37 -> -3600 | E9: ='07 — Cash projection — hypothet'!E8+'01 — Editable assumptions — USD'!B36-'01 — Editable assumptions — USD'!B37 -> -2297.19 | F9: ='07 — Cash projection — hypothet'!F8+'01 — Editable assumptions — USD'!B36-'01 — Editable assumptions — USD'!B37 -> -2297.19 | G9: ='07 — Cash projection — hypothet'!G8+'01 — Editable assumptions — USD'!B36-'01 — Editable assumptions — USD'!B37 -> -2297.19 | H9: ='07 — Cash projection — hypothet'!H8+'01 — Editable assumptions — USD'!B36-'01 — Editable assumptions — USD'!B37 -> -2297.19 | I9: ='07 — Cash projection — hypothet'!I8+'01 — Editable assumptions — USD'!B36-'01 — Editable assumptions — USD'!B37 -> -2297.19 | J9: ='07 — Cash projection — hypothet'!J8+'01 — Editable assumptions — USD'!B36-'01 — Editable assumptions — USD'!B37 -> -2297.19 | K9: ='07 — Cash projection — hypothet'!K8+'01 — Editable assumptions — USD'!B36-'01 — Editable assumptions — USD'!B37 -> -2297.19 | L9: ='07 — Cash projection — hypothet'!L8+'01 — Editable assumptions — USD'!B36-'01 — Editable assumptions — USD'!B37 -> -2297.19 | M9: ='07 — Cash projection — hypothet'!M8+'01 — Editable assumptions — USD'!B36-'01 — Editable assumptions — USD'!B37 -> -2297.19 | N9: ='07 — Cash projection — hypothet'!N8+'01 — Editable assumptions — USD'!B36-'01 — Editable assumptions — USD'!B37 -> -2297.19 | O9: ='07 — Cash projection — hypothet'!O8+'01 — Editable assumptions — USD'!B36-'01 — Editable assumptions — USD'!B37 -> -2297.19 | P9: ='07 — Cash projection — hypothet'!P8+'01 — Editable assumptions — USD'!B36-'01 — Editable assumptions — USD'!B37 -> -2297.19
A10: TS Projected cash bootstrap | B10: =IF(IF(IF(IF(ISERROR(DATE(2026,10,1)=DATE(YEAR('01 — Editable assumptions — USD'!B61),MONTH('01 — Editable assumptions — USD'!B61),1)),DATE(2026,10,1)=DATE(YEAR('01 — Editable assumptions — USD'!B61),MONTH('01 — Editable assumptions — USD'!B61),1),IF(DATE(YEAR('01 — Editable assumptions — USD'!B61),MONTH('01 — Editable assumptions — USD'!B61),1)="","",DATE(2026,10,1)=DATE(YEAR('01 — Editable assumptions — USD'!B61),MONTH('01 — Editable assumptions — USD'!B61),1)))="",FALSE,IF(ISERROR(DATE(2026,10,1)=DATE(YEAR('01 — Editable assumptions — USD'!B61),MONTH('01 — Editable assumptions — USD'!B61),1)),DATE(2026,10,1)=DATE(YEAR('01 — Editable assumptions — USD'!B61),MONTH('01 — Editable assumptions — USD'!B61),1),IF(DATE(YEAR('01 — Editable assumptions — USD'!B61),MONTH('01 — Editable assumptions — USD'!B61),1)="","",DATE(2026,10,1)=DATE(YEAR('01 — Editable assumptions — USD'!B61),MONTH('01 — Editable assumptions — USD'!B61),1)))),IF('04 — Scenario comparison — Base'!B24="","",'04 — Scenario comparison — Base'!B24),IF('Model inputs'!D98="","",'Model inputs'!D98))="",0,IF(IF(IF(ISERROR(DATE(2026,10,1)=DATE(YEAR('01 — Editable assumptions — USD'!B61),MONTH('01 — Editable assumptions — USD'!B61),1)),DATE(2026,10,1)=DATE(YEAR('01 — Editable assumptions — USD'!B61),MONTH('01 — Editable assumptions — USD'!B61),1),IF(DATE(YEAR('01 — Editable assumptions — USD'!B61),MONTH('01 — Editable assumptions — USD'!B61),1)="","",DATE(2026,10,1)=DATE(YEAR('01 — Editable assumptions — USD'!B61),MONTH('01 — Editable assumptions — USD'!B61),1)))="",FALSE,IF(ISERROR(DATE(2026,10,1)=DATE(YEAR('01 — Editable assumptions — USD'!B61),MONTH('01 — Editable assumptions — USD'!B61),1)),DATE(2026,10,1)=DATE(YEAR('01 — Editable assumptions — USD'!B61),MONTH('01 — Editable assumptions — USD'!B61),1),IF(DATE(YEAR('01 — Editable assumptions — USD'!B61),MONTH('01 — Editable assumptions — USD'!B61),1)="","",DATE(2026,10,1)=DATE(YEAR('01 — Editable assumptions — USD'!B61),MONTH('01 — Editable assumptions — USD'!B61),1)))),IF('04 — Scenario comparison — Base'!B24="","",'04 — Scenario comparison — Base'!B24),IF('Model inputs'!D98="","",'Model inputs'!D98)))+'07 — Cash projection — hypothet'!B8 -> 400 | C10: =IF(IF(IF(IF(ISERROR(DATE(2026,11,1)=DATE(YEAR('01 — Editable assumptions — USD'!B61),MONTH('01 — Editable assumptions — USD'!B61),1)),DATE(2026,11,1)=DATE(YEAR('01 — Editable assumptions — USD'!B61),MONTH('01 — Editable assumptions — USD'!B61),1),IF(DATE(YEAR('01 — Editable assumptions — USD'!B61),MONTH('01 — Editable assumptions — USD'!B61),1)="","",DATE(2026,11,1)=DATE(YEAR('01 — Editable assumptions — USD'!B61),MONTH('01 — Editable assumptions — USD'!B61),1)))="",FALSE,IF(ISERROR(DATE(2026,11,1)=DATE(YEAR('01 — Editable assumptions — USD'!B61),MONTH('01 — Editable assumptions — USD'!B61),1)),DATE(2026,11,1)=DATE(YEAR('01 — Editable assumptions — USD'!B61),MONTH('01 — Editable assumptions — USD'!B61),1),IF(DATE(YEAR('01 — Editable assumptions — USD'!B61),MONTH('01 — Editable assumptions — USD'!B61),1)="","",DATE(2026,11,1)=DATE(YEAR('01 — Editable assumptions — USD'!B61),MONTH('01 — Editable assumptions — USD'!B61),1)))),IF('04 — Scenario comparison — Base'!B24="","",'04 — Scenario comparison — Base'!B24),IF('07 — Cash projection — hypothet'!B10="","",'07 — Cash projection — hypothet'!B10))="",0,IF(IF(IF(ISERROR(DATE(2026,11,1)=DATE(YEAR('01 — Editable assumptions — USD'!B61),MONTH('01 — Editable assumptions — USD'!B61),1)),DATE(2026,11,1)=DATE(YEAR('01 — Editable assumptions — USD'!B61),MONTH('01 — Editable assumptions — USD'!B61),1),IF(DATE(YEAR('01 — Editable assumptions — USD'!B61),MONTH('01 — Editable assumptions — USD'!B61),1)="","",DATE(2026,11,1)=DATE(YEAR('01 — Editable assumptions — USD'!B61),MONTH('01 — Editable assumptions — USD'!B61),1)))="",FALSE,IF(ISERROR(DATE(2026,11,1)=DATE(YEAR('01 — Editable assumptions — USD'!B61),MONTH('01 — Editable assumptions — USD'!B61),1)),DATE(2026,11,1)=DATE(YEAR('01 — Editable assumptions — USD'!B61),MONTH('01 — Editable assumptions — USD'!B61),1),IF(DATE(YEAR('01 — Editable assumptions — USD'!B61),MONTH('01 — Editable assumptions — USD'!B61),1)="","",DATE(2026,11,1)=DATE(YEAR('01 — Editable assumptions — USD'!B61),MONTH('01 — Editable assumptions — USD'!B61),1)))),IF('04 — Scenario comparison — Base'!B24="","",'04 — Scenario comparison — Base'!B24),IF('07 — Cash projection — hypothet'!B10="","",'07 — Cash projection — hypothet'!B10)))+'07 — Cash projection — hypothet'!C8 -> -200 | D10: =IF(IF(IF(IF(ISERROR(DATE(2026,12,1)=DATE(YEAR('01 — Editable assumptions — USD'!B61),MONTH('01 — Editable assumptions — USD'!B61),1)),DATE(2026,12,1)=DATE(YEAR('01 — Editable assumptions — USD'!B61),MONTH('01 — Editable assumptions — USD'!B61),1),IF(DATE(YEAR('01 — Editable assumptions — USD'!B61),MONTH('01 — Editable assumptions — USD'!B61),1)="","",DATE(2026,12,1)=DATE(YEAR('01 — Editable assumptions — USD'!B61),MONTH('01 — Editable assumptions — USD'!B61),1)))="",FALSE,IF(ISERROR(DATE(2026,12,1)=DATE(YEAR('01 — Editable assumptions — USD'!B61),MONTH('01 — Editable assumptions — USD'!B61),1)),DATE(2026,12,1)=DATE(YEAR('01 — Editable assumptions — USD'!B61),MONTH('01 — Editable assumptions — USD'!B61),1),IF(DATE(YEAR('01 — Editable assumptions — USD'!B61),MONTH('01 — Editable assumptions — USD'!B61),1)="","",DATE(2026,12,1)=DATE(YEAR('01 — Editable assumptions — USD'!B61),MONTH('01 — Editable assumptions — USD'!B61),1)))),IF('04 — Scenario comparison — Base'!B24="","",'04 — Scenario comparison — Base'!B24),IF('07 — Cash projection — hypothet'!C10="","",'07 — Cash projection — hypothet'!C10))="",0,IF(IF(IF(ISERROR(DATE(2026,12,1)=DATE(YEAR('01 — Editable assumptions — USD'!B61),MONTH('01 — Editable assumptions — USD'!B61),1)),DATE(2026,12,1)=DATE(YEAR('01 — Editable assumptions — USD'!B61),MONTH('01 — Editable assumptions — USD'!B61),1),IF(DATE(YEAR('01 — Editable assumptions — USD'!B61),MONTH('01 — Editable assumptions — USD'!B61),1)="","",DATE(2026,12,1)=DATE(YEAR('01 — Editable assumptions — USD'!B61),MONTH('01 — Editable assumptions — USD'!B61),1)))="",FALSE,IF(ISERROR(DATE(2026,12,1)=DATE(YEAR('01 — Editable assumptions — USD'!B61),MONTH('01 — Editable assumptions — USD'!B61),1)),DATE(2026,12,1)=DATE(YEAR('01 — Editable assumptions — USD'!B61),MONTH('01 — Editable assumptions — USD'!B61),1),IF(DATE(YEAR('01 — Editable assumptions — USD'!B61),MONTH('01 — Editable assumptions — USD'!B61),1)="","",DATE(2026,12,1)=DATE(YEAR('01 — Editable assumptions — USD'!B61),MONTH('01 — Editable assumptions — USD'!B61),1)))),IF('04 — Scenario comparison — Base'!B24="","",'04 — Scenario comparison — Base'!B24),IF('07 — Cash projection — hypothet'!C10="","",'07 — Cash projection — hypothet'!C10)))+'07 — Cash projection — hypothet'!D8 -> -800 | E10: =IF(IF(IF(IF(ISERROR(DATE(2027,1,1)=DATE(YEAR('01 — Editable assumptions — USD'!B61),MONTH('01 — Editable assumptions — USD'!B61),1)),DATE(2027,1,1)=DATE(YEAR('01 — Editable assumptions — USD'!B61),MONTH('01 — Editable assumptions — USD'!B61),1),IF(DATE(YEAR('01 — Editable assumptions — USD'!B61),MONTH('01 — Editable assumptions — USD'!B61),1)="","",DATE(2027,1,1)=DATE(YEAR('01 — Editable assumptions — USD'!B61),MONTH('01 — Editable assumptions — USD'!B61),1)))="",FALSE,IF(ISERROR(DATE(2027,1,1)=DATE(YEAR('01 — Editable assumptions — USD'!B61),MONTH('01 — Editable assumptions — USD'!B61),1)),DATE(2027,1,1)=DATE(YEAR('01 — Editable assumptions — USD'!B61),MONTH('01 — Editable assumptions — USD'!B61),1),IF(DATE(YEAR('01 — Editable assumptions — USD'!B61),MONTH('01 — Editable assumptions — USD'!B61),1)="","",DATE(2027,1,1)=DATE(YEAR('01 — Editable assumptions — USD'!B61),MONTH('01 — Editable assumptions — USD'!B61),1)))),IF('04 — Scenario comparison — Base'!B24="","",'04 — Scenario comparison — Base'!B24),IF('07 — Cash projection — hypothet'!D10="","",'07 — Cash projection — hypothet'!D10))="",0,IF(IF(IF(ISERROR(DATE(2027,1,1)=DATE(YEAR('01 — Editable assumptions — USD'!B61),MONTH('01 — Editable assumptions — USD'!B61),1)),DATE(2027,1,1)=DATE(YEAR('01 — Editable assumptions — USD'!B61),MONTH('01 — Editable assumptions — USD'!B61),1),IF(DATE(YEAR('01 — Editable assumptions — USD'!B61),MONTH('01 — Editable assumptions — USD'!B61),1)="","",DATE(2027,1,1)=DATE(YEAR('01 — Editable assumptions — USD'!B61),MONTH('01 — Editable assumptions — USD'!B61),1)))="",FALSE,IF(ISERROR(DATE(2027,1,1)=DATE(YEAR('01 — Editable assumptions — USD'!B61),MONTH('01 — Editable assumptions — USD'!B61),1)),DATE(2027,1,1)=DATE(YEAR('01 — Editable assumptions — USD'!B61),MONTH('01 — Editable assumptions — USD'!B61),1),IF(DATE(YEAR('01 — Editable assumptions — USD'!B61),MONTH('01 — Editable assumptions — USD'!B61),1)="","",DATE(2027,1,1)=DATE(YEAR('01 — Editable assumptions — USD'!B61),MONTH('01 — Editable assumptions — USD'!B61),1)))),IF('04 — Scenario comparison — Base'!B24="","",'04 — Scenario comparison — Base'!B24),IF('07 — Cash projection — hypothet'!D10="","",'07 — Cash projection — hypothet'!D10)))+'07 — Cash projection — hypothet'!E8 -> -97.19 | F10: =IF(IF(IF(IF(ISERROR(DATE(2027,2,1)=DATE(YEAR('01 — Editable assumptions — USD'!B61),MONTH('01 — Editable assumptions — USD'!B61),1)),DATE(2027,2,1)=DATE(YEAR('01 — Editable assumptions — USD'!B61),MONTH('01 — Editable assumptions — USD'!B61),1),IF(DATE(YEAR('01 — Editable assumptions — USD'!B61),MONTH('01 — Editable assumptions — USD'!B61),1)="","",DATE(2027,2,1)=DATE(YEAR('01 — Editable assumptions — USD'!B61),MONTH('01 — Editable assumptions — USD'!B61),1)))="",FALSE,IF(ISERROR(DATE(2027,2,1)=DATE(YEAR('01 — Editable assumptions — USD'!B61),MONTH('01 — Editable assumptions — USD'!B61),1)),DATE(2027,2,1)=DATE(YEAR('01 — Editable assumptions — USD'!B61),MONTH('01 — Editable assumptions — USD'!B61),1),IF(DATE(YEAR('01 — Editable assumptions — USD'!B61),MONTH('01 — Editable assumptions — USD'!B61),1)="","",DATE(2027,2,1)=DATE(YEAR('01 — Editable assumptions — USD'!B61),MONTH('01 — Editable assumptions — USD'!B61),1)))),IF('04 — Scenario comparison — Base'!B24="","",'04 — Scenario comparison — Base'!B24),IF('07 — Cash projection — hypothet'!E10="","",'07 — Cash projection — hypothet'!E10))="",0,IF(IF(IF(ISERROR(DATE(2027,2,1)=DATE(YEAR('01 — Editable assumptions — USD'!B61),MONTH('01 — Editable assumptions — USD'!B61),1)),DATE(2027,2,1)=DATE(YEAR('01 — Editable assumptions — USD'!B61),MONTH('01 — Editable assumptions — USD'!B61),1),IF(DATE(YEAR('01 — Editable assumptions — USD'!B61),MONTH('01 — Editable assumptions — USD'!B61),1)="","",DATE(2027,2,1)=DATE(YEAR('01 — Editable assumptions — USD'!B61),MONTH('01 — Editable assumptions — USD'!B61),1)))="",FALSE,IF(ISERROR(DATE(2027,2,1)=DATE(YEAR('01 — Editable assumptions — USD'!B61),MONTH('01 — Editable assumptions — USD'!B61),1)),DATE(2027,2,1)=DATE(YEAR('01 — Editable assumptions — USD'!B61),MONTH('01 — Editable assumptions — USD'!B61),1),IF(DATE(YEAR('01 — Editable assumptions — USD'!B61),MONTH('01 — Editable assumptions — USD'!B61),1)="","",DATE(2027,2,1)=DATE(YEAR('01 — Editable assumptions — USD'!B61),MONTH('01 — Editable assumptions — USD'!B61),1)))),IF('04 — Scenario comparison — Base'!B24="","",'04 — Scenario comparison — Base'!B24),IF('07 — Cash projection — hypothet'!E10="","",'07 — Cash projection — hypothet'!E10)))+'07 — Cash projection — hypothet'!F8 -> 605.62 | G10: =IF(IF(IF(IF(ISERROR(DATE(2027,3,1)=DATE(YEAR('01 — Editable assumptions — USD'!B61),MONTH('01 — Editable assumptions — USD'!B61),1)),DATE(2027,3,1)=DATE(YEAR('01 — Editable assumptions — USD'!B61),MONTH('01 — Editable assumptions — USD'!B61),1),IF(DATE(YEAR('01 — Editable assumptions — USD'!B61),MONTH('01 — Editable assumptions — USD'!B61),1)="","",DATE(2027,3,1)=DATE(YEAR('01 — Editable assumptions — USD'!B61),MONTH('01 — Editable assumptions — USD'!B61),1)))="",FALSE,IF(ISERROR(DATE(2027,3,1)=DATE(YEAR('01 — Editable assumptions — USD'!B61),MONTH('01 — Editable assumptions — USD'!B61),1)),DATE(2027,3,1)=DATE(YEAR('01 — Editable assumptions — USD'!B61),MONTH('01 — Editable assumptions — USD'!B61),1),IF(DATE(YEAR('01 — Editable assumptions — USD'!B61),MONTH('01 — Editable assumptions — USD'!B61),1)="","",DATE(2027,3,1)=DATE(YEAR('01 — Editable assumptions — USD'!B61),MONTH('01 — Editable assumptions — USD'!B61),1)))),IF('04 — Scenario comparison — Base'!B24="","",'04 — Scenario comparison — Base'!B24),IF('07 — Cash projection — hypothet'!F10="","",'07 — Cash projection — hypothet'!F10))="",0,IF(IF(IF(ISERROR(DATE(2027,3,1)=DATE(YEAR('01 — Editable assumptions — USD'!B61),MONTH('01 — Editable assumptions — USD'!B61),1)),DATE(2027,3,1)=DATE(YEAR('01 — Editable assumptions — USD'!B61),MONTH('01 — Editable assumptions — USD'!B61),1),IF(DATE(YEAR('01 — Editable assumptions — USD'!B61),MONTH('01 — Editable assumptions — USD'!B61),1)="","",DATE(2027,3,1)=DATE(YEAR('01 — Editable assumptions — USD'!B61),MONTH('01 — Editable assumptions — USD'!B61),1)))="",FALSE,IF(ISERROR(DATE(2027,3,1)=DATE(YEAR('01 — Editable assumptions — USD'!B61),MONTH('01 — Editable assumptions — USD'!B61),1)),DATE(2027,3,1)=DATE(YEAR('01 — Editable assumptions — USD'!B61),MONTH('01 — Editable assumptions — USD'!B61),1),IF(DATE(YEAR('01 — Editable assumptions — USD'!B61),MONTH('01 — Editable assumptions — USD'!B61),1)="","",DATE(2027,3,1)=DATE(YEAR('01 — Editable assumptions — USD'!B61),MONTH('01 — Editable assumptions — USD'!B61),1)))),IF('04 — Scenario comparison — Base'!B24="","",'04 — Scenario comparison — Base'!B24),IF('07 — Cash projection — hypothet'!F10="","",'07 — Cash projection — hypothet'!F10)))+'07 — Cash projection — hypothet'!G8 -> 1308.43 | H10: =IF(IF(IF(IF(ISERROR(DATE(2027,4,1)=DATE(YEAR('01 — Editable assumptions — USD'!B61),MONTH('01 — Editable assumptions — USD'!B61),1)),DATE(2027,4,1)=DATE(YEAR('01 — Editable assumptions — USD'!B61),MONTH('01 — Editable assumptions — USD'!B61),1),IF(DATE(YEAR('01 — Editable assumptions — USD'!B61),MONTH('01 — Editable assumptions — USD'!B61),1)="","",DATE(2027,4,1)=DATE(YEAR('01 — Editable assumptions — USD'!B61),MONTH('01 — Editable assumptions — USD'!B61),1)))="",FALSE,IF(ISERROR(DATE(2027,4,1)=DATE(YEAR('01 — Editable assumptions — USD'!B61),MONTH('01 — Editable assumptions — USD'!B61),1)),DATE(2027,4,1)=DATE(YEAR('01 — Editable assumptions — USD'!B61),MONTH('01 — Editable assumptions — USD'!B61),1),IF(DATE(YEAR('01 — Editable assumptions — USD'!B61),MONTH('01 — Editable assumptions — USD'!B61),1)="","",DATE(2027,4,1)=DATE(YEAR('01 — Editable assumptions — USD'!B61),MONTH('01 — Editable assumptions — USD'!B61),1)))),IF('04 — Scenario comparison — Base'!B24="","",'04 — Scenario comparison — Base'!B24),IF('07 — Cash projection — hypothet'!G10="","",'07 — Cash projection — hypothet'!G10))="",0,IF(IF(IF(ISERROR(DATE(2027,4,1)=DATE(YEAR('01 — Editable assumptions — USD'!B61),MONTH('01 — Editable assumptions — USD'!B61),1)),DATE(2027,4,1)=DATE(YEAR('01 — Editable assumptions — USD'!B61),MONTH('01 — Editable assumptions — USD'!B61),1),IF(DATE(YEAR('01 — Editable assumptions — USD'!B61),MONTH('01 — Editable assumptions — USD'!B61),1)="","",DATE(2027,4,1)=DATE(YEAR('01 — Editable assumptions — USD'!B61),MONTH('01 — Editable assumptions — USD'!B61),1)))="",FALSE,IF(ISERROR(DATE(2027,4,1)=DATE(YEAR('01 — Editable assumptions — USD'!B61),MONTH('01 — Editable assumptions — USD'!B61),1)),DATE(2027,4,1)=DATE(YEAR('01 — Editable assumptions — USD'!B61),MONTH('01 — Editable assumptions — USD'!B61),1),IF(DATE(YEAR('01 — Editable assumptions — USD'!B61),MONTH('01 — Editable assumptions — USD'!B61),1)="","",DATE(2027,4,1)=DATE(YEAR('01 — Editable assumptions — USD'!B61),MONTH('01 — Editable assumptions — USD'!B61),1)))),IF('04 — Scenario comparison — Base'!B24="","",'04 — Scenario comparison — Base'!B24),IF('07 — Cash projection — hypothet'!G10="","",'07 — Cash projection — hypothet'!G10)))+'07 — Cash projection — hypothet'!H8 -> 2011.24 | I10: =IF(IF(IF(IF(ISERROR(DATE(2027,5,1)=DATE(YEAR('01 — Editable assumptions — USD'!B61),MONTH('01 — Editable assumptions — USD'!B61),1)),DATE(2027,5,1)=DATE(YEAR('01 — Editable assumptions — USD'!B61),MONTH('01 — Editable assumptions — USD'!B61),1),IF(DATE(YEAR('01 — Editable assumptions — USD'!B61),MONTH('01 — Editable assumptions — USD'!B61),1)="","",DATE(2027,5,1)=DATE(YEAR('01 — Editable assumptions — USD'!B61),MONTH('01 — Editable assumptions — USD'!B61),1)))="",FALSE,IF(ISERROR(DATE(2027,5,1)=DATE(YEAR('01 — Editable assumptions — USD'!B61),MONTH('01 — Editable assumptions — USD'!B61),1)),DATE(2027,5,1)=DATE(YEAR('01 — Editable assumptions — USD'!B61),MONTH('01 — Editable assumptions — USD'!B61),1),IF(DATE(YEAR('01 — Editable assumptions — USD'!B61),MONTH('01 — Editable assumptions — USD'!B61),1)="","",DATE(2027,5,1)=DATE(YEAR('01 — Editable assumptions — USD'!B61),MONTH('01 — Editable assumptions — USD'!B61),1)))),IF('04 — Scenario comparison — Base'!B24="","",'04 — Scenario comparison — Base'!B24),IF('07 — Cash projection — hypothet'!H10="","",'07 — Cash projection — hypothet'!H10))="",0,IF(IF(IF(ISERROR(DATE(2027,5,1)=DATE(YEAR('01 — Editable assumptions — USD'!B61),MONTH('01 — Editable assumptions — USD'!B61),1)),DATE(2027,5,1)=DATE(YEAR('01 — Editable assumptions — USD'!B61),MONTH('01 — Editable assumptions — USD'!B61),1),IF(DATE(YEAR('01 — Editable assumptions — USD'!B61),MONTH('01 — Editable assumptions — USD'!B61),1)="","",DATE(2027,5,1)=DATE(YEAR('01 — Editable assumptions — USD'!B61),MONTH('01 — Editable assumptions — USD'!B61),1)))="",FALSE,IF(ISERROR(DATE(2027,5,1)=DATE(YEAR('01 — Editable assumptions — USD'!B61),MONTH('01 — Editable assumptions — USD'!B61),1)),DATE(2027,5,1)=DATE(YEAR('01 — Editable assumptions — USD'!B61),MONTH('01 — Editable assumptions — USD'!B61),1),IF(DATE(YEAR('01 — Editable assumptions — USD'!B61),MONTH('01 — Editable assumptions — USD'!B61),1)="","",DATE(2027,5,1)=DATE(YEAR('01 — Editable assumptions — USD'!B61),MONTH('01 — Editable assumptions — USD'!B61),1)))),IF('04 — Scenario comparison — Base'!B24="","",'04 — Scenario comparison — Base'!B24),IF('07 — Cash projection — hypothet'!H10="","",'07 — Cash projection — hypothet'!H10)))+'07 — Cash projection — hypothet'!I8 -> 2714.05 | J10: =IF(IF(IF(IF(ISERROR(DATE(2027,6,1)=DATE(YEAR('01 — Editable assumptions — USD'!B61),MONTH('01 — Editable assumptions — USD'!B61),1)),DATE(2027,6,1)=DATE(YEAR('01 — Editable assumptions — USD'!B61),MONTH('01 — Editable assumptions — USD'!B61),1),IF(DATE(YEAR('01 — Editable assumptions — USD'!B61),MONTH('01 — Editable assumptions — USD'!B61),1)="","",DATE(2027,6,1)=DATE(YEAR('01 — Editable assumptions — USD'!B61),MONTH('01 — Editable assumptions — USD'!B61),1)))="",FALSE,IF(ISERROR(DATE(2027,6,1)=DATE(YEAR('01 — Editable assumptions — USD'!B61),MONTH('01 — Editable assumptions — USD'!B61),1)),DATE(2027,6,1)=DATE(YEAR('01 — Editable assumptions — USD'!B61),MONTH('01 — Editable assumptions — USD'!B61),1),IF(DATE(YEAR('01 — Editable assumptions — USD'!B61),MONTH('01 — Editable assumptions — USD'!B61),1)="","",DATE(2027,6,1)=DATE(YEAR('01 — Editable assumptions — USD'!B61),MONTH('01 — Editable assumptions — USD'!B61),1)))),IF('04 — Scenario comparison — Base'!B24="","",'04 — Scenario comparison — Base'!B24),IF('07 — Cash projection — hypothet'!I10="","",'07 — Cash projection — hypothet'!I10))="",0,IF(IF(IF(ISERROR(DATE(2027,6,1)=DATE(YEAR('01 — Editable assumptions — USD'!B61),MONTH('01 — Editable assumptions — USD'!B61),1)),DATE(2027,6,1)=DATE(YEAR('01 — Editable assumptions — USD'!B61),MONTH('01 — Editable assumptions — USD'!B61),1),IF(DATE(YEAR('01 — Editable assumptions — USD'!B61),MONTH('01 — Editable assumptions — USD'!B61),1)="","",DATE(2027,6,1)=DATE(YEAR('01 — Editable assumptions — USD'!B61),MONTH('01 — Editable assumptions — USD'!B61),1)))="",FALSE,IF(ISERROR(DATE(2027,6,1)=DATE(YEAR('01 — Editable assumptions — USD'!B61),MONTH('01 — Editable assumptions — USD'!B61),1)),DATE(2027,6,1)=DATE(YEAR('01 — Editable assumptions — USD'!B61),MONTH('01 — Editable assumptions — USD'!B61),1),IF(DATE(YEAR('01 — Editable assumptions — USD'!B61),MONTH('01 — Editable assumptions — USD'!B61),1)="","",DATE(2027,6,1)=DATE(YEAR('01 — Editable assumptions — USD'!B61),MONTH('01 — Editable assumptions — USD'!B61),1)))),IF('04 — Scenario comparison — Base'!B24="","",'04 — Scenario comparison — Base'!B24),IF('07 — Cash projection — hypothet'!I10="","",'07 — Cash projection — hypothet'!I10)))+'07 — Cash projection — hypothet'!J8 -> 3416.86 | K10: =IF(IF(IF(IF(ISERROR(DATE(2027,7,1)=DATE(YEAR('01 — Editable assumptions — USD'!B61),MONTH('01 — Editable assumptions — USD'!B61),1)),DATE(2027,7,1)=DATE(YEAR('01 — Editable assumptions — USD'!B61),MONTH('01 — Editable assumptions — USD'!B61),1),IF(DATE(YEAR('01 — Editable assumptions — USD'!B61),MONTH('01 — Editable assumptions — USD'!B61),1)="","",DATE(2027,7,1)=DATE(YEAR('01 — Editable assumptions — USD'!B61),MONTH('01 — Editable assumptions — USD'!B61),1)))="",FALSE,IF(ISERROR(DATE(2027,7,1)=DATE(YEAR('01 — Editable assumptions — USD'!B61),MONTH('01 — Editable assumptions — USD'!B61),1)),DATE(2027,7,1)=DATE(YEAR('01 — Editable assumptions — USD'!B61),MONTH('01 — Editable assumptions — USD'!B61),1),IF(DATE(YEAR('01 — Editable assumptions — USD'!B61),MONTH('01 — Editable assumptions — USD'!B61),1)="","",DATE(2027,7,1)=DATE(YEAR('01 — Editable assumptions — USD'!B61),MONTH('01 — Editable assumptions — USD'!B61),1)))),IF('04 — Scenario comparison — Base'!B24="","",'04 — Scenario comparison — Base'!B24),IF('07 — Cash projection — hypothet'!J10="","",'07 — Cash projection — hypothet'!J10))="",0,IF(IF(IF(ISERROR(DATE(2027,7,1)=DATE(YEAR('01 — Editable assumptions — USD'!B61),MONTH('01 — Editable assumptions — USD'!B61),1)),DATE(2027,7,1)=DATE(YEAR('01 — Editable assumptions — USD'!B61),MONTH('01 — Editable assumptions — USD'!B61),1),IF(DATE(YEAR('01 — Editable assumptions — USD'!B61),MONTH('01 — Editable assumptions — USD'!B61),1)="","",DATE(2027,7,1)=DATE(YEAR('01 — Editable assumptions — USD'!B61),MONTH('01 — Editable assumptions — USD'!B61),1)))="",FALSE,IF(ISERROR(DATE(2027,7,1)=DATE(YEAR('01 — Editable assumptions — USD'!B61),MONTH('01 — Editable assumptions — USD'!B61),1)),DATE(2027,7,1)=DATE(YEAR('01 — Editable assumptions — USD'!B61),MONTH('01 — Editable assumptions — USD'!B61),1),IF(DATE(YEAR('01 — Editable assumptions — USD'!B61),MONTH('01 — Editable assumptions — USD'!B61),1)="","",DATE(2027,7,1)=DATE(YEAR('01 — Editable assumptions — USD'!B61),MONTH('01 — Editable assumptions — USD'!B61),1)))),IF('04 — Scenario comparison — Base'!B24="","",'04 — Scenario comparison — Base'!B24),IF('07 — Cash projection — hypothet'!J10="","",'07 — Cash projection — hypothet'!J10)))+'07 — Cash projection — hypothet'!K8 -> 4119.67 | L10: =IF(IF(IF(IF(ISERROR(DATE(2027,8,1)=DATE(YEAR('01 — Editable assumptions — USD'!B61),MONTH('01 — Editable assumptions — USD'!B61),1)),DATE(2027,8,1)=DATE(YEAR('01 — Editable assumptions — USD'!B61),MONTH('01 — Editable assumptions — USD'!B61),1),IF(DATE(YEAR('01 — Editable assumptions — USD'!B61),MONTH('01 — Editable assumptions — USD'!B61),1)="","",DATE(2027,8,1)=DATE(YEAR('01 — Editable assumptions — USD'!B61),MONTH('01 — Editable assumptions — USD'!B61),1)))="",FALSE,IF(ISERROR(DATE(2027,8,1)=DATE(YEAR('01 — Editable assumptions — USD'!B61),MONTH('01 — Editable assumptions — USD'!B61),1)),DATE(2027,8,1)=DATE(YEAR('01 — Editable assumptions — USD'!B61),MONTH('01 — Editable assumptions — USD'!B61),1),IF(DATE(YEAR('01 — Editable assumptions — USD'!B61),MONTH('01 — Editable assumptions — USD'!B61),1)="","",DATE(2027,8,1)=DATE(YEAR('01 — Editable assumptions — USD'!B61),MONTH('01 — Editable assumptions — USD'!B61),1)))),IF('04 — Scenario comparison — Base'!B24="","",'04 — Scenario comparison — Base'!B24),IF('07 — Cash projection — hypothet'!K10="","",'07 — Cash projection — hypothet'!K10))="",0,IF(IF(IF(ISERROR(DATE(2027,8,1)=DATE(YEAR('01 — Editable assumptions — USD'!B61),MONTH('01 — Editable assumptions — USD'!B61),1)),DATE(2027,8,1)=DATE(YEAR('01 — Editable assumptions — USD'!B61),MONTH('01 — Editable assumptions — USD'!B61),1),IF(DATE(YEAR('01 — Editable assumptions — USD'!B61),MONTH('01 — Editable assumptions — USD'!B61),1)="","",DATE(2027,8,1)=DATE(YEAR('01 — Editable assumptions — USD'!B61),MONTH('01 — Editable assumptions — USD'!B61),1)))="",FALSE,IF(ISERROR(DATE(2027,8,1)=DATE(YEAR('01 — Editable assumptions — USD'!B61),MONTH('01 — Editable assumptions — USD'!B61),1)),DATE(2027,8,1)=DATE(YEAR('01 — Editable assumptions — USD'!B61),MONTH('01 — Editable assumptions — USD'!B61),1),IF(DATE(YEAR('01 — Editable assumptions — USD'!B61),MONTH('01 — Editable assumptions — USD'!B61),1)="","",DATE(2027,8,1)=DATE(YEAR('01 — Editable assumptions — USD'!B61),MONTH('01 — Editable assumptions — USD'!B61),1)))),IF('04 — Scenario comparison — Base'!B24="","",'04 — Scenario comparison — Base'!B24),IF('07 — Cash projection — hypothet'!K10="","",'07 — Cash projection — hypothet'!K10)))+'07 — Cash projection — hypothet'!L8 -> 4822.48 | M10: =IF(IF(IF(IF(ISERROR(DATE(2027,9,1)=DATE(YEAR('01 — Editable assumptions — USD'!B61),MONTH('01 — Editable assumptions — USD'!B61),1)),DATE(2027,9,1)=DATE(YEAR('01 — Editable assumptions — USD'!B61),MONTH('01 — Editable assumptions — USD'!B61),1),IF(DATE(YEAR('01 — Editable assumptions — USD'!B61),MONTH('01 — Editable assumptions — USD'!B61),1)="","",DATE(2027,9,1)=DATE(YEAR('01 — Editable assumptions — USD'!B61),MONTH('01 — Editable assumptions — USD'!B61),1)))="",FALSE,IF(ISERROR(DATE(2027,9,1)=DATE(YEAR('01 — Editable assumptions — USD'!B61),MONTH('01 — Editable assumptions — USD'!B61),1)),DATE(2027,9,1)=DATE(YEAR('01 — Editable assumptions — USD'!B61),MONTH('01 — Editable assumptions — USD'!B61),1),IF(DATE(YEAR('01 — Editable assumptions — USD'!B61),MONTH('01 — Editable assumptions — USD'!B61),1)="","",DATE(2027,9,1)=DATE(YEAR('01 — Editable assumptions — USD'!B61),MONTH('01 — Editable assumptions — USD'!B61),1)))),IF('04 — Scenario comparison — Base'!B24="","",'04 — Scenario comparison — Base'!B24),IF('07 — Cash projection — hypothet'!L10="","",'07 — Cash projection — hypothet'!L10))="",0,IF(IF(IF(ISERROR(DATE(2027,9,1)=DATE(YEAR('01 — Editable assumptions — USD'!B61),MONTH('01 — Editable assumptions — USD'!B61),1)),DATE(2027,9,1)=DATE(YEAR('01 — Editable assumptions — USD'!B61),MONTH('01 — Editable assumptions — USD'!B61),1),IF(DATE(YEAR('01 — Editable assumptions — USD'!B61),MONTH('01 — Editable assumptions — USD'!B61),1)="","",DATE(2027,9,1)=DATE(YEAR('01 — Editable assumptions — USD'!B61),MONTH('01 — Editable assumptions — USD'!B61),1)))="",FALSE,IF(ISERROR(DATE(2027,9,1)=DATE(YEAR('01 — Editable assumptions — USD'!B61),MONTH('01 — Editable assumptions — USD'!B61),1)),DATE(2027,9,1)=DATE(YEAR('01 — Editable assumptions — USD'!B61),MONTH('01 — Editable assumptions — USD'!B61),1),IF(DATE(YEAR('01 — Editable assumptions — USD'!B61),MONTH('01 — Editable assumptions — USD'!B61),1)="","",DATE(2027,9,1)=DATE(YEAR('01 — Editable assumptions — USD'!B61),MONTH('01 — Editable assumptions — USD'!B61),1)))),IF('04 — Scenario comparison — Base'!B24="","",'04 — Scenario comparison — Base'!B24),IF('07 — Cash projection — hypothet'!L10="","",'07 — Cash projection — hypothet'!L10)))+'07 — Cash projection — hypothet'!M8 -> 5525.29 | N10: =IF(IF(IF(IF(ISERROR(DATE(2027,10,1)=DATE(YEAR('01 — Editable assumptions — USD'!B61),MONTH('01 — Editable assumptions — USD'!B61),1)),DATE(2027,10,1)=DATE(YEAR('01 — Editable assumptions — USD'!B61),MONTH('01 — Editable assumptions — USD'!B61),1),IF(DATE(YEAR('01 — Editable assumptions — USD'!B61),MONTH('01 — Editable assumptions — USD'!B61),1)="","",DATE(2027,10,1)=DATE(YEAR('01 — Editable assumptions — USD'!B61),MONTH('01 — Editable assumptions — USD'!B61),1)))="",FALSE,IF(ISERROR(DATE(2027,10,1)=DATE(YEAR('01 — Editable assumptions — USD'!B61),MONTH('01 — Editable assumptions — USD'!B61),1)),DATE(2027,10,1)=DATE(YEAR('01 — Editable assumptions — USD'!B61),MONTH('01 — Editable assumptions — USD'!B61),1),IF(DATE(YEAR('01 — Editable assumptions — USD'!B61),MONTH('01 — Editable assumptions — USD'!B61),1)="","",DATE(2027,10,1)=DATE(YEAR('01 — Editable assumptions — USD'!B61),MONTH('01 — Editable assumptions — USD'!B61),1)))),IF('04 — Scenario comparison — Base'!B24="","",'04 — Scenario comparison — Base'!B24),IF('07 — Cash projection — hypothet'!M10="","",'07 — Cash projection — hypothet'!M10))="",0,IF(IF(IF(ISERROR(DATE(2027,10,1)=DATE(YEAR('01 — Editable assumptions — USD'!B61),MONTH('01 — Editable assumptions — USD'!B61),1)),DATE(2027,10,1)=DATE(YEAR('01 — Editable assumptions — USD'!B61),MONTH('01 — Editable assumptions — USD'!B61),1),IF(DATE(YEAR('01 — Editable assumptions — USD'!B61),MONTH('01 — Editable assumptions — USD'!B61),1)="","",DATE(2027,10,1)=DATE(YEAR('01 — Editable assumptions — USD'!B61),MONTH('01 — Editable assumptions — USD'!B61),1)))="",FALSE,IF(ISERROR(DATE(2027,10,1)=DATE(YEAR('01 — Editable assumptions — USD'!B61),MONTH('01 — Editable assumptions — USD'!B61),1)),DATE(2027,10,1)=DATE(YEAR('01 — Editable assumptions — USD'!B61),MONTH('01 — Editable assumptions — USD'!B61),1),IF(DATE(YEAR('01 — Editable assumptions — USD'!B61),MONTH('01 — Editable assumptions — USD'!B61),1)="","",DATE(2027,10,1)=DATE(YEAR('01 — Editable assumptions — USD'!B61),MONTH('01 — Editable assumptions — USD'!B61),1)))),IF('04 — Scenario comparison — Base'!B24="","",'04 — Scenario comparison — Base'!B24),IF('07 — Cash projection — hypothet'!M10="","",'07 — Cash projection — hypothet'!M10)))+'07 — Cash projection — hypothet'!N8 -> 6228.1 | O10: =IF(IF(IF(IF(ISERROR(DATE(2027,11,1)=DATE(YEAR('01 — Editable assumptions — USD'!B61),MONTH('01 — Editable assumptions — USD'!B61),1)),DATE(2027,11,1)=DATE(YEAR('01 — Editable assumptions — USD'!B61),MONTH('01 — Editable assumptions — USD'!B61),1),IF(DATE(YEAR('01 — Editable assumptions — USD'!B61),MONTH('01 — Editable assumptions — USD'!B61),1)="","",DATE(2027,11,1)=DATE(YEAR('01 — Editable assumptions — USD'!B61),MONTH('01 — Editable assumptions — USD'!B61),1)))="",FALSE,IF(ISERROR(DATE(2027,11,1)=DATE(YEAR('01 — Editable assumptions — USD'!B61),MONTH('01 — Editable assumptions — USD'!B61),1)),DATE(2027,11,1)=DATE(YEAR('01 — Editable assumptions — USD'!B61),MONTH('01 — Editable assumptions — USD'!B61),1),IF(DATE(YEAR('01 — Editable assumptions — USD'!B61),MONTH('01 — Editable assumptions — USD'!B61),1)="","",DATE(2027,11,1)=DATE(YEAR('01 — Editable assumptions — USD'!B61),MONTH('01 — Editable assumptions — USD'!B61),1)))),IF('04 — Scenario comparison — Base'!B24="","",'04 — Scenario comparison — Base'!B24),IF('07 — Cash projection — hypothet'!N10="","",'07 — Cash projection — hypothet'!N10))="",0,IF(IF(IF(ISERROR(DATE(2027,11,1)=DATE(YEAR('01 — Editable assumptions — USD'!B61),MONTH('01 — Editable assumptions — USD'!B61),1)),DATE(2027,11,1)=DATE(YEAR('01 — Editable assumptions — USD'!B61),MONTH('01 — Editable assumptions — USD'!B61),1),IF(DATE(YEAR('01 — Editable assumptions — USD'!B61),MONTH('01 — Editable assumptions — USD'!B61),1)="","",DATE(2027,11,1)=DATE(YEAR('01 — Editable assumptions — USD'!B61),MONTH('01 — Editable assumptions — USD'!B61),1)))="",FALSE,IF(ISERROR(DATE(2027,11,1)=DATE(YEAR('01 — Editable assumptions — USD'!B61),MONTH('01 — Editable assumptions — USD'!B61),1)),DATE(2027,11,1)=DATE(YEAR('01 — Editable assumptions — USD'!B61),MONTH('01 — Editable assumptions — USD'!B61),1),IF(DATE(YEAR('01 — Editable assumptions — USD'!B61),MONTH('01 — Editable assumptions — USD'!B61),1)="","",DATE(2027,11,1)=DATE(YEAR('01 — Editable assumptions — USD'!B61),MONTH('01 — Editable assumptions — USD'!B61),1)))),IF('04 — Scenario comparison — Base'!B24="","",'04 — Scenario comparison — Base'!B24),IF('07 — Cash projection — hypothet'!N10="","",'07 — Cash projection — hypothet'!N10)))+'07 — Cash projection — hypothet'!O8 -> 6930.91 | P10: =IF(IF(IF(IF(ISERROR(DATE(2027,12,1)=DATE(YEAR('01 — Editable assumptions — USD'!B61),MONTH('01 — Editable assumptions — USD'!B61),1)),DATE(2027,12,1)=DATE(YEAR('01 — Editable assumptions — USD'!B61),MONTH('01 — Editable assumptions — USD'!B61),1),IF(DATE(YEAR('01 — Editable assumptions — USD'!B61),MONTH('01 — Editable assumptions — USD'!B61),1)="","",DATE(2027,12,1)=DATE(YEAR('01 — Editable assumptions — USD'!B61),MONTH('01 — Editable assumptions — USD'!B61),1)))="",FALSE,IF(ISERROR(DATE(2027,12,1)=DATE(YEAR('01 — Editable assumptions — USD'!B61),MONTH('01 — Editable assumptions — USD'!B61),1)),DATE(2027,12,1)=DATE(YEAR('01 — Editable assumptions — USD'!B61),MONTH('01 — Editable assumptions — USD'!B61),1),IF(DATE(YEAR('01 — Editable assumptions — USD'!B61),MONTH('01 — Editable assumptions — USD'!B61),1)="","",DATE(2027,12,1)=DATE(YEAR('01 — Editable assumptions — USD'!B61),MONTH('01 — Editable assumptions — USD'!B61),1)))),IF('04 — Scenario comparison — Base'!B24="","",'04 — Scenario comparison — Base'!B24),IF('07 — Cash projection — hypothet'!O10="","",'07 — Cash projection — hypothet'!O10))="",0,IF(IF(IF(ISERROR(DATE(2027,12,1)=DATE(YEAR('01 — Editable assumptions — USD'!B61),MONTH('01 — Editable assumptions — USD'!B61),1)),DATE(2027,12,1)=DATE(YEAR('01 — Editable assumptions — USD'!B61),MONTH('01 — Editable assumptions — USD'!B61),1),IF(DATE(YEAR('01 — Editable assumptions — USD'!B61),MONTH('01 — Editable assumptions — USD'!B61),1)="","",DATE(2027,12,1)=DATE(YEAR('01 — Editable assumptions — USD'!B61),MONTH('01 — Editable assumptions — USD'!B61),1)))="",FALSE,IF(ISERROR(DATE(2027,12,1)=DATE(YEAR('01 — Editable assumptions — USD'!B61),MONTH('01 — Editable assumptions — USD'!B61),1)),DATE(2027,12,1)=DATE(YEAR('01 — Editable assumptions — USD'!B61),MONTH('01 — Editable assumptions — USD'!B61),1),IF(DATE(YEAR('01 — Editable assumptions — USD'!B61),MONTH('01 — Editable assumptions — USD'!B61),1)="","",DATE(2027,12,1)=DATE(YEAR('01 — Editable assumptions — USD'!B61),MONTH('01 — Editable assumptions — USD'!B61),1)))),IF('04 — Scenario comparison — Base'!B24="","",'04 — Scenario comparison — Base'!B24),IF('07 — Cash projection — hypothet'!O10="","",'07 — Cash projection — hypothet'!O10)))+'07 — Cash projection — hypothet'!P8 -> 7633.72
A11: TS Projected cash founder | B11: =IF(IF(IF(IF(ISERROR(DATE(2026,10,1)=DATE(YEAR('01 — Editable assumptions — USD'!B61),MONTH('01 — Editable assumptions — USD'!B61),1)),DATE(2026,10,1)=DATE(YEAR('01 — Editable assumptions — USD'!B61),MONTH('01 — Editable assumptions — USD'!B61),1),IF(DATE(YEAR('01 — Editable assumptions — USD'!B61),MONTH('01 — Editable assumptions — USD'!B61),1)="","",DATE(2026,10,1)=DATE(YEAR('01 — Editable assumptions — USD'!B61),MONTH('01 — Editable assumptions — USD'!B61),1)))="",FALSE,IF(ISERROR(DATE(2026,10,1)=DATE(YEAR('01 — Editable assumptions — USD'!B61),MONTH('01 — Editable assumptions — USD'!B61),1)),DATE(2026,10,1)=DATE(YEAR('01 — Editable assumptions — USD'!B61),MONTH('01 — Editable assumptions — USD'!B61),1),IF(DATE(YEAR('01 — Editable assumptions — USD'!B61),MONTH('01 — Editable assumptions — USD'!B61),1)="","",DATE(2026,10,1)=DATE(YEAR('01 — Editable assumptions — USD'!B61),MONTH('01 — Editable assumptions — USD'!B61),1)))),IF('04 — Scenario comparison — Base'!B24="","",'04 — Scenario comparison — Base'!B24),IF('Model inputs'!D101="","",'Model inputs'!D101))="",0,IF(IF(IF(ISERROR(DATE(2026,10,1)=DATE(YEAR('01 — Editable assumptions — USD'!B61),MONTH('01 — Editable assumptions — USD'!B61),1)),DATE(2026,10,1)=DATE(YEAR('01 — Editable assumptions — USD'!B61),MONTH('01 — Editable assumptions — USD'!B61),1),IF(DATE(YEAR('01 — Editable assumptions — USD'!B61),MONTH('01 — Editable assumptions — USD'!B61),1)="","",DATE(2026,10,1)=DATE(YEAR('01 — Editable assumptions — USD'!B61),MONTH('01 — Editable assumptions — USD'!B61),1)))="",FALSE,IF(ISERROR(DATE(2026,10,1)=DATE(YEAR('01 — Editable assumptions — USD'!B61),MONTH('01 — Editable assumptions — USD'!B61),1)),DATE(2026,10,1)=DATE(YEAR('01 — Editable assumptions — USD'!B61),MONTH('01 — Editable assumptions — USD'!B61),1),IF(DATE(YEAR('01 — Editable assumptions — USD'!B61),MONTH('01 — Editable assumptions — USD'!B61),1)="","",DATE(2026,10,1)=DATE(YEAR('01 — Editable assumptions — USD'!B61),MONTH('01 — Editable assumptions — USD'!B61),1)))),IF('04 — Scenario comparison — Base'!B24="","",'04 — Scenario comparison — Base'!B24),IF('Model inputs'!D101="","",'Model inputs'!D101)))+'07 — Cash projection — hypothet'!B9 -> -2600 | C11: =IF(IF(IF(IF(ISERROR(DATE(2026,11,1)=DATE(YEAR('01 — Editable assumptions — USD'!B61),MONTH('01 — Editable assumptions — USD'!B61),1)),DATE(2026,11,1)=DATE(YEAR('01 — Editable assumptions — USD'!B61),MONTH('01 — Editable assumptions — USD'!B61),1),IF(DATE(YEAR('01 — Editable assumptions — USD'!B61),MONTH('01 — Editable assumptions — USD'!B61),1)="","",DATE(2026,11,1)=DATE(YEAR('01 — Editable assumptions — USD'!B61),MONTH('01 — Editable assumptions — USD'!B61),1)))="",FALSE,IF(ISERROR(DATE(2026,11,1)=DATE(YEAR('01 — Editable assumptions — USD'!B61),MONTH('01 — Editable assumptions — USD'!B61),1)),DATE(2026,11,1)=DATE(YEAR('01 — Editable assumptions — USD'!B61),MONTH('01 — Editable assumptions — USD'!B61),1),IF(DATE(YEAR('01 — Editable assumptions — USD'!B61),MONTH('01 — Editable assumptions — USD'!B61),1)="","",DATE(2026,11,1)=DATE(YEAR('01 — Editable assumptions — USD'!B61),MONTH('01 — Editable assumptions — USD'!B61),1)))),IF('04 — Scenario comparison — Base'!B24="","",'04 — Scenario comparison — Base'!B24),IF('07 — Cash projection — hypothet'!B11="","",'07 — Cash projection — hypothet'!B11))="",0,IF(IF(IF(ISERROR(DATE(2026,11,1)=DATE(YEAR('01 — Editable assumptions — USD'!B61),MONTH('01 — Editable assumptions — USD'!B61),1)),DATE(2026,11,1)=DATE(YEAR('01 — Editable assumptions — USD'!B61),MONTH('01 — Editable assumptions — USD'!B61),1),IF(DATE(YEAR('01 — Editable assumptions — USD'!B61),MONTH('01 — Editable assumptions — USD'!B61),1)="","",DATE(2026,11,1)=DATE(YEAR('01 — Editable assumptions — USD'!B61),MONTH('01 — Editable assumptions — USD'!B61),1)))="",FALSE,IF(ISERROR(DATE(2026,11,1)=DATE(YEAR('01 — Editable assumptions — USD'!B61),MONTH('01 — Editable assumptions — USD'!B61),1)),DATE(2026,11,1)=DATE(YEAR('01 — Editable assumptions — USD'!B61),MONTH('01 — Editable assumptions — USD'!B61),1),IF(DATE(YEAR('01 — Editable assumptions — USD'!B61),MONTH('01 — Editable assumptions — USD'!B61),1)="","",DATE(2026,11,1)=DATE(YEAR('01 — Editable assumptions — USD'!B61),MONTH('01 — Editable assumptions — USD'!B61),1)))),IF('04 — Scenario comparison — Base'!B24="","",'04 — Scenario comparison — Base'!B24),IF('07 — Cash projection — hypothet'!B11="","",'07 — Cash projection — hypothet'!B11)))+'07 — Cash projection — hypothet'!C9 -> -6200 | D11: =IF(IF(IF(IF(ISERROR(DATE(2026,12,1)=DATE(YEAR('01 — Editable assumptions — USD'!B61),MONTH('01 — Editable assumptions — USD'!B61),1)),DATE(2026,12,1)=DATE(YEAR('01 — Editable assumptions — USD'!B61),MONTH('01 — Editable assumptions — USD'!B61),1),IF(DATE(YEAR('01 — Editable assumptions — USD'!B61),MONTH('01 — Editable assumptions — USD'!B61),1)="","",DATE(2026,12,1)=DATE(YEAR('01 — Editable assumptions — USD'!B61),MONTH('01 — Editable assumptions — USD'!B61),1)))="",FALSE,IF(ISERROR(DATE(2026,12,1)=DATE(YEAR('01 — Editable assumptions — USD'!B61),MONTH('01 — Editable assumptions — USD'!B61),1)),DATE(2026,12,1)=DATE(YEAR('01 — Editable assumptions — USD'!B61),MONTH('01 — Editable assumptions — USD'!B61),1),IF(DATE(YEAR('01 — Editable assumptions — USD'!B61),MONTH('01 — Editable assumptions — USD'!B61),1)="","",DATE(2026,12,1)=DATE(YEAR('01 — Editable assumptions — USD'!B61),MONTH('01 — Editable assumptions — USD'!B61),1)))),IF('04 — Scenario comparison — Base'!B24="","",'04 — Scenario comparison — Base'!B24),IF('07 — Cash projection — hypothet'!C11="","",'07 — Cash projection — hypothet'!C11))="",0,IF(IF(IF(ISERROR(DATE(2026,12,1)=DATE(YEAR('01 — Editable assumptions — USD'!B61),MONTH('01 — Editable assumptions — USD'!B61),1)),DATE(2026,12,1)=DATE(YEAR('01 — Editable assumptions — USD'!B61),MONTH('01 — Editable assumptions — USD'!B61),1),IF(DATE(YEAR('01 — Editable assumptions — USD'!B61),MONTH('01 — Editable assumptions — USD'!B61),1)="","",DATE(2026,12,1)=DATE(YEAR('01 — Editable assumptions — USD'!B61),MONTH('01 — Editable assumptions — USD'!B61),1)))="",FALSE,IF(ISERROR(DATE(2026,12,1)=DATE(YEAR('01 — Editable assumptions — USD'!B61),MONTH('01 — Editable assumptions — USD'!B61),1)),DATE(2026,12,1)=DATE(YEAR('01 — Editable assumptions — USD'!B61),MONTH('01 — Editable assumptions — USD'!B61),1),IF(DATE(YEAR('01 — Editable assumptions — USD'!B61),MONTH('01 — Editable assumptions — USD'!B61),1)="","",DATE(2026,12,1)=DATE(YEAR('01 — Editable assumptions — USD'!B61),MONTH('01 — Editable assumptions — USD'!B61),1)))),IF('04 — Scenario comparison — Base'!B24="","",'04 — Scenario comparison — Base'!B24),IF('07 — Cash projection — hypothet'!C11="","",'07 — Cash projection — hypothet'!C11)))+'07 — Cash projection — hypothet'!D9 -> -9800 | E11: =IF(IF(IF(IF(ISERROR(DATE(2027,1,1)=DATE(YEAR('01 — Editable assumptions — USD'!B61),MONTH('01 — Editable assumptions — USD'!B61),1)),DATE(2027,1,1)=DATE(YEAR('01 — Editable assumptions — USD'!B61),MONTH('01 — Editable assumptions — USD'!B61),1),IF(DATE(YEAR('01 — Editable assumptions — USD'!B61),MONTH('01 — Editable assumptions — USD'!B61),1)="","",DATE(2027,1,1)=DATE(YEAR('01 — Editable assumptions — USD'!B61),MONTH('01 — Editable assumptions — USD'!B61),1)))="",FALSE,IF(ISERROR(DATE(2027,1,1)=DATE(YEAR('01 — Editable assumptions — USD'!B61),MONTH('01 — Editable assumptions — USD'!B61),1)),DATE(2027,1,1)=DATE(YEAR('01 — Editable assumptions — USD'!B61),MONTH('01 — Editable assumptions — USD'!B61),1),IF(DATE(YEAR('01 — Editable assumptions — USD'!B61),MONTH('01 — Editable assumptions — USD'!B61),1)="","",DATE(2027,1,1)=DATE(YEAR('01 — Editable assumptions — USD'!B61),MONTH('01 — Editable assumptions — USD'!B61),1)))),IF('04 — Scenario comparison — Base'!B24="","",'04 — Scenario comparison — Base'!B24),IF('07 — Cash projection — hypothet'!D11="","",'07 — Cash projection — hypothet'!D11))="",0,IF(IF(IF(ISERROR(DATE(2027,1,1)=DATE(YEAR('01 — Editable assumptions — USD'!B61),MONTH('01 — Editable assumptions — USD'!B61),1)),DATE(2027,1,1)=DATE(YEAR('01 — Editable assumptions — USD'!B61),MONTH('01 — Editable assumptions — USD'!B61),1),IF(DATE(YEAR('01 — Editable assumptions — USD'!B61),MONTH('01 — Editable assumptions — USD'!B61),1)="","",DATE(2027,1,1)=DATE(YEAR('01 — Editable assumptions — USD'!B61),MONTH('01 — Editable assumptions — USD'!B61),1)))="",FALSE,IF(ISERROR(DATE(2027,1,1)=DATE(YEAR('01 — Editable assumptions — USD'!B61),MONTH('01 — Editable assumptions — USD'!B61),1)),DATE(2027,1,1)=DATE(YEAR('01 — Editable assumptions — USD'!B61),MONTH('01 — Editable assumptions — USD'!B61),1),IF(DATE(YEAR('01 — Editable assumptions — USD'!B61),MONTH('01 — Editable assumptions — USD'!B61),1)="","",DATE(2027,1,1)=DATE(YEAR('01 — Editable assumptions — USD'!B61),MONTH('01 — Editable assumptions — USD'!B61),1)))),IF('04 — Scenario comparison — Base'!B24="","",'04 — Scenario comparison — Base'!B24),IF('07 — Cash projection — hypothet'!D11="","",'07 — Cash projection — hypothet'!D11)))+'07 — Cash projection — hypothet'!E9 -> -12097.19 | F11: =IF(IF(IF(IF(ISERROR(DATE(2027,2,1)=DATE(YEAR('01 — Editable assumptions — USD'!B61),MONTH('01 — Editable assumptions — USD'!B61),1)),DATE(2027,2,1)=DATE(YEAR('01 — Editable assumptions — USD'!B61),MONTH('01 — Editable assumptions — USD'!B61),1),IF(DATE(YEAR('01 — Editable assumptions — USD'!B61),MONTH('01 — Editable assumptions — USD'!B61),1)="","",DATE(2027,2,1)=DATE(YEAR('01 — Editable assumptions — USD'!B61),MONTH('01 — Editable assumptions — USD'!B61),1)))="",FALSE,IF(ISERROR(DATE(2027,2,1)=DATE(YEAR('01 — Editable assumptions — USD'!B61),MONTH('01 — Editable assumptions — USD'!B61),1)),DATE(2027,2,1)=DATE(YEAR('01 — Editable assumptions — USD'!B61),MONTH('01 — Editable assumptions — USD'!B61),1),IF(DATE(YEAR('01 — Editable assumptions — USD'!B61),MONTH('01 — Editable assumptions — USD'!B61),1)="","",DATE(2027,2,1)=DATE(YEAR('01 — Editable assumptions — USD'!B61),MONTH('01 — Editable assumptions — USD'!B61),1)))),IF('04 — Scenario comparison — Base'!B24="","",'04 — Scenario comparison — Base'!B24),IF('07 — Cash projection — hypothet'!E11="","",'07 — Cash projection — hypothet'!E11))="",0,IF(IF(IF(ISERROR(DATE(2027,2,1)=DATE(YEAR('01 — Editable assumptions — USD'!B61),MONTH('01 — Editable assumptions — USD'!B61),1)),DATE(2027,2,1)=DATE(YEAR('01 — Editable assumptions — USD'!B61),MONTH('01 — Editable assumptions — USD'!B61),1),IF(DATE(YEAR('01 — Editable assumptions — USD'!B61),MONTH('01 — Editable assumptions — USD'!B61),1)="","",DATE(2027,2,1)=DATE(YEAR('01 — Editable assumptions — USD'!B61),MONTH('01 — Editable assumptions — USD'!B61),1)))="",FALSE,IF(ISERROR(DATE(2027,2,1)=DATE(YEAR('01 — Editable assumptions — USD'!B61),MONTH('01 — Editable assumptions — USD'!B61),1)),DATE(2027,2,1)=DATE(YEAR('01 — Editable assumptions — USD'!B61),MONTH('01 — Editable assumptions — USD'!B61),1),IF(DATE(YEAR('01 — Editable assumptions — USD'!B61),MONTH('01 — Editable assumptions — USD'!B61),1)="","",DATE(2027,2,1)=DATE(YEAR('01 — Editable assumptions — USD'!B61),MONTH('01 — Editable assumptions — USD'!B61),1)))),IF('04 — Scenario comparison — Base'!B24="","",'04 — Scenario comparison — Base'!B24),IF('07 — Cash projection — hypothet'!E11="","",'07 — Cash projection — hypothet'!E11)))+'07 — Cash projection — hypothet'!F9 -> -14394.38 | G11: =IF(IF(IF(IF(ISERROR(DATE(2027,3,1)=DATE(YEAR('01 — Editable assumptions — USD'!B61),MONTH('01 — Editable assumptions — USD'!B61),1)),DATE(2027,3,1)=DATE(YEAR('01 — Editable assumptions — USD'!B61),MONTH('01 — Editable assumptions — USD'!B61),1),IF(DATE(YEAR('01 — Editable assumptions — USD'!B61),MONTH('01 — Editable assumptions — USD'!B61),1)="","",DATE(2027,3,1)=DATE(YEAR('01 — Editable assumptions — USD'!B61),MONTH('01 — Editable assumptions — USD'!B61),1)))="",FALSE,IF(ISERROR(DATE(2027,3,1)=DATE(YEAR('01 — Editable assumptions — USD'!B61),MONTH('01 — Editable assumptions — USD'!B61),1)),DATE(2027,3,1)=DATE(YEAR('01 — Editable assumptions — USD'!B61),MONTH('01 — Editable assumptions — USD'!B61),1),IF(DATE(YEAR('01 — Editable assumptions — USD'!B61),MONTH('01 — Editable assumptions — USD'!B61),1)="","",DATE(2027,3,1)=DATE(YEAR('01 — Editable assumptions — USD'!B61),MONTH('01 — Editable assumptions — USD'!B61),1)))),IF('04 — Scenario comparison — Base'!B24="","",'04 — Scenario comparison — Base'!B24),IF('07 — Cash projection — hypothet'!F11="","",'07 — Cash projection — hypothet'!F11))="",0,IF(IF(IF(ISERROR(DATE(2027,3,1)=DATE(YEAR('01 — Editable assumptions — USD'!B61),MONTH('01 — Editable assumptions — USD'!B61),1)),DATE(2027,3,1)=DATE(YEAR('01 — Editable assumptions — USD'!B61),MONTH('01 — Editable assumptions — USD'!B61),1),IF(DATE(YEAR('01 — Editable assumptions — USD'!B61),MONTH('01 — Editable assumptions — USD'!B61),1)="","",DATE(2027,3,1)=DATE(YEAR('01 — Editable assumptions — USD'!B61),MONTH('01 — Editable assumptions — USD'!B61),1)))="",FALSE,IF(ISERROR(DATE(2027,3,1)=DATE(YEAR('01 — Editable assumptions — USD'!B61),MONTH('01 — Editable assumptions — USD'!B61),1)),DATE(2027,3,1)=DATE(YEAR('01 — Editable assumptions — USD'!B61),MONTH('01 — Editable assumptions — USD'!B61),1),IF(DATE(YEAR('01 — Editable assumptions — USD'!B61),MONTH('01 — Editable assumptions — USD'!B61),1)="","",DATE(2027,3,1)=DATE(YEAR('01 — Editable assumptions — USD'!B61),MONTH('01 — Editable assumptions — USD'!B61),1)))),IF('04 — Scenario comparison — Base'!B24="","",'04 — Scenario comparison — Base'!B24),IF('07 — Cash projection — hypothet'!F11="","",'07 — Cash projection — hypothet'!F11)))+'07 — Cash projection — hypothet'!G9 -> -16691.57 | H11: =IF(IF(IF(IF(ISERROR(DATE(2027,4,1)=DATE(YEAR('01 — Editable assumptions — USD'!B61),MONTH('01 — Editable assumptions — USD'!B61),1)),DATE(2027,4,1)=DATE(YEAR('01 — Editable assumptions — USD'!B61),MONTH('01 — Editable assumptions — USD'!B61),1),IF(DATE(YEAR('01 — Editable assumptions — USD'!B61),MONTH('01 — Editable assumptions — USD'!B61),1)="","",DATE(2027,4,1)=DATE(YEAR('01 — Editable assumptions — USD'!B61),MONTH('01 — Editable assumptions — USD'!B61),1)))="",FALSE,IF(ISERROR(DATE(2027,4,1)=DATE(YEAR('01 — Editable assumptions — USD'!B61),MONTH('01 — Editable assumptions — USD'!B61),1)),DATE(2027,4,1)=DATE(YEAR('01 — Editable assumptions — USD'!B61),MONTH('01 — Editable assumptions — USD'!B61),1),IF(DATE(YEAR('01 — Editable assumptions — USD'!B61),MONTH('01 — Editable assumptions — USD'!B61),1)="","",DATE(2027,4,1)=DATE(YEAR('01 — Editable assumptions — USD'!B61),MONTH('01 — Editable assumptions — USD'!B61),1)))),IF('04 — Scenario comparison — Base'!B24="","",'04 — Scenario comparison — Base'!B24),IF('07 — Cash projection — hypothet'!G11="","",'07 — Cash projection — hypothet'!G11))="",0,IF(IF(IF(ISERROR(DATE(2027,4,1)=DATE(YEAR('01 — Editable assumptions — USD'!B61),MONTH('01 — Editable assumptions — USD'!B61),1)),DATE(2027,4,1)=DATE(YEAR('01 — Editable assumptions — USD'!B61),MONTH('01 — Editable assumptions — USD'!B61),1),IF(DATE(YEAR('01 — Editable assumptions — USD'!B61),MONTH('01 — Editable assumptions — USD'!B61),1)="","",DATE(2027,4,1)=DATE(YEAR('01 — Editable assumptions — USD'!B61),MONTH('01 — Editable assumptions — USD'!B61),1)))="",FALSE,IF(ISERROR(DATE(2027,4,1)=DATE(YEAR('01 — Editable assumptions — USD'!B61),MONTH('01 — Editable assumptions — USD'!B61),1)),DATE(2027,4,1)=DATE(YEAR('01 — Editable assumptions — USD'!B61),MONTH('01 — Editable assumptions — USD'!B61),1),IF(DATE(YEAR('01 — Editable assumptions — USD'!B61),MONTH('01 — Editable assumptions — USD'!B61),1)="","",DATE(2027,4,1)=DATE(YEAR('01 — Editable assumptions — USD'!B61),MONTH('01 — Editable assumptions — USD'!B61),1)))),IF('04 — Scenario comparison — Base'!B24="","",'04 — Scenario comparison — Base'!B24),IF('07 — Cash projection — hypothet'!G11="","",'07 — Cash projection — hypothet'!G11)))+'07 — Cash projection — hypothet'!H9 -> -18988.76 | I11: =IF(IF(IF(IF(ISERROR(DATE(2027,5,1)=DATE(YEAR('01 — Editable assumptions — USD'!B61),MONTH('01 — Editable assumptions — USD'!B61),1)),DATE(2027,5,1)=DATE(YEAR('01 — Editable assumptions — USD'!B61),MONTH('01 — Editable assumptions — USD'!B61),1),IF(DATE(YEAR('01 — Editable assumptions — USD'!B61),MONTH('01 — Editable assumptions — USD'!B61),1)="","",DATE(2027,5,1)=DATE(YEAR('01 — Editable assumptions — USD'!B61),MONTH('01 — Editable assumptions — USD'!B61),1)))="",FALSE,IF(ISERROR(DATE(2027,5,1)=DATE(YEAR('01 — Editable assumptions — USD'!B61),MONTH('01 — Editable assumptions — USD'!B61),1)),DATE(2027,5,1)=DATE(YEAR('01 — Editable assumptions — USD'!B61),MONTH('01 — Editable assumptions — USD'!B61),1),IF(DATE(YEAR('01 — Editable assumptions — USD'!B61),MONTH('01 — Editable assumptions — USD'!B61),1)="","",DATE(2027,5,1)=DATE(YEAR('01 — Editable assumptions — USD'!B61),MONTH('01 — Editable assumptions — USD'!B61),1)))),IF('04 — Scenario comparison — Base'!B24="","",'04 — Scenario comparison — Base'!B24),IF('07 — Cash projection — hypothet'!H11="","",'07 — Cash projection — hypothet'!H11))="",0,IF(IF(IF(ISERROR(DATE(2027,5,1)=DATE(YEAR('01 — Editable assumptions — USD'!B61),MONTH('01 — Editable assumptions — USD'!B61),1)),DATE(2027,5,1)=DATE(YEAR('01 — Editable assumptions — USD'!B61),MONTH('01 — Editable assumptions — USD'!B61),1),IF(DATE(YEAR('01 — Editable assumptions — USD'!B61),MONTH('01 — Editable assumptions — USD'!B61),1)="","",DATE(2027,5,1)=DATE(YEAR('01 — Editable assumptions — USD'!B61),MONTH('01 — Editable assumptions — USD'!B61),1)))="",FALSE,IF(ISERROR(DATE(2027,5,1)=DATE(YEAR('01 — Editable assumptions — USD'!B61),MONTH('01 — Editable assumptions — USD'!B61),1)),DATE(2027,5,1)=DATE(YEAR('01 — Editable assumptions — USD'!B61),MONTH('01 — Editable assumptions — USD'!B61),1),IF(DATE(YEAR('01 — Editable assumptions — USD'!B61),MONTH('01 — Editable assumptions — USD'!B61),1)="","",DATE(2027,5,1)=DATE(YEAR('01 — Editable assumptions — USD'!B61),MONTH('01 — Editable assumptions — USD'!B61),1)))),IF('04 — Scenario comparison — Base'!B24="","",'04 — Scenario comparison — Base'!B24),IF('07 — Cash projection — hypothet'!H11="","",'07 — Cash projection — hypothet'!H11)))+'07 — Cash projection — hypothet'!I9 -> -21285.95 | J11: =IF(IF(IF(IF(ISERROR(DATE(2027,6,1)=DATE(YEAR('01 — Editable assumptions — USD'!B61),MONTH('01 — Editable assumptions — USD'!B61),1)),DATE(2027,6,1)=DATE(YEAR('01 — Editable assumptions — USD'!B61),MONTH('01 — Editable assumptions — USD'!B61),1),IF(DATE(YEAR('01 — Editable assumptions — USD'!B61),MONTH('01 — Editable assumptions — USD'!B61),1)="","",DATE(2027,6,1)=DATE(YEAR('01 — Editable assumptions — USD'!B61),MONTH('01 — Editable assumptions — USD'!B61),1)))="",FALSE,IF(ISERROR(DATE(2027,6,1)=DATE(YEAR('01 — Editable assumptions — USD'!B61),MONTH('01 — Editable assumptions — USD'!B61),1)),DATE(2027,6,1)=DATE(YEAR('01 — Editable assumptions — USD'!B61),MONTH('01 — Editable assumptions — USD'!B61),1),IF(DATE(YEAR('01 — Editable assumptions — USD'!B61),MONTH('01 — Editable assumptions — USD'!B61),1)="","",DATE(2027,6,1)=DATE(YEAR('01 — Editable assumptions — USD'!B61),MONTH('01 — Editable assumptions — USD'!B61),1)))),IF('04 — Scenario comparison — Base'!B24="","",'04 — Scenario comparison — Base'!B24),IF('07 — Cash projection — hypothet'!I11="","",'07 — Cash projection — hypothet'!I11))="",0,IF(IF(IF(ISERROR(DATE(2027,6,1)=DATE(YEAR('01 — Editable assumptions — USD'!B61),MONTH('01 — Editable assumptions — USD'!B61),1)),DATE(2027,6,1)=DATE(YEAR('01 — Editable assumptions — USD'!B61),MONTH('01 — Editable assumptions — USD'!B61),1),IF(DATE(YEAR('01 — Editable assumptions — USD'!B61),MONTH('01 — Editable assumptions — USD'!B61),1)="","",DATE(2027,6,1)=DATE(YEAR('01 — Editable assumptions — USD'!B61),MONTH('01 — Editable assumptions — USD'!B61),1)))="",FALSE,IF(ISERROR(DATE(2027,6,1)=DATE(YEAR('01 — Editable assumptions — USD'!B61),MONTH('01 — Editable assumptions — USD'!B61),1)),DATE(2027,6,1)=DATE(YEAR('01 — Editable assumptions — USD'!B61),MONTH('01 — Editable assumptions — USD'!B61),1),IF(DATE(YEAR('01 — Editable assumptions — USD'!B61),MONTH('01 — Editable assumptions — USD'!B61),1)="","",DATE(2027,6,1)=DATE(YEAR('01 — Editable assumptions — USD'!B61),MONTH('01 — Editable assumptions — USD'!B61),1)))),IF('04 — Scenario comparison — Base'!B24="","",'04 — Scenario comparison — Base'!B24),IF('07 — Cash projection — hypothet'!I11="","",'07 — Cash projection — hypothet'!I11)))+'07 — Cash projection — hypothet'!J9 -> -23583.14 | K11: =IF(IF(IF(IF(ISERROR(DATE(2027,7,1)=DATE(YEAR('01 — Editable assumptions — USD'!B61),MONTH('01 — Editable assumptions — USD'!B61),1)),DATE(2027,7,1)=DATE(YEAR('01 — Editable assumptions — USD'!B61),MONTH('01 — Editable assumptions — USD'!B61),1),IF(DATE(YEAR('01 — Editable assumptions — USD'!B61),MONTH('01 — Editable assumptions — USD'!B61),1)="","",DATE(2027,7,1)=DATE(YEAR('01 — Editable assumptions — USD'!B61),MONTH('01 — Editable assumptions — USD'!B61),1)))="",FALSE,IF(ISERROR(DATE(2027,7,1)=DATE(YEAR('01 — Editable assumptions — USD'!B61),MONTH('01 — Editable assumptions — USD'!B61),1)),DATE(2027,7,1)=DATE(YEAR('01 — Editable assumptions — USD'!B61),MONTH('01 — Editable assumptions — USD'!B61),1),IF(DATE(YEAR('01 — Editable assumptions — USD'!B61),MONTH('01 — Editable assumptions — USD'!B61),1)="","",DATE(2027,7,1)=DATE(YEAR('01 — Editable assumptions — USD'!B61),MONTH('01 — Editable assumptions — USD'!B61),1)))),IF('04 — Scenario comparison — Base'!B24="","",'04 — Scenario comparison — Base'!B24),IF('07 — Cash projection — hypothet'!J11="","",'07 — Cash projection — hypothet'!J11))="",0,IF(IF(IF(ISERROR(DATE(2027,7,1)=DATE(YEAR('01 — Editable assumptions — USD'!B61),MONTH('01 — Editable assumptions — USD'!B61),1)),DATE(2027,7,1)=DATE(YEAR('01 — Editable assumptions — USD'!B61),MONTH('01 — Editable assumptions — USD'!B61),1),IF(DATE(YEAR('01 — Editable assumptions — USD'!B61),MONTH('01 — Editable assumptions — USD'!B61),1)="","",DATE(2027,7,1)=DATE(YEAR('01 — Editable assumptions — USD'!B61),MONTH('01 — Editable assumptions — USD'!B61),1)))="",FALSE,IF(ISERROR(DATE(2027,7,1)=DATE(YEAR('01 — Editable assumptions — USD'!B61),MONTH('01 — Editable assumptions — USD'!B61),1)),DATE(2027,7,1)=DATE(YEAR('01 — Editable assumptions — USD'!B61),MONTH('01 — Editable assumptions — USD'!B61),1),IF(DATE(YEAR('01 — Editable assumptions — USD'!B61),MONTH('01 — Editable assumptions — USD'!B61),1)="","",DATE(2027,7,1)=DATE(YEAR('01 — Editable assumptions — USD'!B61),MONTH('01 — Editable assumptions — USD'!B61),1)))),IF('04 — Scenario comparison — Base'!B24="","",'04 — Scenario comparison — Base'!B24),IF('07 — Cash projection — hypothet'!J11="","",'07 — Cash projection — hypothet'!J11)))+'07 — Cash projection — hypothet'!K9 -> -25880.33 | L11: =IF(IF(IF(IF(ISERROR(DATE(2027,8,1)=DATE(YEAR('01 — Editable assumptions — USD'!B61),MONTH('01 — Editable assumptions — USD'!B61),1)),DATE(2027,8,1)=DATE(YEAR('01 — Editable assumptions — USD'!B61),MONTH('01 — Editable assumptions — USD'!B61),1),IF(DATE(YEAR('01 — Editable assumptions — USD'!B61),MONTH('01 — Editable assumptions — USD'!B61),1)="","",DATE(2027,8,1)=DATE(YEAR('01 — Editable assumptions — USD'!B61),MONTH('01 — Editable assumptions — USD'!B61),1)))="",FALSE,IF(ISERROR(DATE(2027,8,1)=DATE(YEAR('01 — Editable assumptions — USD'!B61),MONTH('01 — Editable assumptions — USD'!B61),1)),DATE(2027,8,1)=DATE(YEAR('01 — Editable assumptions — USD'!B61),MONTH('01 — Editable assumptions — USD'!B61),1),IF(DATE(YEAR('01 — Editable assumptions — USD'!B61),MONTH('01 — Editable assumptions — USD'!B61),1)="","",DATE(2027,8,1)=DATE(YEAR('01 — Editable assumptions — USD'!B61),MONTH('01 — Editable assumptions — USD'!B61),1)))),IF('04 — Scenario comparison — Base'!B24="","",'04 — Scenario comparison — Base'!B24),IF('07 — Cash projection — hypothet'!K11="","",'07 — Cash projection — hypothet'!K11))="",0,IF(IF(IF(ISERROR(DATE(2027,8,1)=DATE(YEAR('01 — Editable assumptions — USD'!B61),MONTH('01 — Editable assumptions — USD'!B61),1)),DATE(2027,8,1)=DATE(YEAR('01 — Editable assumptions — USD'!B61),MONTH('01 — Editable assumptions — USD'!B61),1),IF(DATE(YEAR('01 — Editable assumptions — USD'!B61),MONTH('01 — Editable assumptions — USD'!B61),1)="","",DATE(2027,8,1)=DATE(YEAR('01 — Editable assumptions — USD'!B61),MONTH('01 — Editable assumptions — USD'!B61),1)))="",FALSE,IF(ISERROR(DATE(2027,8,1)=DATE(YEAR('01 — Editable assumptions — USD'!B61),MONTH('01 — Editable assumptions — USD'!B61),1)),DATE(2027,8,1)=DATE(YEAR('01 — Editable assumptions — USD'!B61),MONTH('01 — Editable assumptions — USD'!B61),1),IF(DATE(YEAR('01 — Editable assumptions — USD'!B61),MONTH('01 — Editable assumptions — USD'!B61),1)="","",DATE(2027,8,1)=DATE(YEAR('01 — Editable assumptions — USD'!B61),MONTH('01 — Editable assumptions — USD'!B61),1)))),IF('04 — Scenario comparison — Base'!B24="","",'04 — Scenario comparison — Base'!B24),IF('07 — Cash projection — hypothet'!K11="","",'07 — Cash projection — hypothet'!K11)))+'07 — Cash projection — hypothet'!L9 -> -28177.52 | M11: =IF(IF(IF(IF(ISERROR(DATE(2027,9,1)=DATE(YEAR('01 — Editable assumptions — USD'!B61),MONTH('01 — Editable assumptions — USD'!B61),1)),DATE(2027,9,1)=DATE(YEAR('01 — Editable assumptions — USD'!B61),MONTH('01 — Editable assumptions — USD'!B61),1),IF(DATE(YEAR('01 — Editable assumptions — USD'!B61),MONTH('01 — Editable assumptions — USD'!B61),1)="","",DATE(2027,9,1)=DATE(YEAR('01 — Editable assumptions — USD'!B61),MONTH('01 — Editable assumptions — USD'!B61),1)))="",FALSE,IF(ISERROR(DATE(2027,9,1)=DATE(YEAR('01 — Editable assumptions — USD'!B61),MONTH('01 — Editable assumptions — USD'!B61),1)),DATE(2027,9,1)=DATE(YEAR('01 — Editable assumptions — USD'!B61),MONTH('01 — Editable assumptions — USD'!B61),1),IF(DATE(YEAR('01 — Editable assumptions — USD'!B61),MONTH('01 — Editable assumptions — USD'!B61),1)="","",DATE(2027,9,1)=DATE(YEAR('01 — Editable assumptions — USD'!B61),MONTH('01 — Editable assumptions — USD'!B61),1)))),IF('04 — Scenario comparison — Base'!B24="","",'04 — Scenario comparison — Base'!B24),IF('07 — Cash projection — hypothet'!L11="","",'07 — Cash projection — hypothet'!L11))="",0,IF(IF(IF(ISERROR(DATE(2027,9,1)=DATE(YEAR('01 — Editable assumptions — USD'!B61),MONTH('01 — Editable assumptions — USD'!B61),1)),DATE(2027,9,1)=DATE(YEAR('01 — Editable assumptions — USD'!B61),MONTH('01 — Editable assumptions — USD'!B61),1),IF(DATE(YEAR('01 — Editable assumptions — USD'!B61),MONTH('01 — Editable assumptions — USD'!B61),1)="","",DATE(2027,9,1)=DATE(YEAR('01 — Editable assumptions — USD'!B61),MONTH('01 — Editable assumptions — USD'!B61),1)))="",FALSE,IF(ISERROR(DATE(2027,9,1)=DATE(YEAR('01 — Editable assumptions — USD'!B61),MONTH('01 — Editable assumptions — USD'!B61),1)),DATE(2027,9,1)=DATE(YEAR('01 — Editable assumptions — USD'!B61),MONTH('01 — Editable assumptions — USD'!B61),1),IF(DATE(YEAR('01 — Editable assumptions — USD'!B61),MONTH('01 — Editable assumptions — USD'!B61),1)="","",DATE(2027,9,1)=DATE(YEAR('01 — Editable assumptions — USD'!B61),MONTH('01 — Editable assumptions — USD'!B61),1)))),IF('04 — Scenario comparison — Base'!B24="","",'04 — Scenario comparison — Base'!B24),IF('07 — Cash projection — hypothet'!L11="","",'07 — Cash projection — hypothet'!L11)))+'07 — Cash projection — hypothet'!M9 -> -30474.71 | N11: =IF(IF(IF(IF(ISERROR(DATE(2027,10,1)=DATE(YEAR('01 — Editable assumptions — USD'!B61),MONTH('01 — Editable assumptions — USD'!B61),1)),DATE(2027,10,1)=DATE(YEAR('01 — Editable assumptions — USD'!B61),MONTH('01 — Editable assumptions — USD'!B61),1),IF(DATE(YEAR('01 — Editable assumptions — USD'!B61),MONTH('01 — Editable assumptions — USD'!B61),1)="","",DATE(2027,10,1)=DATE(YEAR('01 — Editable assumptions — USD'!B61),MONTH('01 — Editable assumptions — USD'!B61),1)))="",FALSE,IF(ISERROR(DATE(2027,10,1)=DATE(YEAR('01 — Editable assumptions — USD'!B61),MONTH('01 — Editable assumptions — USD'!B61),1)),DATE(2027,10,1)=DATE(YEAR('01 — Editable assumptions — USD'!B61),MONTH('01 — Editable assumptions — USD'!B61),1),IF(DATE(YEAR('01 — Editable assumptions — USD'!B61),MONTH('01 — Editable assumptions — USD'!B61),1)="","",DATE(2027,10,1)=DATE(YEAR('01 — Editable assumptions — USD'!B61),MONTH('01 — Editable assumptions — USD'!B61),1)))),IF('04 — Scenario comparison — Base'!B24="","",'04 — Scenario comparison — Base'!B24),IF('07 — Cash projection — hypothet'!M11="","",'07 — Cash projection — hypothet'!M11))="",0,IF(IF(IF(ISERROR(DATE(2027,10,1)=DATE(YEAR('01 — Editable assumptions — USD'!B61),MONTH('01 — Editable assumptions — USD'!B61),1)),DATE(2027,10,1)=DATE(YEAR('01 — Editable assumptions — USD'!B61),MONTH('01 — Editable assumptions — USD'!B61),1),IF(DATE(YEAR('01 — Editable assumptions — USD'!B61),MONTH('01 — Editable assumptions — USD'!B61),1)="","",DATE(2027,10,1)=DATE(YEAR('01 — Editable assumptions — USD'!B61),MONTH('01 — Editable assumptions — USD'!B61),1)))="",FALSE,IF(ISERROR(DATE(2027,10,1)=DATE(YEAR('01 — Editable assumptions — USD'!B61),MONTH('01 — Editable assumptions — USD'!B61),1)),DATE(2027,10,1)=DATE(YEAR('01 — Editable assumptions — USD'!B61),MONTH('01 — Editable assumptions — USD'!B61),1),IF(DATE(YEAR('01 — Editable assumptions — USD'!B61),MONTH('01 — Editable assumptions — USD'!B61),1)="","",DATE(2027,10,1)=DATE(YEAR('01 — Editable assumptions — USD'!B61),MONTH('01 — Editable assumptions — USD'!B61),1)))),IF('04 — Scenario comparison — Base'!B24="","",'04 — Scenario comparison — Base'!B24),IF('07 — Cash projection — hypothet'!M11="","",'07 — Cash projection — hypothet'!M11)))+'07 — Cash projection — hypothet'!N9 -> -32771.9 | O11: =IF(IF(IF(IF(ISERROR(DATE(2027,11,1)=DATE(YEAR('01 — Editable assumptions — USD'!B61),MONTH('01 — Editable assumptions — USD'!B61),1)),DATE(2027,11,1)=DATE(YEAR('01 — Editable assumptions — USD'!B61),MONTH('01 — Editable assumptions — USD'!B61),1),IF(DATE(YEAR('01 — Editable assumptions — USD'!B61),MONTH('01 — Editable assumptions — USD'!B61),1)="","",DATE(2027,11,1)=DATE(YEAR('01 — Editable assumptions — USD'!B61),MONTH('01 — Editable assumptions — USD'!B61),1)))="",FALSE,IF(ISERROR(DATE(2027,11,1)=DATE(YEAR('01 — Editable assumptions — USD'!B61),MONTH('01 — Editable assumptions — USD'!B61),1)),DATE(2027,11,1)=DATE(YEAR('01 — Editable assumptions — USD'!B61),MONTH('01 — Editable assumptions — USD'!B61),1),IF(DATE(YEAR('01 — Editable assumptions — USD'!B61),MONTH('01 — Editable assumptions — USD'!B61),1)="","",DATE(2027,11,1)=DATE(YEAR('01 — Editable assumptions — USD'!B61),MONTH('01 — Editable assumptions — USD'!B61),1)))),IF('04 — Scenario comparison — Base'!B24="","",'04 — Scenario comparison — Base'!B24),IF('07 — Cash projection — hypothet'!N11="","",'07 — Cash projection — hypothet'!N11))="",0,IF(IF(IF(ISERROR(DATE(2027,11,1)=DATE(YEAR('01 — Editable assumptions — USD'!B61),MONTH('01 — Editable assumptions — USD'!B61),1)),DATE(2027,11,1)=DATE(YEAR('01 — Editable assumptions — USD'!B61),MONTH('01 — Editable assumptions — USD'!B61),1),IF(DATE(YEAR('01 — Editable assumptions — USD'!B61),MONTH('01 — Editable assumptions — USD'!B61),1)="","",DATE(2027,11,1)=DATE(YEAR('01 — Editable assumptions — USD'!B61),MONTH('01 — Editable assumptions — USD'!B61),1)))="",FALSE,IF(ISERROR(DATE(2027,11,1)=DATE(YEAR('01 — Editable assumptions — USD'!B61),MONTH('01 — Editable assumptions — USD'!B61),1)),DATE(2027,11,1)=DATE(YEAR('01 — Editable assumptions — USD'!B61),MONTH('01 — Editable assumptions — USD'!B61),1),IF(DATE(YEAR('01 — Editable assumptions — USD'!B61),MONTH('01 — Editable assumptions — USD'!B61),1)="","",DATE(2027,11,1)=DATE(YEAR('01 — Editable assumptions — USD'!B61),MONTH('01 — Editable assumptions — USD'!B61),1)))),IF('04 — Scenario comparison — Base'!B24="","",'04 — Scenario comparison — Base'!B24),IF('07 — Cash projection — hypothet'!N11="","",'07 — Cash projection — hypothet'!N11)))+'07 — Cash projection — hypothet'!O9 -> -35069.09 | P11: =IF(IF(IF(IF(ISERROR(DATE(2027,12,1)=DATE(YEAR('01 — Editable assumptions — USD'!B61),MONTH('01 — Editable assumptions — USD'!B61),1)),DATE(2027,12,1)=DATE(YEAR('01 — Editable assumptions — USD'!B61),MONTH('01 — Editable assumptions — USD'!B61),1),IF(DATE(YEAR('01 — Editable assumptions — USD'!B61),MONTH('01 — Editable assumptions — USD'!B61),1)="","",DATE(2027,12,1)=DATE(YEAR('01 — Editable assumptions — USD'!B61),MONTH('01 — Editable assumptions — USD'!B61),1)))="",FALSE,IF(ISERROR(DATE(2027,12,1)=DATE(YEAR('01 — Editable assumptions — USD'!B61),MONTH('01 — Editable assumptions — USD'!B61),1)),DATE(2027,12,1)=DATE(YEAR('01 — Editable assumptions — USD'!B61),MONTH('01 — Editable assumptions — USD'!B61),1),IF(DATE(YEAR('01 — Editable assumptions — USD'!B61),MONTH('01 — Editable assumptions — USD'!B61),1)="","",DATE(2027,12,1)=DATE(YEAR('01 — Editable assumptions — USD'!B61),MONTH('01 — Editable assumptions — USD'!B61),1)))),IF('04 — Scenario comparison — Base'!B24="","",'04 — Scenario comparison — Base'!B24),IF('07 — Cash projection — hypothet'!O11="","",'07 — Cash projection — hypothet'!O11))="",0,IF(IF(IF(ISERROR(DATE(2027,12,1)=DATE(YEAR('01 — Editable assumptions — USD'!B61),MONTH('01 — Editable assumptions — USD'!B61),1)),DATE(2027,12,1)=DATE(YEAR('01 — Editable assumptions — USD'!B61),MONTH('01 — Editable assumptions — USD'!B61),1),IF(DATE(YEAR('01 — Editable assumptions — USD'!B61),MONTH('01 — Editable assumptions — USD'!B61),1)="","",DATE(2027,12,1)=DATE(YEAR('01 — Editable assumptions — USD'!B61),MONTH('01 — Editable assumptions — USD'!B61),1)))="",FALSE,IF(ISERROR(DATE(2027,12,1)=DATE(YEAR('01 — Editable assumptions — USD'!B61),MONTH('01 — Editable assumptions — USD'!B61),1)),DATE(2027,12,1)=DATE(YEAR('01 — Editable assumptions — USD'!B61),MONTH('01 — Editable assumptions — USD'!B61),1),IF(DATE(YEAR('01 — Editable assumptions — USD'!B61),MONTH('01 — Editable assumptions — USD'!B61),1)="","",DATE(2027,12,1)=DATE(YEAR('01 — Editable assumptions — USD'!B61),MONTH('01 — Editable assumptions — USD'!B61),1)))),IF('04 — Scenario comparison — Base'!B24="","",'04 — Scenario comparison — Base'!B24),IF('07 — Cash projection — hypothet'!O11="","",'07 — Cash projection — hypothet'!O11)))+'07 — Cash projection — hypothet'!P9 -> -37366.28
